Workbook
Name DT_AVGCharge: #REF!
Name DT_AVGSalary: #REF!
Name DT_ClientName: #REF!
Name DT_Ex_Curr_Rate: #REF!
Name DT_WorkDaysPA: #REF!
Name Possibility: #REF!

Sheet Summary
B2: Summary People Stats
R4: Leavers | S4: =DATE(YEAR(S$5), MONTH(S$5), 1) -> 45444 | T4: =DATE(YEAR(T$5), MONTH(T$5), 1) -> 45474 | U4: =DATE(YEAR(U$5), MONTH(U$5), 1) -> 45505 | V4: =DATE(YEAR(V$5), MONTH(V$5), 1) -> 45536 | W4: =DATE(YEAR(W$5), MONTH(W$5), 1) -> 45566 | X4: =DATE(YEAR(X$5), MONTH(X$5), 1) -> 45597 | Y4: =DATE(YEAR(Y$5), MONTH(Y$5), 1) -> 45627 | Z4: =DATE(YEAR(Z$5), MONTH(Z$5), 1) -> 45658 | ... BI4: =DATE(YEAR(BI$5), MONTH(BI$5), 1) -> 1
B5: Summary by business unit - Previous Month End | H5: Summary by business unit - LIVE | R5: Business Unit | S5: 30/06/2024 | T5: 31/07/2024 | U5: 31/08/2024 | V5: 30/09/2024 | W5: 31/10/2024 | X5: 30/11/2024 | Y5: 31/12/2024 | Z5: 30/01/2025 | AA5: 28/02/2025 | AB5: 31/03/2025 | AC5: 30/04/2025 | AD5: 31/05/2025 | AE5: 30/06/2025 | AF5: 31/07/2025 | AG5: 31/08/2025 | AH5: 30/09/2025 | AI5: 31/10/2025 | AJ5: 30/11/2025 | AK5: 31/12/2025 | AL5: 30/01/2026 | AM5: 28/02/2026 | AN5: 31/03/2026 | AO5: 30/04/2026 | AP5: 31/05/2026 | AQ5: 30/06/2026 | AR5: 31/07/2026 | AS5: 31/08/2026 | AT5: 30/09/2026 | AU5: 31/10/2026 | AV5: 30/11/2026 | AW5: 31/12/2026 | AX5: 30/01/2027 | AY5: 28/02/2027 | AZ5: 31/03/2027 | BA5: 30/04/2027 | BB5: 31/05/2027 | BC5: 30/06/2027 | BD5: 31/07/2027 | BE5: 31/08/2027 | BF5: 30/09/2027 | BG5: 31/10/2027
R6: Engineering | S6: 1 | T6: 0 | U6: 0 | V6: 0 | W6: 3 | Y6: 1 | AA6: 1 | AC6: 1 | AE6: 1 | AF6: =SUMIFS('Regional allocations LIVE'!$T:$T, 'Regional allocations LIVE'!$H:$H, $R6, 'Regional allocations LIVE'!$R:$R, ">=" & AF$4, 'Regional allocations LIVE'!$R:$R, "<=" & Table14[[#Headers],[31/07/2025]] ) -> 1 | AG6: =SUMIFS('Regional allocations LIVE'!$T:$T, 'Regional allocations LIVE'!$H:$H, $R6, 'Regional allocations LIVE'!$R:$R, ">=" & AG$4, 'Regional allocations LIVE'!$R:$R, "<=" & Table14[[#Headers],[31/08/2025]] ) -> 1 | AH6: =SUMIFS('Regional allocations LIVE'!$T:$T, 'Regional allocations LIVE'!$H:$H, $R6, 'Regional allocations LIVE'!$R:$R, ">=" & AH$4, 'Regional allocations LIVE'!$R:$R, "<=" & Table14[[#Headers],[30/09/2025]] ) -> 1.8 | AI6: =SUMIFS('Regional allocations LIVE'!$T:$T, 'Regional allocations LIVE'!$H:$H, $R6, 'Regional allocations LIVE'!$R:$R, ">=" & AI$4, 'Regional allocations LIVE'!$R:$R, "<=" & Table14[[#Headers],[31/10/2025]] ) -> 0 | AJ6: =SUMIFS('Regional allocations LIVE'!$T:$T, 'Regional allocations LIVE'!$H:$H, $R6, 'Regional allocations LIVE'!$R:$R, ">=" & AJ$4, 'Regional allocations LIVE'!$R:$R, "<=" & Table14[[#Headers],[30/11/2025]] ) -> 0 | AK6: =SUMIFS('Regional allocations LIVE'!$T:$T, 'Regional allocations LIVE'!$H:$H, $R6, 'Regional allocations LIVE'!$R:$R, ">=" & AK$4, 'Regional allocations LIVE'!$R:$R, "<=" & Table14[[#Headers],[31/12/2025]] ) -> 0 | AL6: =SUMIFS('Regional allocations LIVE'!$T:$T, 'Regional allocations LIVE'!$H:$H, $R6, 'Regional allocations LIVE'!$R:$R, ">=" & AL$4, 'Regional allocations LIVE'!$R:$R, "<=" & Table14[[#Headers],[30/01/2026]] ) -> 0 | AM6: =SUMIFS('Regional allocations LIVE'!$T:$T, 'Regional allocations LIVE'!$H:$H, $R6, 'Regional allocations LIVE'!$R:$R, ">=" & AM$4, 'Regional allocations LIVE'!$R:$R, "<=" & Table14[[#Headers],[28/02/2026]] ) -> 0 | AN6: =SUMIFS('Regional allocations LIVE'!$T:$T, 'Regional allocations LIVE'!$H:$H, $R6, 'Regional allocations LIVE'!$R:$R, ">=" & AN$4, 'Regional allocations LIVE'!$R:$R, "<=" & Table14[[#Headers],[31/03/2026]] ) -> 0 | AO6: =SUMIFS('Regional allocations LIVE'!$T:$T, 'Regional allocations LIVE'!$H:$H, $R6, 'Regional allocations LIVE'!$R:$R, ">=" & AO$4, 'Regional allocations LIVE'!$R:$R, "<=" & Table14[[#Headers],[30/04/2026]] ) -> 0 | AP6: =SUMIFS('Regional allocations LIVE'!$T:$T, 'Regional allocations LIVE'!$H:$H, $R6, 'Regional allocations LIVE'!$R:$R, ">=" & AP$4, 'Regional allocations LIVE'!$R:$R, "<=" & Table14[[#Headers],[31/05/2026]] ) -> 0 | AQ6: =SUMIFS('Regional allocations LIVE'!$T:$T, 'Regional allocations LIVE'!$H:$H, $R6, 'Regional allocations LIVE'!$R:$R, ">=" & AQ$4, 'Regional allocations LIVE'!$R:$R, "<=" & Table14[[#Headers],[30/06/2026]] ) -> 0 | AR6: =SUMIFS('Regional allocations LIVE'!$T:$T, 'Regional allocations LIVE'!$H:$H, $R6, 'Regional allocations LIVE'!$R:$R, ">=" & AR$4, 'Regional allocations LIVE'!$R:$R, "<=" & Table14[[#Headers],[31/07/2026]] ) -> 0 | AS6: =SUMIFS('Regional allocations LIVE'!$T:$T, 'Regional allocations LIVE'!$H:$H, $R6, 'Regional allocations LIVE'!$R:$R, ">=" & AS$4, 'Regional allocations LIVE'!$R:$R, "<=" & Table14[[#Headers],[31/08/2026]] ) -> 0 | AT6: =SUMIFS('Regional allocations LIVE'!$T:$T, 'Regional allocations LIVE'!$H:$H, $R6, 'Regional allocations LIVE'!$R:$R, ">=" & AT$4, 'Regional allocations LIVE'!$R:$R, "<=" & Table14[[#Headers],[30/09/2026]] ) -> 0 | AU6: =SUMIFS('Regional allocations LIVE'!$T:$T, 'Regional allocations LIVE'!$H:$H, $R6, 'Regional allocations LIVE'!$R:$R, ">=" & AU$4, 'Regional allocations LIVE'!$R:$R, "<=" & Table14[[#Headers],[31/10/2026]] ) -> 0 | AV6: =SUMIFS('Regional allocations LIVE'!$T:$T, 'Regional allocations LIVE'!$H:$H, $R6, 'Regional allocations LIVE'!$R:$R, ">=" & AV$4, 'Regional allocations LIVE'!$R:$R, "<=" & Table14[[#Headers],[30/11/2026]] ) -> 0 | AW6: =SUMIFS('Regional allocations LIVE'!$T:$T, 'Regional allocations LIVE'!$H:$H, $R6, 'Regional allocations LIVE'!$R:$R, ">=" & AW$4, 'Regional allocations LIVE'!$R:$R, "<=" & Table14[[#Headers],[31/12/2026]] ) -> 0 | AX6: =SUMIFS('Regional allocations LIVE'!$T:$T, 'Regional allocations LIVE'!$H:$H, $R6, 'Regional allocations LIVE'!$R:$R, ">=" & AX$4, 'Regional allocations LIVE'!$R:$R, "<=" & Table14[[#Headers],[30/01/2027]] ) -> 0 | AY6: =SUMIFS('Regional allocations LIVE'!$T:$T, 'Regional allocations LIVE'!$H:$H, $R6, 'Regional allocations LIVE'!$R:$R, ">=" & AY$4, 'Regional allocations LIVE'!$R:$R, "<=" & Table14[[#Headers],[28/02/2027]] ) -> 0 | AZ6: =SUMIFS('Regional allocations LIVE'!$T:$T, 'Regional allocations LIVE'!$H:$H, $R6, 'Regional allocations LIVE'!$R:$R, ">=" & AZ$4, 'Regional allocations LIVE'!$R:$R, "<=" & Table14[[#Headers],[31/03/2027]] ) -> 0 | BA6: =SUMIFS('Regional allocations LIVE'!$T:$T, 'Regional allocations LIVE'!$H:$H, $R6, 'Regional allocations LIVE'!$R:$R, ">=" & BA$4, 'Regional allocations LIVE'!$R:$R, "<=" & Table14[[#Headers],[30/04/2027]] ) -> 0 | BB6: =SUMIFS('Regional allocations LIVE'!$T:$T, 'Regional allocations LIVE'!$H:$H, $R6, 'Regional allocations LIVE'!$R:$R, ">=" & BB$4, 'Regional allocations LIVE'!$R:$R, "<=" & Table14[[#Headers],[31/05/2027]] ) -> 0 | BC6: =SUMIFS('Regional allocations LIVE'!$T:$T, 'Regional allocations LIVE'!$H:$H, $R6, 'Regional allocations LIVE'!$R:$R, ">=" & BC$4, 'Regional allocations LIVE'!$R:$R, "<=" & Table14[[#Headers],[30/06/2027]] ) -> 0 | BD6: =SUMIFS('Regional allocations LIVE'!$T:$T, 'Regional allocations LIVE'!$H:$H, $R6, 'Regional allocations LIVE'!$R:$R, ">=" & BD$4, 'Regional allocations LIVE'!$R:$R, "<=" & Table14[[#Headers],[31/07/2027]] ) -> 0 | BE6: =SUMIFS('Regional allocations LIVE'!$T:$T, 'Regional allocations LIVE'!$H:$H, $R6, 'Regional allocations LIVE'!$R:$R, ">=" & BE$4, 'Regional allocations LIVE'!$R:$R, "<=" & Table14[[#Headers],[31/08/2027]] ) -> 0 | BF6: =SUMIFS('Regional allocations LIVE'!$T:$T, 'Regional allocations LIVE'!$H:$H, $R6, 'Regional allocations LIVE'!$R:$R, ">=" & BF$4, 'Regional allocations LIVE'!$R:$R, "<=" & Table14[[#Headers],[30/09/2027]] ) -> 0 | BG6: =SUMIFS('Regional allocations LIVE'!$T:$T, 'Regional allocations LIVE'!$H:$H, $R6, 'Regional allocations LIVE'!$R:$R, ">=" & BG$4, 'Regional allocations LIVE'!$R:$R, "<=" & Table14[[#Headers],[31/10/2027]] ) -> 0
B7: Business Unit | C7: Headcount | E7: Regional Headcount | H7: Business Unit | I7: Headcount | J7: Vaccancies to backfill | K7: Vaccancies for new roles | L7: Increase headcount roles TBC | M7: Contractors | N7: Perm Headcount (minus contractors) | O7: Perm with Vaccancies filled | R7: Sales | S7: 0 | T7: 0 | U7: 0 | V7: 1 | W7: 0 | AF7: =SUMIFS('Regional allocations LIVE'!$T:$T, 'Regional allocations LIVE'!$H:$H, $R7, 'Regional allocations LIVE'!$R:$R, ">=" & AF$4, 'Regional allocations LIVE'!$R:$R, "<=" & Table14[[#Headers],[31/07/2025]] ) -> 0 | AG7: =SUMIFS('Regional allocations LIVE'!$T:$T, 'Regional allocations LIVE'!$H:$H, $R7, 'Regional allocations LIVE'!$R:$R, ">=" & AG$4, 'Regional allocations LIVE'!$R:$R, "<=" & Table14[[#Headers],[31/08/2025]] ) -> 0 | AH7: =SUMIFS('Regional allocations LIVE'!$T:$T, 'Regional allocations LIVE'!$H:$H, $R7, 'Regional allocations LIVE'!$R:$R, ">=" & AH$4, 'Regional allocations LIVE'!$R:$R, "<=" & Table14[[#Headers],[30/09/2025]] ) -> 0 | AI7: =SUMIFS('Regional allocations LIVE'!$T:$T, 'Regional allocations LIVE'!$H:$H, $R7, 'Regional allocations LIVE'!$R:$R, ">=" & AI$4, 'Regional allocations LIVE'!$R:$R, "<=" & Table14[[#Headers],[31/10/2025]] ) -> 0 | AJ7: =SUMIFS('Regional allocations LIVE'!$T:$T, 'Regional allocations LIVE'!$H:$H, $R7, 'Regional allocations LIVE'!$R:$R, ">=" & AJ$4, 'Regional allocations LIVE'!$R:$R, "<=" & Table14[[#Headers],[30/11/2025]] ) -> 0 | AK7: =SUMIFS('Regional allocations LIVE'!$T:$T, 'Regional allocations LIVE'!$H:$H, $R7, 'Regional allocations LIVE'!$R:$R, ">=" & AK$4, 'Regional allocations LIVE'!$R:$R, "<=" & Table14[[#Headers],[31/12/2025]] ) -> 0 | AL7: =SUMIFS('Regional allocations LIVE'!$T:$T, 'Regional allocations LIVE'!$H:$H, $R7, 'Regional allocations LIVE'!$R:$R, ">=" & AL$4, 'Regional allocations LIVE'!$R:$R, "<=" & Table14[[#Headers],[30/01/2026]] ) -> 0 | AM7: =SUMIFS('Regional allocations LIVE'!$T:$T, 'Regional allocations LIVE'!$H:$H, $R7, 'Regional allocations LIVE'!$R:$R, ">=" & AM$4, 'Regional allocations LIVE'!$R:$R, "<=" & Table14[[#Headers],[28/02/2026]] ) -> 0 | AN7: =SUMIFS('Regional allocations LIVE'!$T:$T, 'Regional allocations LIVE'!$H:$H, $R7, 'Regional allocations LIVE'!$R:$R, ">=" & AN$4, 'Regional allocations LIVE'!$R:$R, "<=" & Table14[[#Headers],[31/03/2026]] ) -> 0 | AO7: =SUMIFS('Regional allocations LIVE'!$T:$T, 'Regional allocations LIVE'!$H:$H, $R7, 'Regional allocations LIVE'!$R:$R, ">=" & AO$4, 'Regional allocations LIVE'!$R:$R, "<=" & Table14[[#Headers],[30/04/2026]] ) -> 0 | AP7: =SUMIFS('Regional allocations LIVE'!$T:$T, 'Regional allocations LIVE'!$H:$H, $R7, 'Regional allocations LIVE'!$R:$R, ">=" & AP$4, 'Regional allocations LIVE'!$R:$R, "<=" & Table14[[#Headers],[31/05/2026]] ) -> 0 | AQ7: =SUMIFS('Regional allocations LIVE'!$T:$T, 'Regional allocations LIVE'!$H:$H, $R7, 'Regional allocations LIVE'!$R:$R, ">=" & AQ$4, 'Regional allocations LIVE'!$R:$R, "<=" & Table14[[#Headers],[30/06/2026]] ) -> 0 | AR7: =SUMIFS('Regional allocations LIVE'!$T:$T, 'Regional allocations LIVE'!$H:$H, $R7, 'Regional allocations LIVE'!$R:$R, ">=" & AR$4, 'Regional allocations LIVE'!$R:$R, "<=" & Table14[[#Headers],[31/07/2026]] ) -> 0 | AS7: =SUMIFS('Regional allocations LIVE'!$T:$T, 'Regional allocations LIVE'!$H:$H, $R7, 'Regional allocations LIVE'!$R:$R, ">=" & AS$4, 'Regional allocations LIVE'!$R:$R, "<=" & Table14[[#Headers],[31/08/2026]] ) -> 0 | AT7: =SUMIFS('Regional allocations LIVE'!$T:$T, 'Regional allocations LIVE'!$H:$H, $R7, 'Regional allocations LIVE'!$R:$R, ">=" & AT$4, 'Regional allocations LIVE'!$R:$R, "<=" & Table14[[#Headers],[30/09/2026]] ) -> 0 | AU7: =SUMIFS('Regional allocations LIVE'!$T:$T, 'Regional allocations LIVE'!$H:$H, $R7, 'Regional allocations LIVE'!$R:$R, ">=" & AU$4, 'Regional allocations LIVE'!$R:$R, "<=" & Table14[[#Headers],[31/10/2026]] ) -> 0 | AV7: =SUMIFS('Regional allocations LIVE'!$T:$T, 'Regional allocations LIVE'!$H:$H, $R7, 'Regional allocations LIVE'!$R:$R, ">=" & AV$4, 'Regional allocations LIVE'!$R:$R, "<=" & Table14[[#Headers],[30/11/2026]] ) -> 0 | AW7: =SUMIFS('Regional allocations LIVE'!$T:$T, 'Regional allocations LIVE'!$H:$H, $R7, 'Regional allocations LIVE'!$R:$R, ">=" & AW$4, 'Regional allocations LIVE'!$R:$R, "<=" & Table14[[#Headers],[31/12/2026]] ) -> 0 | AX7: =SUMIFS('Regional allocations LIVE'!$T:$T, 'Regional allocations LIVE'!$H:$H, $R7, 'Regional allocations LIVE'!$R:$R, ">=" & AX$4, 'Regional allocations LIVE'!$R:$R, "<=" & Table14[[#Headers],[30/01/2027]] ) -> 0 | AY7: =SUMIFS('Regional allocations LIVE'!$T:$T, 'Regional allocations LIVE'!$H:$H, $R7, 'Regional allocations LIVE'!$R:$R, ">=" & AY$4, 'Regional allocations LIVE'!$R:$R, "<=" & Table14[[#Headers],[28/02/2027]] ) -> 0 | AZ7: =SUMIFS('Regional allocations LIVE'!$T:$T, 'Regional allocations LIVE'!$H:$H, $R7, 'Regional allocations LIVE'!$R:$R, ">=" & AZ$4, 'Regional allocations LIVE'!$R:$R, "<=" & Table14[[#Headers],[31/03/2027]] ) -> 0 | BA7: =SUMIFS('Regional allocations LIVE'!$T:$T, 'Regional allocations LIVE'!$H:$H, $R7, 'Regional allocations LIVE'!$R:$R, ">=" & BA$4, 'Regional allocations LIVE'!$R:$R, "<=" & Table14[[#Headers],[30/04/2027]] ) -> 0 | BB7: =SUMIFS('Regional allocations LIVE'!$T:$T, 'Regional allocations LIVE'!$H:$H, $R7, 'Regional allocations LIVE'!$R:$R, ">=" & BB$4, 'Regional allocations LIVE'!$R:$R, "<=" & Table14[[#Headers],[31/05/2027]] ) -> 0 | BC7: =SUMIFS('Regional allocations LIVE'!$T:$T, 'Regional allocations LIVE'!$H:$H, $R7, 'Regional allocations LIVE'!$R:$R, ">=" & BC$4, 'Regional allocations LIVE'!$R:$R, "<=" & Table14[[#Headers],[30/06/2027]] ) -> 0 | BD7: =SUMIFS('Regional allocations LIVE'!$T:$T, 'Regional allocations LIVE'!$H:$H, $R7, 'Regional allocations LIVE'!$R:$R, ">=" & BD$4, 'Regional allocations LIVE'!$R:$R, "<=" & Table14[[#Headers],[31/07/2027]] ) -> 0 | BE7: =SUMIFS('Regional allocations LIVE'!$T:$T, 'Regional allocations LIVE'!$H:$H, $R7, 'Regional allocations LIVE'!$R:$R, ">=" & BE$4, 'Regional allocations LIVE'!$R:$R, "<=" & Table14[[#Headers],[31/08/2027]] ) -> 0 | BF7: =SUMIFS('Regional allocations LIVE'!$T:$T, 'Regional allocations LIVE'!$H:$H, $R7, 'Regional allocations LIVE'!$R:$R, ">=" & BF$4, 'Regional allocations LIVE'!$R:$R, "<=" & Table14[[#Headers],[30/09/2027]] ) -> 0 | BG7: =SUMIFS('Regional allocations LIVE'!$T:$T, 'Regional allocations LIVE'!$H:$H, $R7, 'Regional allocations LIVE'!$R:$R, ">=" & BG$4, 'Regional allocations LIVE'!$R:$R, "<=" & Table14[[#Headers],[31/10/2027]] ) -> 0
B8: Engineering | C8: =AD40 -> 42.2 | E8: =C11+C12+C14+3 -> 108.55 | H8: Engineering | I8: =COUNTIFS('Regional allocations LIVE'!H:H,Table1116[[#This Row],[Business Unit]],'Regional allocations LIVE'!R:R,"") -> 36 | J8: 4 | L8: 3 | M8: =COUNTIFS('Regional allocations LIVE'!H:H,Table1116[[#This Row],[Business Unit]],'Regional allocations LIVE'!U:U,"Y",'Regional allocations LIVE'!R:R,"") -> 1 | N8: =Table1116[[#This Row],[Headcount]]-Table1116[[#This Row],[Contractors]] -> 35 | O8: =Table1116[[#This Row],[Perm Headcount (minus contractors)]]+Table1116[[#This Row],[Vaccancies to backfill]]+Table1116[[#This Row],[Vaccancies for new roles]] -> 39 | R8: Shared Services | S8: 0 | T8: 1 | U8: 0 | V8: 1 | W8: 0 | Z8: 1 | AC8: 1 | AF8: =SUMIFS('Regional allocations LIVE'!$T:$T, 'Regional allocations LIVE'!$H:$H, $R8, 'Regional allocations LIVE'!$R:$R, ">=" & AF$4, 'Regional allocations LIVE'!$R:$R, "<=" & Table14[[#Headers],[31/07/2025]] ) -> 0 | AG8: =SUMIFS('Regional allocations LIVE'!$T:$T, 'Regional allocations LIVE'!$H:$H, $R8, 'Regional allocations LIVE'!$R:$R, ">=" & AG$4, 'Regional allocations LIVE'!$R:$R, "<=" & Table14[[#Headers],[31/08/2025]] ) -> 0 | AH8: =SUMIFS('Regional allocations LIVE'!$T:$T, 'Regional allocations LIVE'!$H:$H, $R8, 'Regional allocations LIVE'!$R:$R, ">=" & AH$4, 'Regional allocations LIVE'!$R:$R, "<=" & Table14[[#Headers],[30/09/2025]] ) -> 0 | AI8: =SUMIFS('Regional allocations LIVE'!$T:$T, 'Regional allocations LIVE'!$H:$H, $R8, 'Regional allocations LIVE'!$R:$R, ">=" & AI$4, 'Regional allocations LIVE'!$R:$R, "<=" & Table14[[#Headers],[31/10/2025]] ) -> 0 | AJ8: =SUMIFS('Regional allocations LIVE'!$T:$T, 'Regional allocations LIVE'!$H:$H, $R8, 'Regional allocations LIVE'!$R:$R, ">=" & AJ$4, 'Regional allocations LIVE'!$R:$R, "<=" & Table14[[#Headers],[30/11/2025]] ) -> 0 | AK8: =SUMIFS('Regional allocations LIVE'!$T:$T, 'Regional allocations LIVE'!$H:$H, $R8, 'Regional allocations LIVE'!$R:$R, ">=" & AK$4, 'Regional allocations LIVE'!$R:$R, "<=" & Table14[[#Headers],[31/12/2025]] ) -> 0 | AL8: =SUMIFS('Regional allocations LIVE'!$T:$T, 'Regional allocations LIVE'!$H:$H, $R8, 'Regional allocations LIVE'!$R:$R, ">=" & AL$4, 'Regional allocations LIVE'!$R:$R, "<=" & Table14[[#Headers],[30/01/2026]] ) -> 0 | AM8: =SUMIFS('Regional allocations LIVE'!$T:$T, 'Regional allocations LIVE'!$H:$H, $R8, 'Regional allocations LIVE'!$R:$R, ">=" & AM$4, 'Regional allocations LIVE'!$R:$R, "<=" & Table14[[#Headers],[28/02/2026]] ) -> 0 | AN8: =SUMIFS('Regional allocations LIVE'!$T:$T, 'Regional allocations LIVE'!$H:$H, $R8, 'Regional allocations LIVE'!$R:$R, ">=" & AN$4, 'Regional allocations LIVE'!$R:$R, "<=" & Table14[[#Headers],[31/03/2026]] ) -> 0 | AO8: =SUMIFS('Regional allocations LIVE'!$T:$T, 'Regional allocations LIVE'!$H:$H, $R8, 'Regional allocations LIVE'!$R:$R, ">=" & AO$4, 'Regional allocations LIVE'!$R:$R, "<=" & Table14[[#Headers],[30/04/2026]] ) -> 0 | AP8: =SUMIFS('Regional allocations LIVE'!$T:$T, 'Regional allocations LIVE'!$H:$H, $R8, 'Regional allocations LIVE'!$R:$R, ">=" & AP$4, 'Regional allocations LIVE'!$R:$R, "<=" & Table14[[#Headers],[31/05/2026]] ) -> 0 | AQ8: =SUMIFS('Regional allocations LIVE'!$T:$T, 'Regional allocations LIVE'!$H:$H, $R8, 'Regional allocations LIVE'!$R:$R, ">=" & AQ$4, 'Regional allocations LIVE'!$R:$R, "<=" & Table14[[#Headers],[30/06/2026]] ) -> 0 | AR8: =SUMIFS('Regional allocations LIVE'!$T:$T, 'Regional allocations LIVE'!$H:$H, $R8, 'Regional allocations LIVE'!$R:$R, ">=" & AR$4, 'Regional allocations LIVE'!$R:$R, "<=" & Table14[[#Headers],[31/07/2026]] ) -> 0 | AS8: =SUMIFS('Regional allocations LIVE'!$T:$T, 'Regional allocations LIVE'!$H:$H, $R8, 'Regional allocations LIVE'!$R:$R, ">=" & AS$4, 'Regional allocations LIVE'!$R:$R, "<=" & Table14[[#Headers],[31/08/2026]] ) -> 0 | AT8: =SUMIFS('Regional allocations LIVE'!$T:$T, 'Regional allocations LIVE'!$H:$H, $R8, 'Regional allocations LIVE'!$R:$R, ">=" & AT$4, 'Regional allocations LIVE'!$R:$R, "<=" & Table14[[#Headers],[30/09/2026]] ) -> 0 | AU8: =SUMIFS('Regional allocations LIVE'!$T:$T, 'Regional allocations LIVE'!$H:$H, $R8, 'Regional allocations LIVE'!$R:$R, ">=" & AU$4, 'Regional allocations LIVE'!$R:$R, "<=" & Table14[[#Headers],[31/10/2026]] ) -> 0 | AV8: =SUMIFS('Regional allocations LIVE'!$T:$T, 'Regional allocations LIVE'!$H:$H, $R8, 'Regional allocations LIVE'!$R:$R, ">=" & AV$4, 'Regional allocations LIVE'!$R:$R, "<=" & Table14[[#Headers],[30/11/2026]] ) -> 0 | AW8: =SUMIFS('Regional allocations LIVE'!$T:$T, 'Regional allocations LIVE'!$H:$H, $R8, 'Regional allocations LIVE'!$R:$R, ">=" & AW$4, 'Regional allocations LIVE'!$R:$R, "<=" & Table14[[#Headers],[31/12/2026]] ) -> 0 | AX8: =SUMIFS('Regional allocations LIVE'!$T:$T, 'Regional allocations LIVE'!$H:$H, $R8, 'Regional allocations LIVE'!$R:$R, ">=" & AX$4, 'Regional allocations LIVE'!$R:$R, "<=" & Table14[[#Headers],[30/01/2027]] ) -> 0 | AY8: =SUMIFS('Regional allocations LIVE'!$T:$T, 'Regional allocations LIVE'!$H:$H, $R8, 'Regional allocations LIVE'!$R:$R, ">=" & AY$4, 'Regional allocations LIVE'!$R:$R, "<=" & Table14[[#Headers],[28/02/2027]] ) -> 0 | AZ8: =SUMIFS('Regional allocations LIVE'!$T:$T, 'Regional allocations LIVE'!$H:$H, $R8, 'Regional allocations LIVE'!$R:$R, ">=" & AZ$4, 'Regional allocations LIVE'!$R:$R, "<=" & Table14[[#Headers],[31/03/2027]] ) -> 0 | BA8: =SUMIFS('Regional allocations LIVE'!$T:$T, 'Regional allocations LIVE'!$H:$H, $R8, 'Regional allocations LIVE'!$R:$R, ">=" & BA$4, 'Regional allocations LIVE'!$R:$R, "<=" & Table14[[#Headers],[30/04/2027]] ) -> 0 | BB8: =SUMIFS('Regional allocations LIVE'!$T:$T, 'Regional allocations LIVE'!$H:$H, $R8, 'Regional allocations LIVE'!$R:$R, ">=" & BB$4, 'Regional allocations LIVE'!$R:$R, "<=" & Table14[[#Headers],[31/05/2027]] ) -> 0 | BC8: =SUMIFS('Regional allocations LIVE'!$T:$T, 'Regional allocations LIVE'!$H:$H, $R8, 'Regional allocations LIVE'!$R:$R, ">=" & BC$4, 'Regional allocations LIVE'!$R:$R, "<=" & Table14[[#Headers],[30/06/2027]] ) -> 0 | BD8: =SUMIFS('Regional allocations LIVE'!$T:$T, 'Regional allocations LIVE'!$H:$H, $R8, 'Regional allocations LIVE'!$R:$R, ">=" & BD$4, 'Regional allocations LIVE'!$R:$R, "<=" & Table14[[#Headers],[31/07/2027]] ) -> 0 | BE8: =SUMIFS('Regional allocations LIVE'!$T:$T, 'Regional allocations LIVE'!$H:$H, $R8, 'Regional allocations LIVE'!$R:$R, ">=" & BE$4, 'Regional allocations LIVE'!$R:$R, "<=" & Table14[[#Headers],[31/08/2027]] ) -> 0 | BF8: =SUMIFS('Regional allocations LIVE'!$T:$T, 'Regional allocations LIVE'!$H:$H, $R8, 'Regional allocations LIVE'!$R:$R, ">=" & BF$4, 'Regional allocations LIVE'!$R:$R, "<=" & Table14[[#Headers],[30/09/2027]] ) -> 0 | BG8: =SUMIFS('Regional allocations LIVE'!$T:$T, 'Regional allocations LIVE'!$H:$H, $R8, 'Regional allocations LIVE'!$R:$R, ">=" & BG$4, 'Regional allocations LIVE'!$R:$R, "<=" & Table14[[#Headers],[31/10/2027]] ) -> 0
B9: Sales | C9: =AD41 -> 3 | H9: Sales | I9: =COUNTIFS('Regional allocations LIVE'!H:H,Table1116[[#This Row],[Business Unit]],'Regional allocations LIVE'!R:R,"") -> 5 | J9: 1 | K9: 1 | M9: =COUNTIFS('Regional allocations LIVE'!H:H,Table1116[[#This Row],[Business Unit]],'Regional allocations LIVE'!U:U,"Y",'Regional allocations LIVE'!R:R,"") -> 1 | N9: =Table1116[[#This Row],[Headcount]]-Table1116[[#This Row],[Contractors]] -> 4 | O9: =Table1116[[#This Row],[Perm Headcount (minus contractors)]]+Table1116[[#This Row],[Vaccancies to backfill]]+Table1116[[#This Row],[Vaccancies for new roles]] -> 6 | R9: Europe | S9: 2 | T9: 1 | U9: 1 | V9: 0 | W9: 1 | X9: 1 | Z9: 1 | AA9: 1 | AB9: 1 | AC9: 1 | AD9: 1 | AE9: 2 | AF9: =SUMIFS('Regional allocations LIVE'!$T:$T, 'Regional allocations LIVE'!$H:$H, $R9, 'Regional allocations LIVE'!$R:$R, ">=" & AF$4, 'Regional allocations LIVE'!$R:$R, "<=" & Table14[[#Headers],[31/07/2025]] ) -> 0 | AG9: =SUMIFS('Regional allocations LIVE'!$T:$T, 'Regional allocations LIVE'!$H:$H, $R9, 'Regional allocations LIVE'!$R:$R, ">=" & AG$4, 'Regional allocations LIVE'!$R:$R, "<=" & Table14[[#Headers],[31/08/2025]] ) -> 0 | AH9: =SUMIFS('Regional allocations LIVE'!$T:$T, 'Regional allocations LIVE'!$H:$H, $R9, 'Regional allocations LIVE'!$R:$R, ">=" & AH$4, 'Regional allocations LIVE'!$R:$R, "<=" & Table14[[#Headers],[30/09/2025]] ) -> 0 | AI9: =SUMIFS('Regional allocations LIVE'!$T:$T, 'Regional allocations LIVE'!$H:$H, $R9, 'Regional allocations LIVE'!$R:$R, ">=" & AI$4, 'Regional allocations LIVE'!$R:$R, "<=" & Table14[[#Headers],[31/10/2025]] ) -> 1 | AJ9: =SUMIFS('Regional allocations LIVE'!$T:$T, 'Regional allocations LIVE'!$H:$H, $R9, 'Regional allocations LIVE'!$R:$R, ">=" & AJ$4, 'Regional allocations LIVE'!$R:$R, "<=" & Table14[[#Headers],[30/11/2025]] ) -> 0 | AK9: =SUMIFS('Regional allocations LIVE'!$T:$T, 'Regional allocations LIVE'!$H:$H, $R9, 'Regional allocations LIVE'!$R:$R, ">=" & AK$4, 'Regional allocations LIVE'!$R:$R, "<=" & Table14[[#Headers],[31/12/2025]] ) -> 0 | AL9: =SUMIFS('Regional allocations LIVE'!$T:$T, 'Regional allocations LIVE'!$H:$H, $R9, 'Regional allocations LIVE'!$R:$R, ">=" & AL$4, 'Regional allocations LIVE'!$R:$R, "<=" & Table14[[#Headers],[30/01/2026]] ) -> 0 | AM9: =SUMIFS('Regional allocations LIVE'!$T:$T, 'Regional allocations LIVE'!$H:$H, $R9, 'Regional allocations LIVE'!$R:$R, ">=" & AM$4, 'Regional allocations LIVE'!$R:$R, "<=" & Table14[[#Headers],[28/02/2026]] ) -> 0 | AN9: =SUMIFS('Regional allocations LIVE'!$T:$T, 'Regional allocations LIVE'!$H:$H, $R9, 'Regional allocations LIVE'!$R:$R, ">=" & AN$4, 'Regional allocations LIVE'!$R:$R, "<=" & Table14[[#Headers],[31/03/2026]] ) -> 0 | AO9: =SUMIFS('Regional allocations LIVE'!$T:$T, 'Regional allocations LIVE'!$H:$H, $R9, 'Regional allocations LIVE'!$R:$R, ">=" & AO$4, 'Regional allocations LIVE'!$R:$R, "<=" & Table14[[#Headers],[30/04/2026]] ) -> 0 | AP9: =SUMIFS('Regional allocations LIVE'!$T:$T, 'Regional allocations LIVE'!$H:$H, $R9, 'Regional allocations LIVE'!$R:$R, ">=" & AP$4, 'Regional allocations LIVE'!$R:$R, "<=" & Table14[[#Headers],[31/05/2026]] ) -> 0 | AQ9: =SUMIFS('Regional allocations LIVE'!$T:$T, 'Regional allocations LIVE'!$H:$H, $R9, 'Regional allocations LIVE'!$R:$R, ">=" & AQ$4, 'Regional allocations LIVE'!$R:$R, "<=" & Table14[[#Headers],[30/06/2026]] ) -> 0 | AR9: =SUMIFS('Regional allocations LIVE'!$T:$T, 'Regional allocations LIVE'!$H:$H, $R9, 'Regional allocations LIVE'!$R:$R, ">=" & AR$4, 'Regional allocations LIVE'!$R:$R, "<=" & Table14[[#Headers],[31/07/2026]] ) -> 0 | AS9: =SUMIFS('Regional allocations LIVE'!$T:$T, 'Regional allocations LIVE'!$H:$H, $R9, 'Regional allocations LIVE'!$R:$R, ">=" & AS$4, 'Regional allocations LIVE'!$R:$R, "<=" & Table14[[#Headers],[31/08/2026]] ) -> 0 | AT9: =SUMIFS('Regional allocations LIVE'!$T:$T, 'Regional allocations LIVE'!$H:$H, $R9, 'Regional allocations LIVE'!$R:$R, ">=" & AT$4, 'Regional allocations LIVE'!$R:$R, "<=" & Table14[[#Headers],[30/09/2026]] ) -> 0 | AU9: =SUMIFS('Regional allocations LIVE'!$T:$T, 'Regional allocations LIVE'!$H:$H, $R9, 'Regional allocations LIVE'!$R:$R, ">=" & AU$4, 'Regional allocations LIVE'!$R:$R, "<=" & Table14[[#Headers],[31/10/2026]] ) -> 0 | AV9: =SUMIFS('Regional allocations LIVE'!$T:$T, 'Regional allocations LIVE'!$H:$H, $R9, 'Regional allocations LIVE'!$R:$R, ">=" & AV$4, 'Regional allocations LIVE'!$R:$R, "<=" & Table14[[#Headers],[30/11/2026]] ) -> 0 | AW9: =SUMIFS('Regional allocations LIVE'!$T:$T, 'Regional allocations LIVE'!$H:$H, $R9, 'Regional allocations LIVE'!$R:$R, ">=" & AW$4, 'Regional allocations LIVE'!$R:$R, "<=" & Table14[[#Headers],[31/12/2026]] ) -> 0 | AX9: =SUMIFS('Regional allocations LIVE'!$T:$T, 'Regional allocations LIVE'!$H:$H, $R9, 'Regional allocations LIVE'!$R:$R, ">=" & AX$4, 'Regional allocations LIVE'!$R:$R, "<=" & Table14[[#Headers],[30/01/2027]] ) -> 0 | AY9: =SUMIFS('Regional allocations LIVE'!$T:$T, 'Regional allocations LIVE'!$H:$H, $R9, 'Regional allocations LIVE'!$R:$R, ">=" & AY$4, 'Regional allocations LIVE'!$R:$R, "<=" & Table14[[#Headers],[28/02/2027]] ) -> 0 | AZ9: =SUMIFS('Regional allocations LIVE'!$T:$T, 'Regional allocations LIVE'!$H:$H, $R9, 'Regional allocations LIVE'!$R:$R, ">=" & AZ$4, 'Regional allocations LIVE'!$R:$R, "<=" & Table14[[#Headers],[31/03/2027]] ) -> 0 | BA9: =SUMIFS('Regional allocations LIVE'!$T:$T, 'Regional allocations LIVE'!$H:$H, $R9, 'Regional allocations LIVE'!$R:$R, ">=" & BA$4, 'Regional allocations LIVE'!$R:$R, "<=" & Table14[[#Headers],[30/04/2027]] ) -> 0 | BB9: =SUMIFS('Regional allocations LIVE'!$T:$T, 'Regional allocations LIVE'!$H:$H, $R9, 'Regional allocations LIVE'!$R:$R, ">=" & BB$4, 'Regional allocations LIVE'!$R:$R, "<=" & Table14[[#Headers],[31/05/2027]] ) -> 0 | BC9: =SUMIFS('Regional allocations LIVE'!$T:$T, 'Regional allocations LIVE'!$H:$H, $R9, 'Regional allocations LIVE'!$R:$R, ">=" & BC$4, 'Regional allocations LIVE'!$R:$R, "<=" & Table14[[#Headers],[30/06/2027]] ) -> 0 | BD9: =SUMIFS('Regional allocations LIVE'!$T:$T, 'Regional allocations LIVE'!$H:$H, $R9, 'Regional allocations LIVE'!$R:$R, ">=" & BD$4, 'Regional allocations LIVE'!$R:$R, "<=" & Table14[[#Headers],[31/07/2027]] ) -> 0 | BE9: =SUMIFS('Regional allocations LIVE'!$T:$T, 'Regional allocations LIVE'!$H:$H, $R9, 'Regional allocations LIVE'!$R:$R, ">=" & BE$4, 'Regional allocations LIVE'!$R:$R, "<=" & Table14[[#Headers],[31/08/2027]] ) -> 0 | BF9: =SUMIFS('Regional allocations LIVE'!$T:$T, 'Regional allocations LIVE'!$H:$H, $R9, 'Regional allocations LIVE'!$R:$R, ">=" & BF$4, 'Regional allocations LIVE'!$R:$R, "<=" & Table14[[#Headers],[30/09/2027]] ) -> 0 | BG9: =SUMIFS('Regional allocations LIVE'!$T:$T, 'Regional allocations LIVE'!$H:$H, $R9, 'Regional allocations LIVE'!$R:$R, ">=" & BG$4, 'Regional allocations LIVE'!$R:$R, "<=" & Table14[[#Headers],[31/10/2027]] ) -> 0
B10: Shared Services | C10: =AD42 -> 16 | E10: Total Headcount | H10: Shared Services | I10: =COUNTIFS('Regional allocations LIVE'!H:H,Table1116[[#This Row],[Business Unit]],'Regional allocations LIVE'!R:R,"") -> 16 | J10: 1 | M10: =COUNTIFS('Regional allocations LIVE'!H:H,Table1116[[#This Row],[Business Unit]],'Regional allocations LIVE'!U:U,"Y",'Regional allocations LIVE'!R:R,"") -> 0 | N10: =Table1116[[#This Row],[Headcount]]-Table1116[[#This Row],[Contractors]] -> 16 | O10: =Table1116[[#This Row],[Perm Headcount (minus contractors)]]+Table1116[[#This Row],[Vaccancies to backfill]]+Table1116[[#This Row],[Vaccancies for new roles]] -> 17 | R10: Asia Pacific | S10: 0 | T10: 0 | U10: 0 | V10: 1 | W10: 0 | Y10: 1 | Z10: 2 | AE10: 1 | AF10: =SUMIFS('Regional allocations LIVE'!$T:$T, 'Regional allocations LIVE'!$H:$H, $R10, 'Regional allocations LIVE'!$R:$R, ">=" & AF$4, 'Regional allocations LIVE'!$R:$R, "<=" & Table14[[#Headers],[31/07/2025]] ) -> 0 | AG10: =SUMIFS('Regional allocations LIVE'!$T:$T, 'Regional allocations LIVE'!$H:$H, $R10, 'Regional allocations LIVE'!$R:$R, ">=" & AG$4, 'Regional allocations LIVE'!$R:$R, "<=" & Table14[[#Headers],[31/08/2025]] ) -> 0 | AH10: =SUMIFS('Regional allocations LIVE'!$T:$T, 'Regional allocations LIVE'!$H:$H, $R10, 'Regional allocations LIVE'!$R:$R, ">=" & AH$4, 'Regional allocations LIVE'!$R:$R, "<=" & Table14[[#Headers],[30/09/2025]] ) -> 0 | AI10: =SUMIFS('Regional allocations LIVE'!$T:$T, 'Regional allocations LIVE'!$H:$H, $R10, 'Regional allocations LIVE'!$R:$R, ">=" & AI$4, 'Regional allocations LIVE'!$R:$R, "<=" & Table14[[#Headers],[31/10/2025]] ) -> 0 | AJ10: =SUMIFS('Regional allocations LIVE'!$T:$T, 'Regional allocations LIVE'!$H:$H, $R10, 'Regional allocations LIVE'!$R:$R, ">=" & AJ$4, 'Regional allocations LIVE'!$R:$R, "<=" & Table14[[#Headers],[30/11/2025]] ) -> 0 | AK10: =SUMIFS('Regional allocations LIVE'!$T:$T, 'Regional allocations LIVE'!$H:$H, $R10, 'Regional allocations LIVE'!$R:$R, ">=" & AK$4, 'Regional allocations LIVE'!$R:$R, "<=" & Table14[[#Headers],[31/12/2025]] ) -> 0 | AL10: =SUMIFS('Regional allocations LIVE'!$T:$T, 'Regional allocations LIVE'!$H:$H, $R10, 'Regional allocations LIVE'!$R:$R, ">=" & AL$4, 'Regional allocations LIVE'!$R:$R, "<=" & Table14[[#Headers],[30/01/2026]] ) -> 0 | AM10: =SUMIFS('Regional allocations LIVE'!$T:$T, 'Regional allocations LIVE'!$H:$H, $R10, 'Regional allocations LIVE'!$R:$R, ">=" & AM$4, 'Regional allocations LIVE'!$R:$R, "<=" & Table14[[#Headers],[28/02/2026]] ) -> 0 | AN10: =SUMIFS('Regional allocations LIVE'!$T:$T, 'Regional allocations LIVE'!$H:$H, $R10, 'Regional allocations LIVE'!$R:$R, ">=" & AN$4, 'Regional allocations LIVE'!$R:$R, "<=" & Table14[[#Headers],[31/03/2026]] ) -> 0 | AO10: =SUMIFS('Regional allocations LIVE'!$T:$T, 'Regional allocations LIVE'!$H:$H, $R10, 'Regional allocations LIVE'!$R:$R, ">=" & AO$4, 'Regional allocations LIVE'!$R:$R, "<=" & Table14[[#Headers],[30/04/2026]] ) -> 0 | AP10: =SUMIFS('Regional allocations LIVE'!$T:$T, 'Regional allocations LIVE'!$H:$H, $R10, 'Regional allocations LIVE'!$R:$R, ">=" & AP$4, 'Regional allocations LIVE'!$R:$R, "<=" & Table14[[#Headers],[31/05/2026]] ) -> 0 | AQ10: =SUMIFS('Regional allocations LIVE'!$T:$T, 'Regional allocations LIVE'!$H:$H, $R10, 'Regional allocations LIVE'!$R:$R, ">=" & AQ$4, 'Regional allocations LIVE'!$R:$R, "<=" & Table14[[#Headers],[30/06/2026]] ) -> 0 | AR10: =SUMIFS('Regional allocations LIVE'!$T:$T, 'Regional allocations LIVE'!$H:$H, $R10, 'Regional allocations LIVE'!$R:$R, ">=" & AR$4, 'Regional allocations LIVE'!$R:$R, "<=" & Table14[[#Headers],[31/07/2026]] ) -> 0 | AS10: =SUMIFS('Regional allocations LIVE'!$T:$T, 'Regional allocations LIVE'!$H:$H, $R10, 'Regional allocations LIVE'!$R:$R, ">=" & AS$4, 'Regional allocations LIVE'!$R:$R, "<=" & Table14[[#Headers],[31/08/2026]] ) -> 0 | AT10: =SUMIFS('Regional allocations LIVE'!$T:$T, 'Regional allocations LIVE'!$H:$H, $R10, 'Regional allocations LIVE'!$R:$R, ">=" & AT$4, 'Regional allocations LIVE'!$R:$R, "<=" & Table14[[#Headers],[30/09/2026]] ) -> 0 | AU10: =SUMIFS('Regional allocations LIVE'!$T:$T, 'Regional allocations LIVE'!$H:$H, $R10, 'Regional allocations LIVE'!$R:$R, ">=" & AU$4, 'Regional allocations LIVE'!$R:$R, "<=" & Table14[[#Headers],[31/10/2026]] ) -> 0 | AV10: =SUMIFS('Regional allocations LIVE'!$T:$T, 'Regional allocations LIVE'!$H:$H, $R10, 'Regional allocations LIVE'!$R:$R, ">=" & AV$4, 'Regional allocations LIVE'!$R:$R, "<=" & Table14[[#Headers],[30/11/2026]] ) -> 0 | AW10: =SUMIFS('Regional allocations LIVE'!$T:$T, 'Regional allocations LIVE'!$H:$H, $R10, 'Regional allocations LIVE'!$R:$R, ">=" & AW$4, 'Regional allocations LIVE'!$R:$R, "<=" & Table14[[#Headers],[31/12/2026]] ) -> 0 | AX10: =SUMIFS('Regional allocations LIVE'!$T:$T, 'Regional allocations LIVE'!$H:$H, $R10, 'Regional allocations LIVE'!$R:$R, ">=" & AX$4, 'Regional allocations LIVE'!$R:$R, "<=" & Table14[[#Headers],[30/01/2027]] ) -> 0 | AY10: =SUMIFS('Regional allocations LIVE'!$T:$T, 'Regional allocations LIVE'!$H:$H, $R10, 'Regional allocations LIVE'!$R:$R, ">=" & AY$4, 'Regional allocations LIVE'!$R:$R, "<=" & Table14[[#Headers],[28/02/2027]] ) -> 0 | AZ10: =SUMIFS('Regional allocations LIVE'!$T:$T, 'Regional allocations LIVE'!$H:$H, $R10, 'Regional allocations LIVE'!$R:$R, ">=" & AZ$4, 'Regional allocations LIVE'!$R:$R, "<=" & Table14[[#Headers],[31/03/2027]] ) -> 0 | BA10: =SUMIFS('Regional allocations LIVE'!$T:$T, 'Regional allocations LIVE'!$H:$H, $R10, 'Regional allocations LIVE'!$R:$R, ">=" & BA$4, 'Regional allocations LIVE'!$R:$R, "<=" & Table14[[#Headers],[30/04/2027]] ) -> 0 | BB10: =SUMIFS('Regional allocations LIVE'!$T:$T, 'Regional allocations LIVE'!$H:$H, $R10, 'Regional allocations LIVE'!$R:$R, ">=" & BB$4, 'Regional allocations LIVE'!$R:$R, "<=" & Table14[[#Headers],[31/05/2027]] ) -> 0 | BC10: =SUMIFS('Regional allocations LIVE'!$T:$T, 'Regional allocations LIVE'!$H:$H, $R10, 'Regional allocations LIVE'!$R:$R, ">=" & BC$4, 'Regional allocations LIVE'!$R:$R, "<=" & Table14[[#Headers],[30/06/2027]] ) -> 0 | BD10: =SUMIFS('Regional allocations LIVE'!$T:$T, 'Regional allocations LIVE'!$H:$H, $R10, 'Regional allocations LIVE'!$R:$R, ">=" & BD$4, 'Regional allocations LIVE'!$R:$R, "<=" & Table14[[#Headers],[31/07/2027]] ) -> 0 | BE10: =SUMIFS('Regional allocations LIVE'!$T:$T, 'Regional allocations LIVE'!$H:$H, $R10, 'Regional allocations LIVE'!$R:$R, ">=" & BE$4, 'Regional allocations LIVE'!$R:$R, "<=" & Table14[[#Headers],[31/08/2027]] ) -> 0 | BF10: =SUMIFS('Regional allocations LIVE'!$T:$T, 'Regional allocations LIVE'!$H:$H, $R10, 'Regional allocations LIVE'!$R:$R, ">=" & BF$4, 'Regional allocations LIVE'!$R:$R, "<=" & Table14[[#Headers],[30/09/2027]] ) -> 0 | BG10: =SUMIFS('Regional allocations LIVE'!$T:$T, 'Regional allocations LIVE'!$H:$H, $R10, 'Regional allocations LIVE'!$R:$R, ">=" & BG$4, 'Regional allocations LIVE'!$R:$R, "<=" & Table14[[#Headers],[31/10/2027]] ) -> 0
B11: Europe | C11: =AD43 -> 44.8 | E11: =SUM(Table11[Headcount]) -> 170.75 | H11: Europe | I11: =COUNTIFS('Regional allocations LIVE'!H:H,Table1116[[#This Row],[Business Unit]],'Regional allocations LIVE'!R:R,"") -> 49 | J11: 5 | K11: 2 | M11: =COUNTIFS('Regional allocations LIVE'!H:H,Table1116[[#This Row],[Business Unit]],'Regional allocations LIVE'!U:U,"Y",'Regional allocations LIVE'!R:R,"") -> 0 | N11: =Table1116[[#This Row],[Headcount]]-Table1116[[#This Row],[Contractors]] -> 49 | O11: =Table1116[[#This Row],[Perm Headcount (minus contractors)]]+Table1116[[#This Row],[Vaccancies to backfill]]+Table1116[[#This Row],[Vaccancies for new roles]] -> 56 | R11: ELT | S11: 0 | T11: 0 | U11: 0 | V11: 0 | W11: 0 | AA11: 1 | AF11: =SUMIFS('Regional allocations LIVE'!$T:$T, 'Regional allocations LIVE'!$H:$H, $R11, 'Regional allocations LIVE'!$R:$R, ">=" & AF$4, 'Regional allocations LIVE'!$R:$R, "<=" & Table14[[#Headers],[31/07/2025]] ) -> 0 | AG11: =SUMIFS('Regional allocations LIVE'!$T:$T, 'Regional allocations LIVE'!$H:$H, $R11, 'Regional allocations LIVE'!$R:$R, ">=" & AG$4, 'Regional allocations LIVE'!$R:$R, "<=" & Table14[[#Headers],[31/08/2025]] ) -> 0 | AH11: =SUMIFS('Regional allocations LIVE'!$T:$T, 'Regional allocations LIVE'!$H:$H, $R11, 'Regional allocations LIVE'!$R:$R, ">=" & AH$4, 'Regional allocations LIVE'!$R:$R, "<=" & Table14[[#Headers],[30/09/2025]] ) -> 0 | AI11: =SUMIFS('Regional allocations LIVE'!$T:$T, 'Regional allocations LIVE'!$H:$H, $R11, 'Regional allocations LIVE'!$R:$R, ">=" & AI$4, 'Regional allocations LIVE'!$R:$R, "<=" & Table14[[#Headers],[31/10/2025]] ) -> 0 | AJ11: =SUMIFS('Regional allocations LIVE'!$T:$T, 'Regional allocations LIVE'!$H:$H, $R11, 'Regional allocations LIVE'!$R:$R, ">=" & AJ$4, 'Regional allocations LIVE'!$R:$R, "<=" & Table14[[#Headers],[30/11/2025]] ) -> 0 | AK11: =SUMIFS('Regional allocations LIVE'!$T:$T, 'Regional allocations LIVE'!$H:$H, $R11, 'Regional allocations LIVE'!$R:$R, ">=" & AK$4, 'Regional allocations LIVE'!$R:$R, "<=" & Table14[[#Headers],[31/12/2025]] ) -> 0 | AL11: =SUMIFS('Regional allocations LIVE'!$T:$T, 'Regional allocations LIVE'!$H:$H, $R11, 'Regional allocations LIVE'!$R:$R, ">=" & AL$4, 'Regional allocations LIVE'!$R:$R, "<=" & Table14[[#Headers],[30/01/2026]] ) -> 0 | AM11: =SUMIFS('Regional allocations LIVE'!$T:$T, 'Regional allocations LIVE'!$H:$H, $R11, 'Regional allocations LIVE'!$R:$R, ">=" & AM$4, 'Regional allocations LIVE'!$R:$R, "<=" & Table14[[#Headers],[28/02/2026]] ) -> 0 | AN11: =SUMIFS('Regional allocations LIVE'!$T:$T, 'Regional allocations LIVE'!$H:$H, $R11, 'Regional allocations LIVE'!$R:$R, ">=" & AN$4, 'Regional allocations LIVE'!$R:$R, "<=" & Table14[[#Headers],[31/03/2026]] ) -> 0 | AO11: =SUMIFS('Regional allocations LIVE'!$T:$T, 'Regional allocations LIVE'!$H:$H, $R11, 'Regional allocations LIVE'!$R:$R, ">=" & AO$4, 'Regional allocations LIVE'!$R:$R, "<=" & Table14[[#Headers],[30/04/2026]] ) -> 0 | AP11: =SUMIFS('Regional allocations LIVE'!$T:$T, 'Regional allocations LIVE'!$H:$H, $R11, 'Regional allocations LIVE'!$R:$R, ">=" & AP$4, 'Regional allocations LIVE'!$R:$R, "<=" & Table14[[#Headers],[31/05/2026]] ) -> 0 | AQ11: =SUMIFS('Regional allocations LIVE'!$T:$T, 'Regional allocations LIVE'!$H:$H, $R11, 'Regional allocations LIVE'!$R:$R, ">=" & AQ$4, 'Regional allocations LIVE'!$R:$R, "<=" & Table14[[#Headers],[30/06/2026]] ) -> 0 | AR11: =SUMIFS('Regional allocations LIVE'!$T:$T, 'Regional allocations LIVE'!$H:$H, $R11, 'Regional allocations LIVE'!$R:$R, ">=" & AR$4, 'Regional allocations LIVE'!$R:$R, "<=" & Table14[[#Headers],[31/07/2026]] ) -> 0 | AS11: =SUMIFS('Regional allocations LIVE'!$T:$T, 'Regional allocations LIVE'!$H:$H, $R11, 'Regional allocations LIVE'!$R:$R, ">=" & AS$4, 'Regional allocations LIVE'!$R:$R, "<=" & Table14[[#Headers],[31/08/2026]] ) -> 0 | AT11: =SUMIFS('Regional allocations LIVE'!$T:$T, 'Regional allocations LIVE'!$H:$H, $R11, 'Regional allocations LIVE'!$R:$R, ">=" & AT$4, 'Regional allocations LIVE'!$R:$R, "<=" & Table14[[#Headers],[30/09/2026]] ) -> 0 | AU11: =SUMIFS('Regional allocations LIVE'!$T:$T, 'Regional allocations LIVE'!$H:$H, $R11, 'Regional allocations LIVE'!$R:$R, ">=" & AU$4, 'Regional allocations LIVE'!$R:$R, "<=" & Table14[[#Headers],[31/10/2026]] ) -> 0 | AV11: =SUMIFS('Regional allocations LIVE'!$T:$T, 'Regional allocations LIVE'!$H:$H, $R11, 'Regional allocations LIVE'!$R:$R, ">=" & AV$4, 'Regional allocations LIVE'!$R:$R, "<=" & Table14[[#Headers],[30/11/2026]] ) -> 0 | AW11: =SUMIFS('Regional allocations LIVE'!$T:$T, 'Regional allocations LIVE'!$H:$H, $R11, 'Regional allocations LIVE'!$R:$R, ">=" & AW$4, 'Regional allocations LIVE'!$R:$R, "<=" & Table14[[#Headers],[31/12/2026]] ) -> 0 | AX11: =SUMIFS('Regional allocations LIVE'!$T:$T, 'Regional allocations LIVE'!$H:$H, $R11, 'Regional allocations LIVE'!$R:$R, ">=" & AX$4, 'Regional allocations LIVE'!$R:$R, "<=" & Table14[[#Headers],[30/01/2027]] ) -> 0 | AY11: =SUMIFS('Regional allocations LIVE'!$T:$T, 'Regional allocations LIVE'!$H:$H, $R11, 'Regional allocations LIVE'!$R:$R, ">=" & AY$4, 'Regional allocations LIVE'!$R:$R, "<=" & Table14[[#Headers],[28/02/2027]] ) -> 0 | AZ11: =SUMIFS('Regional allocations LIVE'!$T:$T, 'Regional allocations LIVE'!$H:$H, $R11, 'Regional allocations LIVE'!$R:$R, ">=" & AZ$4, 'Regional allocations LIVE'!$R:$R, "<=" & Table14[[#Headers],[31/03/2027]] ) -> 0 | BA11: =SUMIFS('Regional allocations LIVE'!$T:$T, 'Regional allocations LIVE'!$H:$H, $R11, 'Regional allocations LIVE'!$R:$R, ">=" & BA$4, 'Regional allocations LIVE'!$R:$R, "<=" & Table14[[#Headers],[30/04/2027]] ) -> 0 | BB11: =SUMIFS('Regional allocations LIVE'!$T:$T, 'Regional allocations LIVE'!$H:$H, $R11, 'Regional allocations LIVE'!$R:$R, ">=" & BB$4, 'Regional allocations LIVE'!$R:$R, "<=" & Table14[[#Headers],[31/05/2027]] ) -> 0 | BC11: =SUMIFS('Regional allocations LIVE'!$T:$T, 'Regional allocations LIVE'!$H:$H, $R11, 'Regional allocations LIVE'!$R:$R, ">=" & BC$4, 'Regional allocations LIVE'!$R:$R, "<=" & Table14[[#Headers],[30/06/2027]] ) -> 0 | BD11: =SUMIFS('Regional allocations LIVE'!$T:$T, 'Regional allocations LIVE'!$H:$H, $R11, 'Regional allocations LIVE'!$R:$R, ">=" & BD$4, 'Regional allocations LIVE'!$R:$R, "<=" & Table14[[#Headers],[31/07/2027]] ) -> 0 | BE11: =SUMIFS('Regional allocations LIVE'!$T:$T, 'Regional allocations LIVE'!$H:$H, $R11, 'Regional allocations LIVE'!$R:$R, ">=" & BE$4, 'Regional allocations LIVE'!$R:$R, "<=" & Table14[[#Headers],[31/08/2027]] ) -> 0 | BF11: =SUMIFS('Regional allocations LIVE'!$T:$T, 'Regional allocations LIVE'!$H:$H, $R11, 'Regional allocations LIVE'!$R:$R, ">=" & BF$4, 'Regional allocations LIVE'!$R:$R, "<=" & Table14[[#Headers],[30/09/2027]] ) -> 0 | BG11: =SUMIFS('Regional allocations LIVE'!$T:$T, 'Regional allocations LIVE'!$H:$H, $R11, 'Regional allocations LIVE'!$R:$R, ">=" & BG$4, 'Regional allocations LIVE'!$R:$R, "<=" & Table14[[#Headers],[31/10/2027]] ) -> 0
B12: Asia Pacific | C12: =AD44 -> 19.75 | H12: Asia Pacific | I12: =COUNTIFS('Regional allocations LIVE'!H:H,Table1116[[#This Row],[Business Unit]],'Regional allocations LIVE'!R:R,"") -> 18 | J12: 0 | M12: =COUNTIFS('Regional allocations LIVE'!H:H,Table1116[[#This Row],[Business Unit]],'Regional allocations LIVE'!U:U,"Y",'Regional allocations LIVE'!R:R,"") -> 0 | N12: =Table1116[[#This Row],[Headcount]]-Table1116[[#This Row],[Contractors]] -> 18 | O12: =Table1116[[#This Row],[Perm Headcount (minus contractors)]]+Table1116[[#This Row],[Vaccancies to backfill]]+Table1116[[#This Row],[Vaccancies for new roles]] -> 18 | R12: Americas | S12: 0 | T12: 1 | U12: 0 | V12: 1 | W12: 0 | AD12: 1 | AE12: 2 | AF12: =SUMIFS('Regional allocations LIVE'!$T:$T, 'Regional allocations LIVE'!$H:$H, $R12, 'Regional allocations LIVE'!$R:$R, ">=" & AF$4, 'Regional allocations LIVE'!$R:$R, "<=" & Table14[[#Headers],[31/07/2025]] ) -> 1 | AG12: =SUMIFS('Regional allocations LIVE'!$T:$T, 'Regional allocations LIVE'!$H:$H, $R12, 'Regional allocations LIVE'!$R:$R, ">=" & AG$4, 'Regional allocations LIVE'!$R:$R, "<=" & Table14[[#Headers],[31/08/2025]] ) -> 1 | AH12: =SUMIFS('Regional allocations LIVE'!$T:$T, 'Regional allocations LIVE'!$H:$H, $R12, 'Regional allocations LIVE'!$R:$R, ">=" & AH$4, 'Regional allocations LIVE'!$R:$R, "<=" & Table14[[#Headers],[30/09/2025]] ) -> 1 | AI12: =SUMIFS('Regional allocations LIVE'!$T:$T, 'Regional allocations LIVE'!$H:$H, $R12, 'Regional allocations LIVE'!$R:$R, ">=" & AI$4, 'Regional allocations LIVE'!$R:$R, "<=" & Table14[[#Headers],[31/10/2025]] ) -> 2 | AJ12: =SUMIFS('Regional allocations LIVE'!$T:$T, 'Regional allocations LIVE'!$H:$H, $R12, 'Regional allocations LIVE'!$R:$R, ">=" & AJ$4, 'Regional allocations LIVE'!$R:$R, "<=" & Table14[[#Headers],[30/11/2025]] ) -> 1 | AK12: =SUMIFS('Regional allocations LIVE'!$T:$T, 'Regional allocations LIVE'!$H:$H, $R12, 'Regional allocations LIVE'!$R:$R, ">=" & AK$4, 'Regional allocations LIVE'!$R:$R, "<=" & Table14[[#Headers],[31/12/2025]] ) -> 1 | AL12: =SUMIFS('Regional allocations LIVE'!$T:$T, 'Regional allocations LIVE'!$H:$H, $R12, 'Regional allocations LIVE'!$R:$R, ">=" & AL$4, 'Regional allocations LIVE'!$R:$R, "<=" & Table14[[#Headers],[30/01/2026]] ) -> 1 | AM12: =SUMIFS('Regional allocations LIVE'!$T:$T, 'Regional allocations LIVE'!$H:$H, $R12, 'Regional allocations LIVE'!$R:$R, ">=" & AM$4, 'Regional allocations LIVE'!$R:$R, "<=" & Table14[[#Headers],[28/02/2026]] ) -> 0 | AN12: =SUMIFS('Regional allocations LIVE'!$T:$T, 'Regional allocations LIVE'!$H:$H, $R12, 'Regional allocations LIVE'!$R:$R, ">=" & AN$4, 'Regional allocations LIVE'!$R:$R, "<=" & Table14[[#Headers],[31/03/2026]] ) -> 0 | AO12: =SUMIFS('Regional allocations LIVE'!$T:$T, 'Regional allocations LIVE'!$H:$H, $R12, 'Regional allocations LIVE'!$R:$R, ">=" & AO$4, 'Regional allocations LIVE'!$R:$R, "<=" & Table14[[#Headers],[30/04/2026]] ) -> 0 | AP12: =SUMIFS('Regional allocations LIVE'!$T:$T, 'Regional allocations LIVE'!$H:$H, $R12, 'Regional allocations LIVE'!$R:$R, ">=" & AP$4, 'Regional allocations LIVE'!$R:$R, "<=" & Table14[[#Headers],[31/05/2026]] ) -> 0 | AQ12: =SUMIFS('Regional allocations LIVE'!$T:$T, 'Regional allocations LIVE'!$H:$H, $R12, 'Regional allocations LIVE'!$R:$R, ">=" & AQ$4, 'Regional allocations LIVE'!$R:$R, "<=" & Table14[[#Headers],[30/06/2026]] ) -> 0 | AR12: =SUMIFS('Regional allocations LIVE'!$T:$T, 'Regional allocations LIVE'!$H:$H, $R12, 'Regional allocations LIVE'!$R:$R, ">=" & AR$4, 'Regional allocations LIVE'!$R:$R, "<=" & Table14[[#Headers],[31/07/2026]] ) -> 0 | AS12: =SUMIFS('Regional allocations LIVE'!$T:$T, 'Regional allocations LIVE'!$H:$H, $R12, 'Regional allocations LIVE'!$R:$R, ">=" & AS$4, 'Regional allocations LIVE'!$R:$R, "<=" & Table14[[#Headers],[31/08/2026]] ) -> 0 | AT12: =SUMIFS('Regional allocations LIVE'!$T:$T, 'Regional allocations LIVE'!$H:$H, $R12, 'Regional allocations LIVE'!$R:$R, ">=" & AT$4, 'Regional allocations LIVE'!$R:$R, "<=" & Table14[[#Headers],[30/09/2026]] ) -> 0 | AU12: =SUMIFS('Regional allocations LIVE'!$T:$T, 'Regional allocations LIVE'!$H:$H, $R12, 'Regional allocations LIVE'!$R:$R, ">=" & AU$4, 'Regional allocations LIVE'!$R:$R, "<=" & Table14[[#Headers],[31/10/2026]] ) -> 0 | AV12: =SUMIFS('Regional allocations LIVE'!$T:$T, 'Regional allocations LIVE'!$H:$H, $R12, 'Regional allocations LIVE'!$R:$R, ">=" & AV$4, 'Regional allocations LIVE'!$R:$R, "<=" & Table14[[#Headers],[30/11/2026]] ) -> 0 | AW12: =SUMIFS('Regional allocations LIVE'!$T:$T, 'Regional allocations LIVE'!$H:$H, $R12, 'Regional allocations LIVE'!$R:$R, ">=" & AW$4, 'Regional allocations LIVE'!$R:$R, "<=" & Table14[[#Headers],[31/12/2026]] ) -> 0 | AX12: =SUMIFS('Regional allocations LIVE'!$T:$T, 'Regional allocations LIVE'!$H:$H, $R12, 'Regional allocations LIVE'!$R:$R, ">=" & AX$4, 'Regional allocations LIVE'!$R:$R, "<=" & Table14[[#Headers],[30/01/2027]] ) -> 0 | AY12: =SUMIFS('Regional allocations LIVE'!$T:$T, 'Regional allocations LIVE'!$H:$H, $R12, 'Regional allocations LIVE'!$R:$R, ">=" & AY$4, 'Regional allocations LIVE'!$R:$R, "<=" & Table14[[#Headers],[28/02/2027]] ) -> 0 | AZ12: =SUMIFS('Regional allocations LIVE'!$T:$T, 'Regional allocations LIVE'!$H:$H, $R12, 'Regional allocations LIVE'!$R:$R, ">=" & AZ$4, 'Regional allocations LIVE'!$R:$R, "<=" & Table14[[#Headers],[31/03/2027]] ) -> 0 | BA12: =SUMIFS('Regional allocations LIVE'!$T:$T, 'Regional allocations LIVE'!$H:$H, $R12, 'Regional allocations LIVE'!$R:$R, ">=" & BA$4, 'Regional allocations LIVE'!$R:$R, "<=" & Table14[[#Headers],[30/04/2027]] ) -> 0 | BB12: =SUMIFS('Regional allocations LIVE'!$T:$T, 'Regional allocations LIVE'!$H:$H, $R12, 'Regional allocations LIVE'!$R:$R, ">=" & BB$4, 'Regional allocations LIVE'!$R:$R, "<=" & Table14[[#Headers],[31/05/2027]] ) -> 0 | BC12: =SUMIFS('Regional allocations LIVE'!$T:$T, 'Regional allocations LIVE'!$H:$H, $R12, 'Regional allocations LIVE'!$R:$R, ">=" & BC$4, 'Regional allocations LIVE'!$R:$R, "<=" & Table14[[#Headers],[30/06/2027]] ) -> 0 | BD12: =SUMIFS('Regional allocations LIVE'!$T:$T, 'Regional allocations LIVE'!$H:$H, $R12, 'Regional allocations LIVE'!$R:$R, ">=" & BD$4, 'Regional allocations LIVE'!$R:$R, "<=" & Table14[[#Headers],[31/07/2027]] ) -> 0 | BE12: =SUMIFS('Regional allocations LIVE'!$T:$T, 'Regional allocations LIVE'!$H:$H, $R12, 'Regional allocations LIVE'!$R:$R, ">=" & BE$4, 'Regional allocations LIVE'!$R:$R, "<=" & Table14[[#Headers],[31/08/2027]] ) -> 0 | BF12: =SUMIFS('Regional allocations LIVE'!$T:$T, 'Regional allocations LIVE'!$H:$H, $R12, 'Regional allocations LIVE'!$R:$R, ">=" & BF$4, 'Regional allocations LIVE'!$R:$R, "<=" & Table14[[#Headers],[30/09/2027]] ) -> 0 | BG12: =SUMIFS('Regional allocations LIVE'!$T:$T, 'Regional allocations LIVE'!$H:$H, $R12, 'Regional allocations LIVE'!$R:$R, ">=" & BG$4, 'Regional allocations LIVE'!$R:$R, "<=" & Table14[[#Headers],[31/10/2027]] ) -> 0
B13: ELT | C13: =AD45 -> 0 | H13: ELT | I13: =COUNTIFS('Regional allocations LIVE'!H:H,Table1116[[#This Row],[Business Unit]],'Regional allocations LIVE'!R:R,"") -> 0 | J13: 1 | M13: =COUNTIFS('Regional allocations LIVE'!H:H,Table1116[[#This Row],[Business Unit]],'Regional allocations LIVE'!U:U,"Y",'Regional allocations LIVE'!R:R,"") -> 0 | N13: =Table1116[[#This Row],[Headcount]]-Table1116[[#This Row],[Contractors]] -> 0 | O13: =Table1116[[#This Row],[Perm Headcount (minus contractors)]]+Table1116[[#This Row],[Vaccancies to backfill]]+Table1116[[#This Row],[Vaccancies for new roles]] -> 1 | R13: Clever Cloud | S13: 0 | T13: 0 | U13: 0 | V13: 0 | W13: 0 | AF13: =SUMIFS('Regional allocations LIVE'!$T:$T, 'Regional allocations LIVE'!$H:$H, $R13, 'Regional allocations LIVE'!$R:$R, ">=" & AF$4, 'Regional allocations LIVE'!$R:$R, "<=" & Table14[[#Headers],[31/07/2025]] ) -> 0 | AG13: =SUMIFS('Regional allocations LIVE'!$T:$T, 'Regional allocations LIVE'!$H:$H, $R13, 'Regional allocations LIVE'!$R:$R, ">=" & AG$4, 'Regional allocations LIVE'!$R:$R, "<=" & Table14[[#Headers],[31/08/2025]] ) -> 0 | AH13: =SUMIFS('Regional allocations LIVE'!$T:$T, 'Regional allocations LIVE'!$H:$H, $R13, 'Regional allocations LIVE'!$R:$R, ">=" & AH$4, 'Regional allocations LIVE'!$R:$R, "<=" & Table14[[#Headers],[30/09/2025]] ) -> 0 | AI13: =SUMIFS('Regional allocations LIVE'!$T:$T, 'Regional allocations LIVE'!$H:$H, $R13, 'Regional allocations LIVE'!$R:$R, ">=" & AI$4, 'Regional allocations LIVE'!$R:$R, "<=" & Table14[[#Headers],[31/10/2025]] ) -> 0 | AJ13: =SUMIFS('Regional allocations LIVE'!$T:$T, 'Regional allocations LIVE'!$H:$H, $R13, 'Regional allocations LIVE'!$R:$R, ">=" & AJ$4, 'Regional allocations LIVE'!$R:$R, "<=" & Table14[[#Headers],[30/11/2025]] ) -> 0 | AK13: =SUMIFS('Regional allocations LIVE'!$T:$T, 'Regional allocations LIVE'!$H:$H, $R13, 'Regional allocations LIVE'!$R:$R, ">=" & AK$4, 'Regional allocations LIVE'!$R:$R, "<=" & Table14[[#Headers],[31/12/2025]] ) -> 0 | AL13: =SUMIFS('Regional allocations LIVE'!$T:$T, 'Regional allocations LIVE'!$H:$H, $R13, 'Regional allocations LIVE'!$R:$R, ">=" & AL$4, 'Regional allocations LIVE'!$R:$R, "<=" & Table14[[#Headers],[30/01/2026]] ) -> 0 | AM13: =SUMIFS('Regional allocations LIVE'!$T:$T, 'Regional allocations LIVE'!$H:$H, $R13, 'Regional allocations LIVE'!$R:$R, ">=" & AM$4, 'Regional allocations LIVE'!$R:$R, "<=" & Table14[[#Headers],[28/02/2026]] ) -> 0 | AN13: =SUMIFS('Regional allocations LIVE'!$T:$T, 'Regional allocations LIVE'!$H:$H, $R13, 'Regional allocations LIVE'!$R:$R, ">=" & AN$4, 'Regional allocations LIVE'!$R:$R, "<=" & Table14[[#Headers],[31/03/2026]] ) -> 0 | AO13: =SUMIFS('Regional allocations LIVE'!$T:$T, 'Regional allocations LIVE'!$H:$H, $R13, 'Regional allocations LIVE'!$R:$R, ">=" & AO$4, 'Regional allocations LIVE'!$R:$R, "<=" & Table14[[#Headers],[30/04/2026]] ) -> 0 | AP13: =SUMIFS('Regional allocations LIVE'!$T:$T, 'Regional allocations LIVE'!$H:$H, $R13, 'Regional allocations LIVE'!$R:$R, ">=" & AP$4, 'Regional allocations LIVE'!$R:$R, "<=" & Table14[[#Headers],[31/05/2026]] ) -> 0 | AQ13: =SUMIFS('Regional allocations LIVE'!$T:$T, 'Regional allocations LIVE'!$H:$H, $R13, 'Regional allocations LIVE'!$R:$R, ">=" & AQ$4, 'Regional allocations LIVE'!$R:$R, "<=" & Table14[[#Headers],[30/06/2026]] ) -> 0 | AR13: =SUMIFS('Regional allocations LIVE'!$T:$T, 'Regional allocations LIVE'!$H:$H, $R13, 'Regional allocations LIVE'!$R:$R, ">=" & AR$4, 'Regional allocations LIVE'!$R:$R, "<=" & Table14[[#Headers],[31/07/2026]] ) -> 0 | AS13: =SUMIFS('Regional allocations LIVE'!$T:$T, 'Regional allocations LIVE'!$H:$H, $R13, 'Regional allocations LIVE'!$R:$R, ">=" & AS$4, 'Regional allocations LIVE'!$R:$R, "<=" & Table14[[#Headers],[31/08/2026]] ) -> 0 | AT13: =SUMIFS('Regional allocations LIVE'!$T:$T, 'Regional allocations LIVE'!$H:$H, $R13, 'Regional allocations LIVE'!$R:$R, ">=" & AT$4, 'Regional allocations LIVE'!$R:$R, "<=" & Table14[[#Headers],[30/09/2026]] ) -> 0 | AU13: =SUMIFS('Regional allocations LIVE'!$T:$T, 'Regional allocations LIVE'!$H:$H, $R13, 'Regional allocations LIVE'!$R:$R, ">=" & AU$4, 'Regional allocations LIVE'!$R:$R, "<=" & Table14[[#Headers],[31/10/2026]] ) -> 0 | AV13: =SUMIFS('Regional allocations LIVE'!$T:$T, 'Regional allocations LIVE'!$H:$H, $R13, 'Regional allocations LIVE'!$R:$R, ">=" & AV$4, 'Regional allocations LIVE'!$R:$R, "<=" & Table14[[#Headers],[30/11/2026]] ) -> 0 | AW13: =SUMIFS('Regional allocations LIVE'!$T:$T, 'Regional allocations LIVE'!$H:$H, $R13, 'Regional allocations LIVE'!$R:$R, ">=" & AW$4, 'Regional allocations LIVE'!$R:$R, "<=" & Table14[[#Headers],[31/12/2026]] ) -> 0 | AX13: =SUMIFS('Regional allocations LIVE'!$T:$T, 'Regional allocations LIVE'!$H:$H, $R13, 'Regional allocations LIVE'!$R:$R, ">=" & AX$4, 'Regional allocations LIVE'!$R:$R, "<=" & Table14[[#Headers],[30/01/2027]] ) -> 0 | AY13: =SUMIFS('Regional allocations LIVE'!$T:$T, 'Regional allocations LIVE'!$H:$H, $R13, 'Regional allocations LIVE'!$R:$R, ">=" & AY$4, 'Regional allocations LIVE'!$R:$R, "<=" & Table14[[#Headers],[28/02/2027]] ) -> 0 | AZ13: =SUMIFS('Regional allocations LIVE'!$T:$T, 'Regional allocations LIVE'!$H:$H, $R13, 'Regional allocations LIVE'!$R:$R, ">=" & AZ$4, 'Regional allocations LIVE'!$R:$R, "<=" & Table14[[#Headers],[31/03/2027]] ) -> 0 | BA13: =SUMIFS('Regional allocations LIVE'!$T:$T, 'Regional allocations LIVE'!$H:$H, $R13, 'Regional allocations LIVE'!$R:$R, ">=" & BA$4, 'Regional allocations LIVE'!$R:$R, "<=" & Table14[[#Headers],[30/04/2027]] ) -> 0 | BB13: =SUMIFS('Regional allocations LIVE'!$T:$T, 'Regional allocations LIVE'!$H:$H, $R13, 'Regional allocations LIVE'!$R:$R, ">=" & BB$4, 'Regional allocations LIVE'!$R:$R, "<=" & Table14[[#Headers],[31/05/2027]] ) -> 0 | BC13: =SUMIFS('Regional allocations LIVE'!$T:$T, 'Regional allocations LIVE'!$H:$H, $R13, 'Regional allocations LIVE'!$R:$R, ">=" & BC$4, 'Regional allocations LIVE'!$R:$R, "<=" & Table14[[#Headers],[30/06/2027]] ) -> 0 | BD13: =SUMIFS('Regional allocations LIVE'!$T:$T, 'Regional allocations LIVE'!$H:$H, $R13, 'Regional allocations LIVE'!$R:$R, ">=" & BD$4, 'Regional allocations LIVE'!$R:$R, "<=" & Table14[[#Headers],[31/07/2027]] ) -> 0 | BE13: =SUMIFS('Regional allocations LIVE'!$T:$T, 'Regional allocations LIVE'!$H:$H, $R13, 'Regional allocations LIVE'!$R:$R, ">=" & BE$4, 'Regional allocations LIVE'!$R:$R, "<=" & Table14[[#Headers],[31/08/2027]] ) -> 0 | BF13: =SUMIFS('Regional allocations LIVE'!$T:$T, 'Regional allocations LIVE'!$H:$H, $R13, 'Regional allocations LIVE'!$R:$R, ">=" & BF$4, 'Regional allocations LIVE'!$R:$R, "<=" & Table14[[#Headers],[30/09/2027]] ) -> 0 | BG13: =SUMIFS('Regional allocations LIVE'!$T:$T, 'Regional allocations LIVE'!$H:$H, $R13, 'Regional allocations LIVE'!$R:$R, ">=" & BG$4, 'Regional allocations LIVE'!$R:$R, "<=" & Table14[[#Headers],[31/10/2027]] ) -> 0
B14: Americas | C14: =AD46 -> 41 | H14: Americas | I14: =COUNTIFS('Regional allocations LIVE'!H:H,Table1116[[#This Row],[Business Unit]],'Regional allocations LIVE'!R:R,"") -> 39 | J14: 2 | K14: 5 | L14: 0 | M14: =COUNTIFS('Regional allocations LIVE'!H:H,Table1116[[#This Row],[Business Unit]],'Regional allocations LIVE'!U:U,"Y",'Regional allocations LIVE'!R:R,"") -> 0 | N14: =Table1116[[#This Row],[Headcount]]-Table1116[[#This Row],[Contractors]] -> 39 | O14: =Table1116[[#This Row],[Perm Headcount (minus contractors)]]+Table1116[[#This Row],[Vaccancies to backfill]]+Table1116[[#This Row],[Vaccancies for new roles]] -> 46 | R14: Advisory, Data &AI | AF14: =SUMIFS('Regional allocations LIVE'!$T:$T, 'Regional allocations LIVE'!$H:$H, $R14, 'Regional allocations LIVE'!$R:$R, ">=" & AF$4, 'Regional allocations LIVE'!$R:$R, "<=" & Table14[[#Headers],[31/07/2025]] ) -> 0 | AG14: =SUMIFS('Regional allocations LIVE'!$T:$T, 'Regional allocations LIVE'!$H:$H, $R14, 'Regional allocations LIVE'!$R:$R, ">=" & AG$4, 'Regional allocations LIVE'!$R:$R, "<=" & Table14[[#Headers],[31/08/2025]] ) -> 0 | AH14: =SUMIFS('Regional allocations LIVE'!$T:$T, 'Regional allocations LIVE'!$H:$H, $R14, 'Regional allocations LIVE'!$R:$R, ">=" & AH$4, 'Regional allocations LIVE'!$R:$R, "<=" & Table14[[#Headers],[30/09/2025]] ) -> 0 | AI14: =SUMIFS('Regional allocations LIVE'!$T:$T, 'Regional allocations LIVE'!$H:$H, $R14, 'Regional allocations LIVE'!$R:$R, ">=" & AI$4, 'Regional allocations LIVE'!$R:$R, "<=" & Table14[[#Headers],[31/10/2025]] ) -> 1 | AJ14: =SUMIFS('Regional allocations LIVE'!$T:$T, 'Regional allocations LIVE'!$H:$H, $R14, 'Regional allocations LIVE'!$R:$R, ">=" & AJ$4, 'Regional allocations LIVE'!$R:$R, "<=" & Table14[[#Headers],[30/11/2025]] ) -> 0 | AK14: =SUMIFS('Regional allocations LIVE'!$T:$T, 'Regional allocations LIVE'!$H:$H, $R14, 'Regional allocations LIVE'!$R:$R, ">=" & AK$4, 'Regional allocations LIVE'!$R:$R, "<=" & Table14[[#Headers],[31/12/2025]] ) -> 0 | AL14: =SUMIFS('Regional allocations LIVE'!$T:$T, 'Regional allocations LIVE'!$H:$H, $R14, 'Regional allocations LIVE'!$R:$R, ">=" & AL$4, 'Regional allocations LIVE'!$R:$R, "<=" & Table14[[#Headers],[30/01/2026]] ) -> 0 | AM14: =SUMIFS('Regional allocations LIVE'!$T:$T, 'Regional allocations LIVE'!$H:$H, $R14, 'Regional allocations LIVE'!$R:$R, ">=" & AM$4, 'Regional allocations LIVE'!$R:$R, "<=" & Table14[[#Headers],[28/02/2026]] ) -> 0 | AN14: =SUMIFS('Regional allocations LIVE'!$T:$T, 'Regional allocations LIVE'!$H:$H, $R14, 'Regional allocations LIVE'!$R:$R, ">=" & AN$4, 'Regional allocations LIVE'!$R:$R, "<=" & Table14[[#Headers],[31/03/2026]] ) -> 0 | AO14: =SUMIFS('Regional allocations LIVE'!$T:$T, 'Regional allocations LIVE'!$H:$H, $R14, 'Regional allocations LIVE'!$R:$R, ">=" & AO$4, 'Regional allocations LIVE'!$R:$R, "<=" & Table14[[#Headers],[30/04/2026]] ) -> 0 | AP14: =SUMIFS('Regional allocations LIVE'!$T:$T, 'Regional allocations LIVE'!$H:$H, $R14, 'Regional allocations LIVE'!$R:$R, ">=" & AP$4, 'Regional allocations LIVE'!$R:$R, "<=" & Table14[[#Headers],[31/05/2026]] ) -> 0 | AQ14: =SUMIFS('Regional allocations LIVE'!$T:$T, 'Regional allocations LIVE'!$H:$H, $R14, 'Regional allocations LIVE'!$R:$R, ">=" & AQ$4, 'Regional allocations LIVE'!$R:$R, "<=" & Table14[[#Headers],[30/06/2026]] ) -> 0 | AR14: =SUMIFS('Regional allocations LIVE'!$T:$T, 'Regional allocations LIVE'!$H:$H, $R14, 'Regional allocations LIVE'!$R:$R, ">=" & AR$4, 'Regional allocations LIVE'!$R:$R, "<=" & Table14[[#Headers],[31/07/2026]] ) -> 0 | AS14: =SUMIFS('Regional allocations LIVE'!$T:$T, 'Regional allocations LIVE'!$H:$H, $R14, 'Regional allocations LIVE'!$R:$R, ">=" & AS$4, 'Regional allocations LIVE'!$R:$R, "<=" & Table14[[#Headers],[31/08/2026]] ) -> 0 | AT14: =SUMIFS('Regional allocations LIVE'!$T:$T, 'Regional allocations LIVE'!$H:$H, $R14, 'Regional allocations LIVE'!$R:$R, ">=" & AT$4, 'Regional allocations LIVE'!$R:$R, "<=" & Table14[[#Headers],[30/09/2026]] ) -> 0 | AU14: =SUMIFS('Regional allocations LIVE'!$T:$T, 'Regional allocations LIVE'!$H:$H, $R14, 'Regional allocations LIVE'!$R:$R, ">=" & AU$4, 'Regional allocations LIVE'!$R:$R, "<=" & Table14[[#Headers],[31/10/2026]] ) -> 0 | AV14: =SUMIFS('Regional allocations LIVE'!$T:$T, 'Regional allocations LIVE'!$H:$H, $R14, 'Regional allocations LIVE'!$R:$R, ">=" & AV$4, 'Regional allocations LIVE'!$R:$R, "<=" & Table14[[#Headers],[30/11/2026]] ) -> 0 | AW14: =SUMIFS('Regional allocations LIVE'!$T:$T, 'Regional allocations LIVE'!$H:$H, $R14, 'Regional allocations LIVE'!$R:$R, ">=" & AW$4, 'Regional allocations LIVE'!$R:$R, "<=" & Table14[[#Headers],[31/12/2026]] ) -> 0 | AX14: =SUMIFS('Regional allocations LIVE'!$T:$T, 'Regional allocations LIVE'!$H:$H, $R14, 'Regional allocations LIVE'!$R:$R, ">=" & AX$4, 'Regional allocations LIVE'!$R:$R, "<=" & Table14[[#Headers],[30/01/2027]] ) -> 0 | AY14: =SUMIFS('Regional allocations LIVE'!$T:$T, 'Regional allocations LIVE'!$H:$H, $R14, 'Regional allocations LIVE'!$R:$R, ">=" & AY$4, 'Regional allocations LIVE'!$R:$R, "<=" & Table14[[#Headers],[28/02/2027]] ) -> 0 | AZ14: =SUMIFS('Regional allocations LIVE'!$T:$T, 'Regional allocations LIVE'!$H:$H, $R14, 'Regional allocations LIVE'!$R:$R, ">=" & AZ$4, 'Regional allocations LIVE'!$R:$R, "<=" & Table14[[#Headers],[31/03/2027]] ) -> 0 | BA14: =SUMIFS('Regional allocations LIVE'!$T:$T, 'Regional allocations LIVE'!$H:$H, $R14, 'Regional allocations LIVE'!$R:$R, ">=" & BA$4, 'Regional allocations LIVE'!$R:$R, "<=" & Table14[[#Headers],[30/04/2027]] ) -> 0 | BB14: =SUMIFS('Regional allocations LIVE'!$T:$T, 'Regional allocations LIVE'!$H:$H, $R14, 'Regional allocations LIVE'!$R:$R, ">=" & BB$4, 'Regional allocations LIVE'!$R:$R, "<=" & Table14[[#Headers],[31/05/2027]] ) -> 0 | BC14: =SUMIFS('Regional allocations LIVE'!$T:$T, 'Regional allocations LIVE'!$H:$H, $R14, 'Regional allocations LIVE'!$R:$R, ">=" & BC$4, 'Regional allocations LIVE'!$R:$R, "<=" & Table14[[#Headers],[30/06/2027]] ) -> 0 | BD14: =SUMIFS('Regional allocations LIVE'!$T:$T, 'Regional allocations LIVE'!$H:$H, $R14, 'Regional allocations LIVE'!$R:$R, ">=" & BD$4, 'Regional allocations LIVE'!$R:$R, "<=" & Table14[[#Headers],[31/07/2027]] ) -> 0 | BE14: =SUMIFS('Regional allocations LIVE'!$T:$T, 'Regional allocations LIVE'!$H:$H, $R14, 'Regional allocations LIVE'!$R:$R, ">=" & BE$4, 'Regional allocations LIVE'!$R:$R, "<=" & Table14[[#Headers],[31/08/2027]] ) -> 0 | BF14: =SUMIFS('Regional allocations LIVE'!$T:$T, 'Regional allocations LIVE'!$H:$H, $R14, 'Regional allocations LIVE'!$R:$R, ">=" & BF$4, 'Regional allocations LIVE'!$R:$R, "<=" & Table14[[#Headers],[30/09/2027]] ) -> 0 | BG14: =SUMIFS('Regional allocations LIVE'!$T:$T, 'Regional allocations LIVE'!$H:$H, $R14, 'Regional allocations LIVE'!$R:$R, ">=" & BG$4, 'Regional allocations LIVE'!$R:$R, "<=" & Table14[[#Headers],[31/10/2027]] ) -> 0
B15: Clever Cloud | C15: 4 | R15: Total | Z15: =SUM(Table14[30/01/2025]) -> 4 | AA15: =SUM(Table14[28/02/2025]) -> 3 | AB15: =SUM(Table14[31/03/2025]) -> 1 | AC15: =SUM(Table14[30/04/2025]) -> 3 | AD15: =SUM(Table14[31/05/2025]) -> 2 | AE15: =SUM(Table14[30/06/2025]) -> 6 | AF15: =SUM(Table14[31/07/2025]) -> 2 | AG15: =SUM(Table14[31/08/2025]) -> 2 | AH15: =SUM(Table14[30/09/2025]) -> 2.8 | AI15: =SUM(Table14[31/10/2025]) -> 4 | AJ15: =SUM(Table14[30/11/2025]) -> 1 | AK15: =SUM(Table14[31/12/2025]) -> 1 | AL15: =SUM(Table14[30/01/2026]) -> 1 | AM15: =SUM(Table14[28/02/2026]) -> 0 | AN15: =SUM(Table14[31/03/2026]) -> 0 | AO15: =SUM(Table14[30/04/2026]) -> 0 | AP15: =SUM(Table14[31/05/2026]) -> 0 | AQ15: =SUM(Table14[30/06/2026]) -> 0 | AR15: =SUM(Table14[31/07/2026]) -> 0 | AS15: =SUM(Table14[31/08/2026]) -> 0 | AT15: =SUM(Table14[30/09/2026]) -> 0 | AU15: =SUM(Table14[31/10/2026]) -> 0 | AV15: =SUM(Table14[30/11/2026]) -> 0 | AW15: =SUM(Table14[31/12/2026]) -> 0 | AX15: =SUM(Table14[30/01/2027]) -> 0 | AY15: =SUM(Table14[28/02/2027]) -> 0 | AZ15: =SUM(Table14[31/03/2027]) -> 0 | BA15: =SUM(Table14[30/04/2027]) -> 0 | BB15: =SUM(Table14[31/05/2027]) -> 0 | BC15: =SUM(Table14[30/06/2027]) -> 0 | BD15: =SUM(Table14[31/07/2027]) -> 0 | BE15: =SUM(Table14[31/08/2027]) -> 0 | BF15: =SUM(Table14[30/09/2027]) -> 0 | BG15: =SUM(Table14[31/10/2027]) -> 0
H16: Data, AI & Consulting | I16: =COUNTIFS('Regional allocations LIVE'!H:H,Table1116[[#This Row],[Business Unit]],'Regional allocations LIVE'!R:R,"") -> 0 | M16: =COUNTIFS('Regional allocations LIVE'!H:H,Table1116[[#This Row],[Business Unit]],'Regional allocations LIVE'!U:U,"Y",'Regional allocations LIVE'!R:R,"") -> 0 | N16: =Table1116[[#This Row],[Headcount]]-Table1116[[#This Row],[Contractors]] -> 0 | O16: =Table1116[[#This Row],[Perm Headcount (minus contractors)]]+Table1116[[#This Row],[Vaccancies to backfill]]+Table1116[[#This Row],[Vaccancies for new roles]] -> 0 | R16: New starters
B17: Summary by office | R17: Business Unit | S17: 30/06/2024 | T17: 31/07/2024 | U17: 31/08/2024 | V17: 30/09/2024 | W17: 31/10/2024 | X17: 30/11/2024 | Y17: 31/12/2024 | Z17: 30/01/2025 | AA17: 28/02/2025 | AB17: 31/03/2025 | AC17: 30/04/2025 | AD17: 31/05/2025 | AE17: 30/06/2025 | AF17: 31/07/2025 | AG17: 31/08/2025 | AH17: 30/09/2025 | AI17: 31/10/2025 | AJ17: 30/11/2025 | AK17: 31/12/2025 | AL17: 30/01/2026 | AM17: 28/02/2026 | AN17: 31/03/2026 | AO17: 30/04/2026 | AP17: 31/05/2026 | AQ17: 30/06/2026 | AR17: 31/07/2026 | AS17: 31/08/2026 | AT17: 30/09/2026 | AU17: 31/10/2026 | AV17: 30/11/2026 | AW17: 31/12/2026 | AX17: 30/01/2027 | AY17: 28/02/2027 | AZ17: 31/03/2027 | BA17: 30/04/2027 | BB17: 31/05/2027 | BC17: 30/06/2027 | BD17: 31/07/2027 | BE17: 31/08/2027 | BF17: 30/09/2027 | BG17: 31/10/2027
R18: Engineering | S18: 0 | T18: 3 | U18: 1 | V18: 2 | W18: 3 | Z18: 1 | AB18: 1 | AD18: 1 | AE18: 2 | AF18: =SUMIFS('Regional allocations LIVE'!$T:$T, 'Regional allocations LIVE'!$H:$H, $R18, 'Regional allocations LIVE'!$D:$D, ">=" & AF$4, 'Regional allocations LIVE'!$D:$D, "<=" & Table14[[#Headers],[31/07/2025]] ) -> 1 | AG18: =SUMIFS('Regional allocations LIVE'!$T:$T, 'Regional allocations LIVE'!$H:$H, $R18, 'Regional allocations LIVE'!$D:$D, ">=" & AG$4, 'Regional allocations LIVE'!$D:$D, "<=" & Table14[[#Headers],[31/08/2025]] ) -> 0 | AH18: =SUMIFS('Regional allocations LIVE'!$T:$T, 'Regional allocations LIVE'!$H:$H, $R18, 'Regional allocations LIVE'!$D:$D, ">=" & AH$4, 'Regional allocations LIVE'!$D:$D, "<=" & Table14[[#Headers],[30/09/2025]] ) -> 3 | AI18: =SUMIFS('Regional allocations LIVE'!$T:$T, 'Regional allocations LIVE'!$H:$H, $R18, 'Regional allocations LIVE'!$D:$D, ">=" & AI$4, 'Regional allocations LIVE'!$D:$D, "<=" & Table14[[#Headers],[31/10/2025]] ) -> 2 | AJ18: =SUMIFS('Regional allocations LIVE'!$T:$T, 'Regional allocations LIVE'!$H:$H, $R18, 'Regional allocations LIVE'!$D:$D, ">=" & AJ$4, 'Regional allocations LIVE'!$D:$D, "<=" & Table14[[#Headers],[30/11/2025]] ) -> 4 | AK18: =SUMIFS('Regional allocations LIVE'!$T:$T, 'Regional allocations LIVE'!$H:$H, $R18, 'Regional allocations LIVE'!$D:$D, ">=" & AK$4, 'Regional allocations LIVE'!$D:$D, "<=" & Table14[[#Headers],[31/12/2025]] ) -> 1 | AL18: =SUMIFS('Regional allocations LIVE'!$T:$T, 'Regional allocations LIVE'!$H:$H, $R18, 'Regional allocations LIVE'!$D:$D, ">=" & AL$4, 'Regional allocations LIVE'!$D:$D, "<=" & Table14[[#Headers],[30/01/2026]] ) -> 0 | AM18: =SUMIFS('Regional allocations LIVE'!$T:$T, 'Regional allocations LIVE'!$H:$H, $R18, 'Regional allocations LIVE'!$D:$D, ">=" & AM$4, 'Regional allocations LIVE'!$D:$D, "<=" & Table14[[#Headers],[28/02/2026]] ) -> 0 | AN18: =SUMIFS('Regional allocations LIVE'!$T:$T, 'Regional allocations LIVE'!$H:$H, $R18, 'Regional allocations LIVE'!$D:$D, ">=" & AN$4, 'Regional allocations LIVE'!$D:$D, "<=" & Table14[[#Headers],[31/03/2026]] ) -> 0 | AO18: =SUMIFS('Regional allocations LIVE'!$T:$T, 'Regional allocations LIVE'!$H:$H, $R18, 'Regional allocations LIVE'!$D:$D, ">=" & AO$4, 'Regional allocations LIVE'!$D:$D, "<=" & Table14[[#Headers],[30/04/2026]] ) -> 0 | AP18: =SUMIFS('Regional allocations LIVE'!$T:$T, 'Regional allocations LIVE'!$H:$H, $R18, 'Regional allocations LIVE'!$D:$D, ">=" & AP$4, 'Regional allocations LIVE'!$D:$D, "<=" & Table14[[#Headers],[31/05/2026]] ) -> 0 | AQ18: =SUMIFS('Regional allocations LIVE'!$T:$T, 'Regional allocations LIVE'!$H:$H, $R18, 'Regional allocations LIVE'!$D:$D, ">=" & AQ$4, 'Regional allocations LIVE'!$D:$D, "<=" & Table14[[#Headers],[30/06/2026]] ) -> 0 | AR18: =SUMIFS('Regional allocations LIVE'!$T:$T, 'Regional allocations LIVE'!$H:$H, $R18, 'Regional allocations LIVE'!$D:$D, ">=" & AR$4, 'Regional allocations LIVE'!$D:$D, "<=" & Table14[[#Headers],[31/07/2026]] ) -> 0 | AS18: =SUMIFS('Regional allocations LIVE'!$T:$T, 'Regional allocations LIVE'!$H:$H, $R18, 'Regional allocations LIVE'!$D:$D, ">=" & AS$4, 'Regional allocations LIVE'!$D:$D, "<=" & Table14[[#Headers],[31/08/2026]] ) -> 0 | AT18: =SUMIFS('Regional allocations LIVE'!$T:$T, 'Regional allocations LIVE'!$H:$H, $R18, 'Regional allocations LIVE'!$D:$D, ">=" & AT$4, 'Regional allocations LIVE'!$D:$D, "<=" & Table14[[#Headers],[30/09/2026]] ) -> 0 | AU18: =SUMIFS('Regional allocations LIVE'!$T:$T, 'Regional allocations LIVE'!$H:$H, $R18, 'Regional allocations LIVE'!$D:$D, ">=" & AU$4, 'Regional allocations LIVE'!$D:$D, "<=" & Table14[[#Headers],[31/10/2026]] ) -> 0 | AV18: =SUMIFS('Regional allocations LIVE'!$T:$T, 'Regional allocations LIVE'!$H:$H, $R18, 'Regional allocations LIVE'!$D:$D, ">=" & AV$4, 'Regional allocations LIVE'!$D:$D, "<=" & Table14[[#Headers],[30/11/2026]] ) -> 0 | AW18: =SUMIFS('Regional allocations LIVE'!$T:$T, 'Regional allocations LIVE'!$H:$H, $R18, 'Regional allocations LIVE'!$D:$D, ">=" & AW$4, 'Regional allocations LIVE'!$D:$D, "<=" & Table14[[#Headers],[31/12/2026]] ) -> 0 | AX18: =SUMIFS('Regional allocations LIVE'!$T:$T, 'Regional allocations LIVE'!$H:$H, $R18, 'Regional allocations LIVE'!$D:$D, ">=" & AX$4, 'Regional allocations LIVE'!$D:$D, "<=" & Table14[[#Headers],[30/01/2027]] ) -> 0 | AY18: =SUMIFS('Regional allocations LIVE'!$T:$T, 'Regional allocations LIVE'!$H:$H, $R18, 'Regional allocations LIVE'!$D:$D, ">=" & AY$4, 'Regional allocations LIVE'!$D:$D, "<=" & Table14[[#Headers],[28/02/2027]] ) -> 0 | AZ18: =SUMIFS('Regional allocations LIVE'!$T:$T, 'Regional allocations LIVE'!$H:$H, $R18, 'Regional allocations LIVE'!$D:$D, ">=" & AZ$4, 'Regional allocations LIVE'!$D:$D, "<=" & Table14[[#Headers],[31/03/2027]] ) -> 0 | BA18: =SUMIFS('Regional allocations LIVE'!$T:$T, 'Regional allocations LIVE'!$H:$H, $R18, 'Regional allocations LIVE'!$D:$D, ">=" & BA$4, 'Regional allocations LIVE'!$D:$D, "<=" & Table14[[#Headers],[30/04/2027]] ) -> 0 | BB18: =SUMIFS('Regional allocations LIVE'!$T:$T, 'Regional allocations LIVE'!$H:$H, $R18, 'Regional allocations LIVE'!$D:$D, ">=" & BB$4, 'Regional allocations LIVE'!$D:$D, "<=" & Table14[[#Headers],[31/05/2027]] ) -> 0 | BC18: =SUMIFS('Regional allocations LIVE'!$T:$T, 'Regional allocations LIVE'!$H:$H, $R18, 'Regional allocations LIVE'!$D:$D, ">=" & BC$4, 'Regional allocations LIVE'!$D:$D, "<=" & Table14[[#Headers],[30/06/2027]] ) -> 0 | BD18: =SUMIFS('Regional allocations LIVE'!$T:$T, 'Regional allocations LIVE'!$H:$H, $R18, 'Regional allocations LIVE'!$D:$D, ">=" & BD$4, 'Regional allocations LIVE'!$D:$D, "<=" & Table14[[#Headers],[31/07/2027]] ) -> 0 | BE18: =SUMIFS('Regional allocations LIVE'!$T:$T, 'Regional allocations LIVE'!$H:$H, $R18, 'Regional allocations LIVE'!$D:$D, ">=" & BE$4, 'Regional allocations LIVE'!$D:$D, "<=" & Table14[[#Headers],[31/08/2027]] ) -> 0 | BF18: =SUMIFS('Regional allocations LIVE'!$T:$T, 'Regional allocations LIVE'!$H:$H, $R18, 'Regional allocations LIVE'!$D:$D, ">=" & BF$4, 'Regional allocations LIVE'!$D:$D, "<=" & Table14[[#Headers],[30/09/2027]] ) -> 0 | BG18: =SUMIFS('Regional allocations LIVE'!$T:$T, 'Regional allocations LIVE'!$H:$H, $R18, 'Regional allocations LIVE'!$D:$D, ">=" & BG$4, 'Regional allocations LIVE'!$D:$D, "<=" & Table14[[#Headers],[31/10/2027]] ) -> 0
B19: Office | C19: Headcount | J19: Regional Headcount | L19: Regional Headcount with Vaccencies filled | R19: Sales | S19: 0 | T19: 0 | U19: 0 | V19: 0 | W19: 0 | AF19: =SUMIFS('Regional allocations LIVE'!$T:$T, 'Regional allocations LIVE'!$H:$H, $R19, 'Regional allocations LIVE'!$D:$D, ">=" & AF$4, 'Regional allocations LIVE'!$D:$D, "<=" & Table14[[#Headers],[31/07/2025]] ) -> 0 | AG19: =SUMIFS('Regional allocations LIVE'!$T:$T, 'Regional allocations LIVE'!$H:$H, $R19, 'Regional allocations LIVE'!$D:$D, ">=" & AG$4, 'Regional allocations LIVE'!$D:$D, "<=" & Table14[[#Headers],[31/08/2025]] ) -> 0 | AH19: =SUMIFS('Regional allocations LIVE'!$T:$T, 'Regional allocations LIVE'!$H:$H, $R19, 'Regional allocations LIVE'!$D:$D, ">=" & AH$4, 'Regional allocations LIVE'!$D:$D, "<=" & Table14[[#Headers],[30/09/2025]] ) -> 0 | AI19: =SUMIFS('Regional allocations LIVE'!$T:$T, 'Regional allocations LIVE'!$H:$H, $R19, 'Regional allocations LIVE'!$D:$D, ">=" & AI$4, 'Regional allocations LIVE'!$D:$D, "<=" & Table14[[#Headers],[31/10/2025]] ) -> 0 | AJ19: =SUMIFS('Regional allocations LIVE'!$T:$T, 'Regional allocations LIVE'!$H:$H, $R19, 'Regional allocations LIVE'!$D:$D, ">=" & AJ$4, 'Regional allocations LIVE'!$D:$D, "<=" & Table14[[#Headers],[30/11/2025]] ) -> 0 | AK19: =SUMIFS('Regional allocations LIVE'!$T:$T, 'Regional allocations LIVE'!$H:$H, $R19, 'Regional allocations LIVE'!$D:$D, ">=" & AK$4, 'Regional allocations LIVE'!$D:$D, "<=" & Table14[[#Headers],[31/12/2025]] ) -> 0 | AL19: =SUMIFS('Regional allocations LIVE'!$T:$T, 'Regional allocations LIVE'!$H:$H, $R19, 'Regional allocations LIVE'!$D:$D, ">=" & AL$4, 'Regional allocations LIVE'!$D:$D, "<=" & Table14[[#Headers],[30/01/2026]] ) -> 0 | AM19: =SUMIFS('Regional allocations LIVE'!$T:$T, 'Regional allocations LIVE'!$H:$H, $R19, 'Regional allocations LIVE'!$D:$D, ">=" & AM$4, 'Regional allocations LIVE'!$D:$D, "<=" & Table14[[#Headers],[28/02/2026]] ) -> 0 | AN19: =SUMIFS('Regional allocations LIVE'!$T:$T, 'Regional allocations LIVE'!$H:$H, $R19, 'Regional allocations LIVE'!$D:$D, ">=" & AN$4, 'Regional allocations LIVE'!$D:$D, "<=" & Table14[[#Headers],[31/03/2026]] ) -> 0 | AO19: =SUMIFS('Regional allocations LIVE'!$T:$T, 'Regional allocations LIVE'!$H:$H, $R19, 'Regional allocations LIVE'!$D:$D, ">=" & AO$4, 'Regional allocations LIVE'!$D:$D, "<=" & Table14[[#Headers],[30/04/2026]] ) -> 0 | AP19: =SUMIFS('Regional allocations LIVE'!$T:$T, 'Regional allocations LIVE'!$H:$H, $R19, 'Regional allocations LIVE'!$D:$D, ">=" & AP$4, 'Regional allocations LIVE'!$D:$D, "<=" & Table14[[#Headers],[31/05/2026]] ) -> 0 | AQ19: =SUMIFS('Regional allocations LIVE'!$T:$T, 'Regional allocations LIVE'!$H:$H, $R19, 'Regional allocations LIVE'!$D:$D, ">=" & AQ$4, 'Regional allocations LIVE'!$D:$D, "<=" & Table14[[#Headers],[30/06/2026]] ) -> 0 | AR19: =SUMIFS('Regional allocations LIVE'!$T:$T, 'Regional allocations LIVE'!$H:$H, $R19, 'Regional allocations LIVE'!$D:$D, ">=" & AR$4, 'Regional allocations LIVE'!$D:$D, "<=" & Table14[[#Headers],[31/07/2026]] ) -> 0 | AS19: =SUMIFS('Regional allocations LIVE'!$T:$T, 'Regional allocations LIVE'!$H:$H, $R19, 'Regional allocations LIVE'!$D:$D, ">=" & AS$4, 'Regional allocations LIVE'!$D:$D, "<=" & Table14[[#Headers],[31/08/2026]] ) -> 0 | AT19: =SUMIFS('Regional allocations LIVE'!$T:$T, 'Regional allocations LIVE'!$H:$H, $R19, 'Regional allocations LIVE'!$D:$D, ">=" & AT$4, 'Regional allocations LIVE'!$D:$D, "<=" & Table14[[#Headers],[30/09/2026]] ) -> 0 | AU19: =SUMIFS('Regional allocations LIVE'!$T:$T, 'Regional allocations LIVE'!$H:$H, $R19, 'Regional allocations LIVE'!$D:$D, ">=" & AU$4, 'Regional allocations LIVE'!$D:$D, "<=" & Table14[[#Headers],[31/10/2026]] ) -> 0 | AV19: =SUMIFS('Regional allocations LIVE'!$T:$T, 'Regional allocations LIVE'!$H:$H, $R19, 'Regional allocations LIVE'!$D:$D, ">=" & AV$4, 'Regional allocations LIVE'!$D:$D, "<=" & Table14[[#Headers],[30/11/2026]] ) -> 0 | AW19: =SUMIFS('Regional allocations LIVE'!$T:$T, 'Regional allocations LIVE'!$H:$H, $R19, 'Regional allocations LIVE'!$D:$D, ">=" & AW$4, 'Regional allocations LIVE'!$D:$D, "<=" & Table14[[#Headers],[31/12/2026]] ) -> 0 | AX19: =SUMIFS('Regional allocations LIVE'!$T:$T, 'Regional allocations LIVE'!$H:$H, $R19, 'Regional allocations LIVE'!$D:$D, ">=" & AX$4, 'Regional allocations LIVE'!$D:$D, "<=" & Table14[[#Headers],[30/01/2027]] ) -> 0 | AY19: =SUMIFS('Regional allocations LIVE'!$T:$T, 'Regional allocations LIVE'!$H:$H, $R19, 'Regional allocations LIVE'!$D:$D, ">=" & AY$4, 'Regional allocations LIVE'!$D:$D, "<=" & Table14[[#Headers],[28/02/2027]] ) -> 0 | AZ19: =SUMIFS('Regional allocations LIVE'!$T:$T, 'Regional allocations LIVE'!$H:$H, $R19, 'Regional allocations LIVE'!$D:$D, ">=" & AZ$4, 'Regional allocations LIVE'!$D:$D, "<=" & Table14[[#Headers],[31/03/2027]] ) -> 0 | BA19: =SUMIFS('Regional allocations LIVE'!$T:$T, 'Regional allocations LIVE'!$H:$H, $R19, 'Regional allocations LIVE'!$D:$D, ">=" & BA$4, 'Regional allocations LIVE'!$D:$D, "<=" & Table14[[#Headers],[30/04/2027]] ) -> 0 | BB19: =SUMIFS('Regional allocations LIVE'!$T:$T, 'Regional allocations LIVE'!$H:$H, $R19, 'Regional allocations LIVE'!$D:$D, ">=" & BB$4, 'Regional allocations LIVE'!$D:$D, "<=" & Table14[[#Headers],[31/05/2027]] ) -> 0 | BC19: =SUMIFS('Regional allocations LIVE'!$T:$T, 'Regional allocations LIVE'!$H:$H, $R19, 'Regional allocations LIVE'!$D:$D, ">=" & BC$4, 'Regional allocations LIVE'!$D:$D, "<=" & Table14[[#Headers],[30/06/2027]] ) -> 0 | BD19: =SUMIFS('Regional allocations LIVE'!$T:$T, 'Regional allocations LIVE'!$H:$H, $R19, 'Regional allocations LIVE'!$D:$D, ">=" & BD$4, 'Regional allocations LIVE'!$D:$D, "<=" & Table14[[#Headers],[31/07/2027]] ) -> 0 | BE19: =SUMIFS('Regional allocations LIVE'!$T:$T, 'Regional allocations LIVE'!$H:$H, $R19, 'Regional allocations LIVE'!$D:$D, ">=" & BE$4, 'Regional allocations LIVE'!$D:$D, "<=" & Table14[[#Headers],[31/08/2027]] ) -> 0 | BF19: =SUMIFS('Regional allocations LIVE'!$T:$T, 'Regional allocations LIVE'!$H:$H, $R19, 'Regional allocations LIVE'!$D:$D, ">=" & BF$4, 'Regional allocations LIVE'!$D:$D, "<=" & Table14[[#Headers],[30/09/2027]] ) -> 0 | BG19: =SUMIFS('Regional allocations LIVE'!$T:$T, 'Regional allocations LIVE'!$H:$H, $R19, 'Regional allocations LIVE'!$D:$D, ">=" & BG$4, 'Regional allocations LIVE'!$D:$D, "<=" & Table14[[#Headers],[31/10/2027]] ) -> 0
B20: New Zealand | C20: 139 | E20: =SUM(Table12[Headcount]) -> #REF! | J20: =I11+I12+I14+2 -> 108 | L20: =J20+J11+J12+J14 -> 115 | R20: Shared Services | S20: 0 | T20: 0 | U20: 0 | V20: 1 | W20: 0 | AC20: 1 | AF20: =SUMIFS('Regional allocations LIVE'!$T:$T, 'Regional allocations LIVE'!$H:$H, $R20, 'Regional allocations LIVE'!$D:$D, ">=" & AF$4, 'Regional allocations LIVE'!$D:$D, "<=" & Table14[[#Headers],[31/07/2025]] ) -> 0 | AG20: =SUMIFS('Regional allocations LIVE'!$T:$T, 'Regional allocations LIVE'!$H:$H, $R20, 'Regional allocations LIVE'!$D:$D, ">=" & AG$4, 'Regional allocations LIVE'!$D:$D, "<=" & Table14[[#Headers],[31/08/2025]] ) -> 0 | AH20: =SUMIFS('Regional allocations LIVE'!$T:$T, 'Regional allocations LIVE'!$H:$H, $R20, 'Regional allocations LIVE'!$D:$D, ">=" & AH$4, 'Regional allocations LIVE'!$D:$D, "<=" & Table14[[#Headers],[30/09/2025]] ) -> 0 | AI20: =SUMIFS('Regional allocations LIVE'!$T:$T, 'Regional allocations LIVE'!$H:$H, $R20, 'Regional allocations LIVE'!$D:$D, ">=" & AI$4, 'Regional allocations LIVE'!$D:$D, "<=" & Table14[[#Headers],[31/10/2025]] ) -> 1 | AJ20: =SUMIFS('Regional allocations LIVE'!$T:$T, 'Regional allocations LIVE'!$H:$H, $R20, 'Regional allocations LIVE'!$D:$D, ">=" & AJ$4, 'Regional allocations LIVE'!$D:$D, "<=" & Table14[[#Headers],[30/11/2025]] ) -> 0 | AK20: =SUMIFS('Regional allocations LIVE'!$T:$T, 'Regional allocations LIVE'!$H:$H, $R20, 'Regional allocations LIVE'!$D:$D, ">=" & AK$4, 'Regional allocations LIVE'!$D:$D, "<=" & Table14[[#Headers],[31/12/2025]] ) -> 0 | AL20: =SUMIFS('Regional allocations LIVE'!$T:$T, 'Regional allocations LIVE'!$H:$H, $R20, 'Regional allocations LIVE'!$D:$D, ">=" & AL$4, 'Regional allocations LIVE'!$D:$D, "<=" & Table14[[#Headers],[30/01/2026]] ) -> 0 | AM20: =SUMIFS('Regional allocations LIVE'!$T:$T, 'Regional allocations LIVE'!$H:$H, $R20, 'Regional allocations LIVE'!$D:$D, ">=" & AM$4, 'Regional allocations LIVE'!$D:$D, "<=" & Table14[[#Headers],[28/02/2026]] ) -> 0 | AN20: =SUMIFS('Regional allocations LIVE'!$T:$T, 'Regional allocations LIVE'!$H:$H, $R20, 'Regional allocations LIVE'!$D:$D, ">=" & AN$4, 'Regional allocations LIVE'!$D:$D, "<=" & Table14[[#Headers],[31/03/2026]] ) -> 0 | AO20: =SUMIFS('Regional allocations LIVE'!$T:$T, 'Regional allocations LIVE'!$H:$H, $R20, 'Regional allocations LIVE'!$D:$D, ">=" & AO$4, 'Regional allocations LIVE'!$D:$D, "<=" & Table14[[#Headers],[30/04/2026]] ) -> 0 | AP20: =SUMIFS('Regional allocations LIVE'!$T:$T, 'Regional allocations LIVE'!$H:$H, $R20, 'Regional allocations LIVE'!$D:$D, ">=" & AP$4, 'Regional allocations LIVE'!$D:$D, "<=" & Table14[[#Headers],[31/05/2026]] ) -> 0 | AQ20: =SUMIFS('Regional allocations LIVE'!$T:$T, 'Regional allocations LIVE'!$H:$H, $R20, 'Regional allocations LIVE'!$D:$D, ">=" & AQ$4, 'Regional allocations LIVE'!$D:$D, "<=" & Table14[[#Headers],[30/06/2026]] ) -> 0 | AR20: =SUMIFS('Regional allocations LIVE'!$T:$T, 'Regional allocations LIVE'!$H:$H, $R20, 'Regional allocations LIVE'!$D:$D, ">=" & AR$4, 'Regional allocations LIVE'!$D:$D, "<=" & Table14[[#Headers],[31/07/2026]] ) -> 0 | AS20: =SUMIFS('Regional allocations LIVE'!$T:$T, 'Regional allocations LIVE'!$H:$H, $R20, 'Regional allocations LIVE'!$D:$D, ">=" & AS$4, 'Regional allocations LIVE'!$D:$D, "<=" & Table14[[#Headers],[31/08/2026]] ) -> 0 | AT20: =SUMIFS('Regional allocations LIVE'!$T:$T, 'Regional allocations LIVE'!$H:$H, $R20, 'Regional allocations LIVE'!$D:$D, ">=" & AT$4, 'Regional allocations LIVE'!$D:$D, "<=" & Table14[[#Headers],[30/09/2026]] ) -> 0 | AU20: =SUMIFS('Regional allocations LIVE'!$T:$T, 'Regional allocations LIVE'!$H:$H, $R20, 'Regional allocations LIVE'!$D:$D, ">=" & AU$4, 'Regional allocations LIVE'!$D:$D, "<=" & Table14[[#Headers],[31/10/2026]] ) -> 0 | AV20: =SUMIFS('Regional allocations LIVE'!$T:$T, 'Regional allocations LIVE'!$H:$H, $R20, 'Regional allocations LIVE'!$D:$D, ">=" & AV$4, 'Regional allocations LIVE'!$D:$D, "<=" & Table14[[#Headers],[30/11/2026]] ) -> 0 | AW20: =SUMIFS('Regional allocations LIVE'!$T:$T, 'Regional allocations LIVE'!$H:$H, $R20, 'Regional allocations LIVE'!$D:$D, ">=" & AW$4, 'Regional allocations LIVE'!$D:$D, "<=" & Table14[[#Headers],[31/12/2026]] ) -> 0 | AX20: =SUMIFS('Regional allocations LIVE'!$T:$T, 'Regional allocations LIVE'!$H:$H, $R20, 'Regional allocations LIVE'!$D:$D, ">=" & AX$4, 'Regional allocations LIVE'!$D:$D, "<=" & Table14[[#Headers],[30/01/2027]] ) -> 0 | AY20: =SUMIFS('Regional allocations LIVE'!$T:$T, 'Regional allocations LIVE'!$H:$H, $R20, 'Regional allocations LIVE'!$D:$D, ">=" & AY$4, 'Regional allocations LIVE'!$D:$D, "<=" & Table14[[#Headers],[28/02/2027]] ) -> 0 | AZ20: =SUMIFS('Regional allocations LIVE'!$T:$T, 'Regional allocations LIVE'!$H:$H, $R20, 'Regional allocations LIVE'!$D:$D, ">=" & AZ$4, 'Regional allocations LIVE'!$D:$D, "<=" & Table14[[#Headers],[31/03/2027]] ) -> 0 | BA20: =SUMIFS('Regional allocations LIVE'!$T:$T, 'Regional allocations LIVE'!$H:$H, $R20, 'Regional allocations LIVE'!$D:$D, ">=" & BA$4, 'Regional allocations LIVE'!$D:$D, "<=" & Table14[[#Headers],[30/04/2027]] ) -> 0 | BB20: =SUMIFS('Regional allocations LIVE'!$T:$T, 'Regional allocations LIVE'!$H:$H, $R20, 'Regional allocations LIVE'!$D:$D, ">=" & BB$4, 'Regional allocations LIVE'!$D:$D, "<=" & Table14[[#Headers],[31/05/2027]] ) -> 0 | BC20: =SUMIFS('Regional allocations LIVE'!$T:$T, 'Regional allocations LIVE'!$H:$H, $R20, 'Regional allocations LIVE'!$D:$D, ">=" & BC$4, 'Regional allocations LIVE'!$D:$D, "<=" & Table14[[#Headers],[30/06/2027]] ) -> 0 | BD20: =SUMIFS('Regional allocations LIVE'!$T:$T, 'Regional allocations LIVE'!$H:$H, $R20, 'Regional allocations LIVE'!$D:$D, ">=" & BD$4, 'Regional allocations LIVE'!$D:$D, "<=" & Table14[[#Headers],[31/07/2027]] ) -> 0 | BE20: =SUMIFS('Regional allocations LIVE'!$T:$T, 'Regional allocations LIVE'!$H:$H, $R20, 'Regional allocations LIVE'!$D:$D, ">=" & BE$4, 'Regional allocations LIVE'!$D:$D, "<=" & Table14[[#Headers],[31/08/2027]] ) -> 0 | BF20: =SUMIFS('Regional allocations LIVE'!$T:$T, 'Regional allocations LIVE'!$H:$H, $R20, 'Regional allocations LIVE'!$D:$D, ">=" & BF$4, 'Regional allocations LIVE'!$D:$D, "<=" & Table14[[#Headers],[30/09/2027]] ) -> 0 | BG20: =SUMIFS('Regional allocations LIVE'!$T:$T, 'Regional allocations LIVE'!$H:$H, $R20, 'Regional allocations LIVE'!$D:$D, ">=" & BG$4, 'Regional allocations LIVE'!$D:$D, "<=" & Table14[[#Headers],[31/10/2027]] ) -> 0
B21: NZ remote | C21: 9 | R21: Europe | S21: 0 | T21: 1 | U21: 1 | V21: 2 | W21: 1 | Y21: 1 | Z21: 2 | AE21: 1 | AF21: =SUMIFS('Regional allocations LIVE'!$T:$T, 'Regional allocations LIVE'!$H:$H, $R21, 'Regional allocations LIVE'!$D:$D, ">=" & AF$4, 'Regional allocations LIVE'!$D:$D, "<=" & Table14[[#Headers],[31/07/2025]] ) -> 0 | AG21: =SUMIFS('Regional allocations LIVE'!$T:$T, 'Regional allocations LIVE'!$H:$H, $R21, 'Regional allocations LIVE'!$D:$D, ">=" & AG$4, 'Regional allocations LIVE'!$D:$D, "<=" & Table14[[#Headers],[31/08/2025]] ) -> 2 | AH21: =SUMIFS('Regional allocations LIVE'!$T:$T, 'Regional allocations LIVE'!$H:$H, $R21, 'Regional allocations LIVE'!$D:$D, ">=" & AH$4, 'Regional allocations LIVE'!$D:$D, "<=" & Table14[[#Headers],[30/09/2025]] ) -> 1 | AI21: =SUMIFS('Regional allocations LIVE'!$T:$T, 'Regional allocations LIVE'!$H:$H, $R21, 'Regional allocations LIVE'!$D:$D, ">=" & AI$4, 'Regional allocations LIVE'!$D:$D, "<=" & Table14[[#Headers],[31/10/2025]] ) -> 1 | AJ21: =SUMIFS('Regional allocations LIVE'!$T:$T, 'Regional allocations LIVE'!$H:$H, $R21, 'Regional allocations LIVE'!$D:$D, ">=" & AJ$4, 'Regional allocations LIVE'!$D:$D, "<=" & Table14[[#Headers],[30/11/2025]] ) -> 1 | AK21: =SUMIFS('Regional allocations LIVE'!$T:$T, 'Regional allocations LIVE'!$H:$H, $R21, 'Regional allocations LIVE'!$D:$D, ">=" & AK$4, 'Regional allocations LIVE'!$D:$D, "<=" & Table14[[#Headers],[31/12/2025]] ) -> 0 | AL21: =SUMIFS('Regional allocations LIVE'!$T:$T, 'Regional allocations LIVE'!$H:$H, $R21, 'Regional allocations LIVE'!$D:$D, ">=" & AL$4, 'Regional allocations LIVE'!$D:$D, "<=" & Table14[[#Headers],[30/01/2026]] ) -> 1 | AM21: =SUMIFS('Regional allocations LIVE'!$T:$T, 'Regional allocations LIVE'!$H:$H, $R21, 'Regional allocations LIVE'!$D:$D, ">=" & AM$4, 'Regional allocations LIVE'!$D:$D, "<=" & Table14[[#Headers],[28/02/2026]] ) -> 0 | AN21: =SUMIFS('Regional allocations LIVE'!$T:$T, 'Regional allocations LIVE'!$H:$H, $R21, 'Regional allocations LIVE'!$D:$D, ">=" & AN$4, 'Regional allocations LIVE'!$D:$D, "<=" & Table14[[#Headers],[31/03/2026]] ) -> 0 | AO21: =SUMIFS('Regional allocations LIVE'!$T:$T, 'Regional allocations LIVE'!$H:$H, $R21, 'Regional allocations LIVE'!$D:$D, ">=" & AO$4, 'Regional allocations LIVE'!$D:$D, "<=" & Table14[[#Headers],[30/04/2026]] ) -> 0 | AP21: =SUMIFS('Regional allocations LIVE'!$T:$T, 'Regional allocations LIVE'!$H:$H, $R21, 'Regional allocations LIVE'!$D:$D, ">=" & AP$4, 'Regional allocations LIVE'!$D:$D, "<=" & Table14[[#Headers],[31/05/2026]] ) -> 0 | AQ21: =SUMIFS('Regional allocations LIVE'!$T:$T, 'Regional allocations LIVE'!$H:$H, $R21, 'Regional allocations LIVE'!$D:$D, ">=" & AQ$4, 'Regional allocations LIVE'!$D:$D, "<=" & Table14[[#Headers],[30/06/2026]] ) -> 0 | AR21: =SUMIFS('Regional allocations LIVE'!$T:$T, 'Regional allocations LIVE'!$H:$H, $R21, 'Regional allocations LIVE'!$D:$D, ">=" & AR$4, 'Regional allocations LIVE'!$D:$D, "<=" & Table14[[#Headers],[31/07/2026]] ) -> 0 | AS21: =SUMIFS('Regional allocations LIVE'!$T:$T, 'Regional allocations LIVE'!$H:$H, $R21, 'Regional allocations LIVE'!$D:$D, ">=" & AS$4, 'Regional allocations LIVE'!$D:$D, "<=" & Table14[[#Headers],[31/08/2026]] ) -> 0 | AT21: =SUMIFS('Regional allocations LIVE'!$T:$T, 'Regional allocations LIVE'!$H:$H, $R21, 'Regional allocations LIVE'!$D:$D, ">=" & AT$4, 'Regional allocations LIVE'!$D:$D, "<=" & Table14[[#Headers],[30/09/2026]] ) -> 0 | AU21: =SUMIFS('Regional allocations LIVE'!$T:$T, 'Regional allocations LIVE'!$H:$H, $R21, 'Regional allocations LIVE'!$D:$D, ">=" & AU$4, 'Regional allocations LIVE'!$D:$D, "<=" & Table14[[#Headers],[31/10/2026]] ) -> 0 | AV21: =SUMIFS('Regional allocations LIVE'!$T:$T, 'Regional allocations LIVE'!$H:$H, $R21, 'Regional allocations LIVE'!$D:$D, ">=" & AV$4, 'Regional allocations LIVE'!$D:$D, "<=" & Table14[[#Headers],[30/11/2026]] ) -> 0 | AW21: =SUMIFS('Regional allocations LIVE'!$T:$T, 'Regional allocations LIVE'!$H:$H, $R21, 'Regional allocations LIVE'!$D:$D, ">=" & AW$4, 'Regional allocations LIVE'!$D:$D, "<=" & Table14[[#Headers],[31/12/2026]] ) -> 0 | AX21: =SUMIFS('Regional allocations LIVE'!$T:$T, 'Regional allocations LIVE'!$H:$H, $R21, 'Regional allocations LIVE'!$D:$D, ">=" & AX$4, 'Regional allocations LIVE'!$D:$D, "<=" & Table14[[#Headers],[30/01/2027]] ) -> 0 | AY21: =SUMIFS('Regional allocations LIVE'!$T:$T, 'Regional allocations LIVE'!$H:$H, $R21, 'Regional allocations LIVE'!$D:$D, ">=" & AY$4, 'Regional allocations LIVE'!$D:$D, "<=" & Table14[[#Headers],[28/02/2027]] ) -> 0 | AZ21: =SUMIFS('Regional allocations LIVE'!$T:$T, 'Regional allocations LIVE'!$H:$H, $R21, 'Regional allocations LIVE'!$D:$D, ">=" & AZ$4, 'Regional allocations LIVE'!$D:$D, "<=" & Table14[[#Headers],[31/03/2027]] ) -> 0 | BA21: =SUMIFS('Regional allocations LIVE'!$T:$T, 'Regional allocations LIVE'!$H:$H, $R21, 'Regional allocations LIVE'!$D:$D, ">=" & BA$4, 'Regional allocations LIVE'!$D:$D, "<=" & Table14[[#Headers],[30/04/2027]] ) -> 0 | BB21: =SUMIFS('Regional allocations LIVE'!$T:$T, 'Regional allocations LIVE'!$H:$H, $R21, 'Regional allocations LIVE'!$D:$D, ">=" & BB$4, 'Regional allocations LIVE'!$D:$D, "<=" & Table14[[#Headers],[31/05/2027]] ) -> 0 | BC21: =SUMIFS('Regional allocations LIVE'!$T:$T, 'Regional allocations LIVE'!$H:$H, $R21, 'Regional allocations LIVE'!$D:$D, ">=" & BC$4, 'Regional allocations LIVE'!$D:$D, "<=" & Table14[[#Headers],[30/06/2027]] ) -> 0 | BD21: =SUMIFS('Regional allocations LIVE'!$T:$T, 'Regional allocations LIVE'!$H:$H, $R21, 'Regional allocations LIVE'!$D:$D, ">=" & BD$4, 'Regional allocations LIVE'!$D:$D, "<=" & Table14[[#Headers],[31/07/2027]] ) -> 0 | BE21: =SUMIFS('Regional allocations LIVE'!$T:$T, 'Regional allocations LIVE'!$H:$H, $R21, 'Regional allocations LIVE'!$D:$D, ">=" & BE$4, 'Regional allocations LIVE'!$D:$D, "<=" & Table14[[#Headers],[31/08/2027]] ) -> 0 | BF21: =SUMIFS('Regional allocations LIVE'!$T:$T, 'Regional allocations LIVE'!$H:$H, $R21, 'Regional allocations LIVE'!$D:$D, ">=" & BF$4, 'Regional allocations LIVE'!$D:$D, "<=" & Table14[[#Headers],[30/09/2027]] ) -> 0 | BG21: =SUMIFS('Regional allocations LIVE'!$T:$T, 'Regional allocations LIVE'!$H:$H, $R21, 'Regional allocations LIVE'!$D:$D, ">=" & BG$4, 'Regional allocations LIVE'!$D:$D, "<=" & Table14[[#Headers],[31/10/2027]] ) -> 0
B22: Cyprus | C22: =GETPIVOTDATA("Employee ID",$B$31,"Office","Cyprus") -> #REF! | J22: Total Headcount | R22: Asia Pacific | S22: 0 | T22: 4 | U22: 0 | V22: 1 | W22: 2 | AA22: 1 | AB22: 1 | AF22: =SUMIFS('Regional allocations LIVE'!$T:$T, 'Regional allocations LIVE'!$H:$H, $R22, 'Regional allocations LIVE'!$D:$D, ">=" & AF$4, 'Regional allocations LIVE'!$D:$D, "<=" & Table14[[#Headers],[31/07/2025]] ) -> 0 | AG22: =SUMIFS('Regional allocations LIVE'!$T:$T, 'Regional allocations LIVE'!$H:$H, $R22, 'Regional allocations LIVE'!$D:$D, ">=" & AG$4, 'Regional allocations LIVE'!$D:$D, "<=" & Table14[[#Headers],[31/08/2025]] ) -> 0 | AH22: =SUMIFS('Regional allocations LIVE'!$T:$T, 'Regional allocations LIVE'!$H:$H, $R22, 'Regional allocations LIVE'!$D:$D, ">=" & AH$4, 'Regional allocations LIVE'!$D:$D, "<=" & Table14[[#Headers],[30/09/2025]] ) -> 0 | AI22: =SUMIFS('Regional allocations LIVE'!$T:$T, 'Regional allocations LIVE'!$H:$H, $R22, 'Regional allocations LIVE'!$D:$D, ">=" & AI$4, 'Regional allocations LIVE'!$D:$D, "<=" & Table14[[#Headers],[31/10/2025]] ) -> 0 | AJ22: =SUMIFS('Regional allocations LIVE'!$T:$T, 'Regional allocations LIVE'!$H:$H, $R22, 'Regional allocations LIVE'!$D:$D, ">=" & AJ$4, 'Regional allocations LIVE'!$D:$D, "<=" & Table14[[#Headers],[30/11/2025]] ) -> 1 | AK22: =SUMIFS('Regional allocations LIVE'!$T:$T, 'Regional allocations LIVE'!$H:$H, $R22, 'Regional allocations LIVE'!$D:$D, ">=" & AK$4, 'Regional allocations LIVE'!$D:$D, "<=" & Table14[[#Headers],[31/12/2025]] ) -> 0 | AL22: =SUMIFS('Regional allocations LIVE'!$T:$T, 'Regional allocations LIVE'!$H:$H, $R22, 'Regional allocations LIVE'!$D:$D, ">=" & AL$4, 'Regional allocations LIVE'!$D:$D, "<=" & Table14[[#Headers],[30/01/2026]] ) -> 0 | AM22: =SUMIFS('Regional allocations LIVE'!$T:$T, 'Regional allocations LIVE'!$H:$H, $R22, 'Regional allocations LIVE'!$D:$D, ">=" & AM$4, 'Regional allocations LIVE'!$D:$D, "<=" & Table14[[#Headers],[28/02/2026]] ) -> 0 | AN22: =SUMIFS('Regional allocations LIVE'!$T:$T, 'Regional allocations LIVE'!$H:$H, $R22, 'Regional allocations LIVE'!$D:$D, ">=" & AN$4, 'Regional allocations LIVE'!$D:$D, "<=" & Table14[[#Headers],[31/03/2026]] ) -> 0 | AO22: =SUMIFS('Regional allocations LIVE'!$T:$T, 'Regional allocations LIVE'!$H:$H, $R22, 'Regional allocations LIVE'!$D:$D, ">=" & AO$4, 'Regional allocations LIVE'!$D:$D, "<=" & Table14[[#Headers],[30/04/2026]] ) -> 0 | AP22: =SUMIFS('Regional allocations LIVE'!$T:$T, 'Regional allocations LIVE'!$H:$H, $R22, 'Regional allocations LIVE'!$D:$D, ">=" & AP$4, 'Regional allocations LIVE'!$D:$D, "<=" & Table14[[#Headers],[31/05/2026]] ) -> 0 | AQ22: =SUMIFS('Regional allocations LIVE'!$T:$T, 'Regional allocations LIVE'!$H:$H, $R22, 'Regional allocations LIVE'!$D:$D, ">=" & AQ$4, 'Regional allocations LIVE'!$D:$D, "<=" & Table14[[#Headers],[30/06/2026]] ) -> 0 | AR22: =SUMIFS('Regional allocations LIVE'!$T:$T, 'Regional allocations LIVE'!$H:$H, $R22, 'Regional allocations LIVE'!$D:$D, ">=" & AR$4, 'Regional allocations LIVE'!$D:$D, "<=" & Table14[[#Headers],[31/07/2026]] ) -> 0 | AS22: =SUMIFS('Regional allocations LIVE'!$T:$T, 'Regional allocations LIVE'!$H:$H, $R22, 'Regional allocations LIVE'!$D:$D, ">=" & AS$4, 'Regional allocations LIVE'!$D:$D, "<=" & Table14[[#Headers],[31/08/2026]] ) -> 0 | AT22: =SUMIFS('Regional allocations LIVE'!$T:$T, 'Regional allocations LIVE'!$H:$H, $R22, 'Regional allocations LIVE'!$D:$D, ">=" & AT$4, 'Regional allocations LIVE'!$D:$D, "<=" & Table14[[#Headers],[30/09/2026]] ) -> 0 | AU22: =SUMIFS('Regional allocations LIVE'!$T:$T, 'Regional allocations LIVE'!$H:$H, $R22, 'Regional allocations LIVE'!$D:$D, ">=" & AU$4, 'Regional allocations LIVE'!$D:$D, "<=" & Table14[[#Headers],[31/10/2026]] ) -> 0 | AV22: =SUMIFS('Regional allocations LIVE'!$T:$T, 'Regional allocations LIVE'!$H:$H, $R22, 'Regional allocations LIVE'!$D:$D, ">=" & AV$4, 'Regional allocations LIVE'!$D:$D, "<=" & Table14[[#Headers],[30/11/2026]] ) -> 0 | AW22: =SUMIFS('Regional allocations LIVE'!$T:$T, 'Regional allocations LIVE'!$H:$H, $R22, 'Regional allocations LIVE'!$D:$D, ">=" & AW$4, 'Regional allocations LIVE'!$D:$D, "<=" & Table14[[#Headers],[31/12/2026]] ) -> 0 | AX22: =SUMIFS('Regional allocations LIVE'!$T:$T, 'Regional allocations LIVE'!$H:$H, $R22, 'Regional allocations LIVE'!$D:$D, ">=" & AX$4, 'Regional allocations LIVE'!$D:$D, "<=" & Table14[[#Headers],[30/01/2027]] ) -> 0 | AY22: =SUMIFS('Regional allocations LIVE'!$T:$T, 'Regional allocations LIVE'!$H:$H, $R22, 'Regional allocations LIVE'!$D:$D, ">=" & AY$4, 'Regional allocations LIVE'!$D:$D, "<=" & Table14[[#Headers],[28/02/2027]] ) -> 0 | AZ22: =SUMIFS('Regional allocations LIVE'!$T:$T, 'Regional allocations LIVE'!$H:$H, $R22, 'Regional allocations LIVE'!$D:$D, ">=" & AZ$4, 'Regional allocations LIVE'!$D:$D, "<=" & Table14[[#Headers],[31/03/2027]] ) -> 0 | BA22: =SUMIFS('Regional allocations LIVE'!$T:$T, 'Regional allocations LIVE'!$H:$H, $R22, 'Regional allocations LIVE'!$D:$D, ">=" & BA$4, 'Regional allocations LIVE'!$D:$D, "<=" & Table14[[#Headers],[30/04/2027]] ) -> 0 | BB22: =SUMIFS('Regional allocations LIVE'!$T:$T, 'Regional allocations LIVE'!$H:$H, $R22, 'Regional allocations LIVE'!$D:$D, ">=" & BB$4, 'Regional allocations LIVE'!$D:$D, "<=" & Table14[[#Headers],[31/05/2027]] ) -> 0 | BC22: =SUMIFS('Regional allocations LIVE'!$T:$T, 'Regional allocations LIVE'!$H:$H, $R22, 'Regional allocations LIVE'!$D:$D, ">=" & BC$4, 'Regional allocations LIVE'!$D:$D, "<=" & Table14[[#Headers],[30/06/2027]] ) -> 0 | BD22: =SUMIFS('Regional allocations LIVE'!$T:$T, 'Regional allocations LIVE'!$H:$H, $R22, 'Regional allocations LIVE'!$D:$D, ">=" & BD$4, 'Regional allocations LIVE'!$D:$D, "<=" & Table14[[#Headers],[31/07/2027]] ) -> 0 | BE22: =SUMIFS('Regional allocations LIVE'!$T:$T, 'Regional allocations LIVE'!$H:$H, $R22, 'Regional allocations LIVE'!$D:$D, ">=" & BE$4, 'Regional allocations LIVE'!$D:$D, "<=" & Table14[[#Headers],[31/08/2027]] ) -> 0 | BF22: =SUMIFS('Regional allocations LIVE'!$T:$T, 'Regional allocations LIVE'!$H:$H, $R22, 'Regional allocations LIVE'!$D:$D, ">=" & BF$4, 'Regional allocations LIVE'!$D:$D, "<=" & Table14[[#Headers],[30/09/2027]] ) -> 0 | BG22: =SUMIFS('Regional allocations LIVE'!$T:$T, 'Regional allocations LIVE'!$H:$H, $R22, 'Regional allocations LIVE'!$D:$D, ">=" & BG$4, 'Regional allocations LIVE'!$D:$D, "<=" & Table14[[#Headers],[31/10/2027]] ) -> 0
B23: Costa Rica | C23: =GETPIVOTDATA("Employee ID",$B$31,"Office","Costa Rica") -> #REF! | J23: =SUM(I8:I16) -> 163 | K23: includes contractors | R23: ELT | S23: 0 | T23: 0 | U23: 0 | V23: 0 | W23: 0 | AF23: =SUMIFS('Regional allocations LIVE'!$T:$T, 'Regional allocations LIVE'!$H:$H, $R23, 'Regional allocations LIVE'!$D:$D, ">=" & AF$4, 'Regional allocations LIVE'!$D:$D, "<=" & Table14[[#Headers],[31/07/2025]] ) -> 0 | AG23: =SUMIFS('Regional allocations LIVE'!$T:$T, 'Regional allocations LIVE'!$H:$H, $R23, 'Regional allocations LIVE'!$D:$D, ">=" & AG$4, 'Regional allocations LIVE'!$D:$D, "<=" & Table14[[#Headers],[31/08/2025]] ) -> 0 | AH23: =SUMIFS('Regional allocations LIVE'!$T:$T, 'Regional allocations LIVE'!$H:$H, $R23, 'Regional allocations LIVE'!$D:$D, ">=" & AH$4, 'Regional allocations LIVE'!$D:$D, "<=" & Table14[[#Headers],[30/09/2025]] ) -> 0 | AI23: =SUMIFS('Regional allocations LIVE'!$T:$T, 'Regional allocations LIVE'!$H:$H, $R23, 'Regional allocations LIVE'!$D:$D, ">=" & AI$4, 'Regional allocations LIVE'!$D:$D, "<=" & Table14[[#Headers],[31/10/2025]] ) -> 0 | AJ23: =SUMIFS('Regional allocations LIVE'!$T:$T, 'Regional allocations LIVE'!$H:$H, $R23, 'Regional allocations LIVE'!$D:$D, ">=" & AJ$4, 'Regional allocations LIVE'!$D:$D, "<=" & Table14[[#Headers],[30/11/2025]] ) -> 0 | AK23: =SUMIFS('Regional allocations LIVE'!$T:$T, 'Regional allocations LIVE'!$H:$H, $R23, 'Regional allocations LIVE'!$D:$D, ">=" & AK$4, 'Regional allocations LIVE'!$D:$D, "<=" & Table14[[#Headers],[31/12/2025]] ) -> 0 | AL23: =SUMIFS('Regional allocations LIVE'!$T:$T, 'Regional allocations LIVE'!$H:$H, $R23, 'Regional allocations LIVE'!$D:$D, ">=" & AL$4, 'Regional allocations LIVE'!$D:$D, "<=" & Table14[[#Headers],[30/01/2026]] ) -> 0 | AM23: =SUMIFS('Regional allocations LIVE'!$T:$T, 'Regional allocations LIVE'!$H:$H, $R23, 'Regional allocations LIVE'!$D:$D, ">=" & AM$4, 'Regional allocations LIVE'!$D:$D, "<=" & Table14[[#Headers],[28/02/2026]] ) -> 0 | AN23: =SUMIFS('Regional allocations LIVE'!$T:$T, 'Regional allocations LIVE'!$H:$H, $R23, 'Regional allocations LIVE'!$D:$D, ">=" & AN$4, 'Regional allocations LIVE'!$D:$D, "<=" & Table14[[#Headers],[31/03/2026]] ) -> 0 | AO23: =SUMIFS('Regional allocations LIVE'!$T:$T, 'Regional allocations LIVE'!$H:$H, $R23, 'Regional allocations LIVE'!$D:$D, ">=" & AO$4, 'Regional allocations LIVE'!$D:$D, "<=" & Table14[[#Headers],[30/04/2026]] ) -> 0 | AP23: =SUMIFS('Regional allocations LIVE'!$T:$T, 'Regional allocations LIVE'!$H:$H, $R23, 'Regional allocations LIVE'!$D:$D, ">=" & AP$4, 'Regional allocations LIVE'!$D:$D, "<=" & Table14[[#Headers],[31/05/2026]] ) -> 0 | AQ23: =SUMIFS('Regional allocations LIVE'!$T:$T, 'Regional allocations LIVE'!$H:$H, $R23, 'Regional allocations LIVE'!$D:$D, ">=" & AQ$4, 'Regional allocations LIVE'!$D:$D, "<=" & Table14[[#Headers],[30/06/2026]] ) -> 0 | AR23: =SUMIFS('Regional allocations LIVE'!$T:$T, 'Regional allocations LIVE'!$H:$H, $R23, 'Regional allocations LIVE'!$D:$D, ">=" & AR$4, 'Regional allocations LIVE'!$D:$D, "<=" & Table14[[#Headers],[31/07/2026]] ) -> 0 | AS23: =SUMIFS('Regional allocations LIVE'!$T:$T, 'Regional allocations LIVE'!$H:$H, $R23, 'Regional allocations LIVE'!$D:$D, ">=" & AS$4, 'Regional allocations LIVE'!$D:$D, "<=" & Table14[[#Headers],[31/08/2026]] ) -> 0 | AT23: =SUMIFS('Regional allocations LIVE'!$T:$T, 'Regional allocations LIVE'!$H:$H, $R23, 'Regional allocations LIVE'!$D:$D, ">=" & AT$4, 'Regional allocations LIVE'!$D:$D, "<=" & Table14[[#Headers],[30/09/2026]] ) -> 0 | AU23: =SUMIFS('Regional allocations LIVE'!$T:$T, 'Regional allocations LIVE'!$H:$H, $R23, 'Regional allocations LIVE'!$D:$D, ">=" & AU$4, 'Regional allocations LIVE'!$D:$D, "<=" & Table14[[#Headers],[31/10/2026]] ) -> 0 | AV23: =SUMIFS('Regional allocations LIVE'!$T:$T, 'Regional allocations LIVE'!$H:$H, $R23, 'Regional allocations LIVE'!$D:$D, ">=" & AV$4, 'Regional allocations LIVE'!$D:$D, "<=" & Table14[[#Headers],[30/11/2026]] ) -> 0 | AW23: =SUMIFS('Regional allocations LIVE'!$T:$T, 'Regional allocations LIVE'!$H:$H, $R23, 'Regional allocations LIVE'!$D:$D, ">=" & AW$4, 'Regional allocations LIVE'!$D:$D, "<=" & Table14[[#Headers],[31/12/2026]] ) -> 0 | AX23: =SUMIFS('Regional allocations LIVE'!$T:$T, 'Regional allocations LIVE'!$H:$H, $R23, 'Regional allocations LIVE'!$D:$D, ">=" & AX$4, 'Regional allocations LIVE'!$D:$D, "<=" & Table14[[#Headers],[30/01/2027]] ) -> 0 | AY23: =SUMIFS('Regional allocations LIVE'!$T:$T, 'Regional allocations LIVE'!$H:$H, $R23, 'Regional allocations LIVE'!$D:$D, ">=" & AY$4, 'Regional allocations LIVE'!$D:$D, "<=" & Table14[[#Headers],[28/02/2027]] ) -> 0 | AZ23: =SUMIFS('Regional allocations LIVE'!$T:$T, 'Regional allocations LIVE'!$H:$H, $R23, 'Regional allocations LIVE'!$D:$D, ">=" & AZ$4, 'Regional allocations LIVE'!$D:$D, "<=" & Table14[[#Headers],[31/03/2027]] ) -> 0 | BA23: =SUMIFS('Regional allocations LIVE'!$T:$T, 'Regional allocations LIVE'!$H:$H, $R23, 'Regional allocations LIVE'!$D:$D, ">=" & BA$4, 'Regional allocations LIVE'!$D:$D, "<=" & Table14[[#Headers],[30/04/2027]] ) -> 0 | BB23: =SUMIFS('Regional allocations LIVE'!$T:$T, 'Regional allocations LIVE'!$H:$H, $R23, 'Regional allocations LIVE'!$D:$D, ">=" & BB$4, 'Regional allocations LIVE'!$D:$D, "<=" & Table14[[#Headers],[31/05/2027]] ) -> 0 | BC23: =SUMIFS('Regional allocations LIVE'!$T:$T, 'Regional allocations LIVE'!$H:$H, $R23, 'Regional allocations LIVE'!$D:$D, ">=" & BC$4, 'Regional allocations LIVE'!$D:$D, "<=" & Table14[[#Headers],[30/06/2027]] ) -> 0 | BD23: =SUMIFS('Regional allocations LIVE'!$T:$T, 'Regional allocations LIVE'!$H:$H, $R23, 'Regional allocations LIVE'!$D:$D, ">=" & BD$4, 'Regional allocations LIVE'!$D:$D, "<=" & Table14[[#Headers],[31/07/2027]] ) -> 0 | BE23: =SUMIFS('Regional allocations LIVE'!$T:$T, 'Regional allocations LIVE'!$H:$H, $R23, 'Regional allocations LIVE'!$D:$D, ">=" & BE$4, 'Regional allocations LIVE'!$D:$D, "<=" & Table14[[#Headers],[31/08/2027]] ) -> 0 | BF23: =SUMIFS('Regional allocations LIVE'!$T:$T, 'Regional allocations LIVE'!$H:$H, $R23, 'Regional allocations LIVE'!$D:$D, ">=" & BF$4, 'Regional allocations LIVE'!$D:$D, "<=" & Table14[[#Headers],[30/09/2027]] ) -> 0 | BG23: =SUMIFS('Regional allocations LIVE'!$T:$T, 'Regional allocations LIVE'!$H:$H, $R23, 'Regional allocations LIVE'!$D:$D, ">=" & BG$4, 'Regional allocations LIVE'!$D:$D, "<=" & Table14[[#Headers],[31/10/2027]] ) -> 0
B24: Remote | C24: 10 | J24: =J23-SUM(Table1116[Contractors]) -> 161 | K24: excludes contractors | R24: Americas | S24: 1 | T24: 0 | U24: 3 | V24: 1 | W24: 0 | AD24: 1 | AF24: =SUMIFS('Regional allocations LIVE'!$T:$T, 'Regional allocations LIVE'!$H:$H, $R24, 'Regional allocations LIVE'!$D:$D, ">=" & AF$4, 'Regional allocations LIVE'!$D:$D, "<=" & Table14[[#Headers],[31/07/2025]] ) -> 1 | AG24: =SUMIFS('Regional allocations LIVE'!$T:$T, 'Regional allocations LIVE'!$H:$H, $R24, 'Regional allocations LIVE'!$D:$D, ">=" & AG$4, 'Regional allocations LIVE'!$D:$D, "<=" & Table14[[#Headers],[31/08/2025]] ) -> 3 | AH24: =SUMIFS('Regional allocations LIVE'!$T:$T, 'Regional allocations LIVE'!$H:$H, $R24, 'Regional allocations LIVE'!$D:$D, ">=" & AH$4, 'Regional allocations LIVE'!$D:$D, "<=" & Table14[[#Headers],[30/09/2025]] ) -> 0 | AI24: =SUMIFS('Regional allocations LIVE'!$T:$T, 'Regional allocations LIVE'!$H:$H, $R24, 'Regional allocations LIVE'!$D:$D, ">=" & AI$4, 'Regional allocations LIVE'!$D:$D, "<=" & Table14[[#Headers],[31/10/2025]] ) -> 0 | AJ24: =SUMIFS('Regional allocations LIVE'!$T:$T, 'Regional allocations LIVE'!$H:$H, $R24, 'Regional allocations LIVE'!$D:$D, ">=" & AJ$4, 'Regional allocations LIVE'!$D:$D, "<=" & Table14[[#Headers],[30/11/2025]] ) -> 2 | AK24: =SUMIFS('Regional allocations LIVE'!$T:$T, 'Regional allocations LIVE'!$H:$H, $R24, 'Regional allocations LIVE'!$D:$D, ">=" & AK$4, 'Regional allocations LIVE'!$D:$D, "<=" & Table14[[#Headers],[31/12/2025]] ) -> 1 | AL24: =SUMIFS('Regional allocations LIVE'!$T:$T, 'Regional allocations LIVE'!$H:$H, $R24, 'Regional allocations LIVE'!$D:$D, ">=" & AL$4, 'Regional allocations LIVE'!$D:$D, "<=" & Table14[[#Headers],[30/01/2026]] ) -> 0 | AM24: =SUMIFS('Regional allocations LIVE'!$T:$T, 'Regional allocations LIVE'!$H:$H, $R24, 'Regional allocations LIVE'!$D:$D, ">=" & AM$4, 'Regional allocations LIVE'!$D:$D, "<=" & Table14[[#Headers],[28/02/2026]] ) -> 0 | AN24: =SUMIFS('Regional allocations LIVE'!$T:$T, 'Regional allocations LIVE'!$H:$H, $R24, 'Regional allocations LIVE'!$D:$D, ">=" & AN$4, 'Regional allocations LIVE'!$D:$D, "<=" & Table14[[#Headers],[31/03/2026]] ) -> 0 | AO24: =SUMIFS('Regional allocations LIVE'!$T:$T, 'Regional allocations LIVE'!$H:$H, $R24, 'Regional allocations LIVE'!$D:$D, ">=" & AO$4, 'Regional allocations LIVE'!$D:$D, "<=" & Table14[[#Headers],[30/04/2026]] ) -> 0 | AP24: =SUMIFS('Regional allocations LIVE'!$T:$T, 'Regional allocations LIVE'!$H:$H, $R24, 'Regional allocations LIVE'!$D:$D, ">=" & AP$4, 'Regional allocations LIVE'!$D:$D, "<=" & Table14[[#Headers],[31/05/2026]] ) -> 0 | AQ24: =SUMIFS('Regional allocations LIVE'!$T:$T, 'Regional allocations LIVE'!$H:$H, $R24, 'Regional allocations LIVE'!$D:$D, ">=" & AQ$4, 'Regional allocations LIVE'!$D:$D, "<=" & Table14[[#Headers],[30/06/2026]] ) -> 0 | AR24: =SUMIFS('Regional allocations LIVE'!$T:$T, 'Regional allocations LIVE'!$H:$H, $R24, 'Regional allocations LIVE'!$D:$D, ">=" & AR$4, 'Regional allocations LIVE'!$D:$D, "<=" & Table14[[#Headers],[31/07/2026]] ) -> 0 | AS24: =SUMIFS('Regional allocations LIVE'!$T:$T, 'Regional allocations LIVE'!$H:$H, $R24, 'Regional allocations LIVE'!$D:$D, ">=" & AS$4, 'Regional allocations LIVE'!$D:$D, "<=" & Table14[[#Headers],[31/08/2026]] ) -> 0 | AT24: =SUMIFS('Regional allocations LIVE'!$T:$T, 'Regional allocations LIVE'!$H:$H, $R24, 'Regional allocations LIVE'!$D:$D, ">=" & AT$4, 'Regional allocations LIVE'!$D:$D, "<=" & Table14[[#Headers],[30/09/2026]] ) -> 0 | AU24: =SUMIFS('Regional allocations LIVE'!$T:$T, 'Regional allocations LIVE'!$H:$H, $R24, 'Regional allocations LIVE'!$D:$D, ">=" & AU$4, 'Regional allocations LIVE'!$D:$D, "<=" & Table14[[#Headers],[31/10/2026]] ) -> 0 | AV24: =SUMIFS('Regional allocations LIVE'!$T:$T, 'Regional allocations LIVE'!$H:$H, $R24, 'Regional allocations LIVE'!$D:$D, ">=" & AV$4, 'Regional allocations LIVE'!$D:$D, "<=" & Table14[[#Headers],[30/11/2026]] ) -> 0 | AW24: =SUMIFS('Regional allocations LIVE'!$T:$T, 'Regional allocations LIVE'!$H:$H, $R24, 'Regional allocations LIVE'!$D:$D, ">=" & AW$4, 'Regional allocations LIVE'!$D:$D, "<=" & Table14[[#Headers],[31/12/2026]] ) -> 0 | AX24: =SUMIFS('Regional allocations LIVE'!$T:$T, 'Regional allocations LIVE'!$H:$H, $R24, 'Regional allocations LIVE'!$D:$D, ">=" & AX$4, 'Regional allocations LIVE'!$D:$D, "<=" & Table14[[#Headers],[30/01/2027]] ) -> 0 | AY24: =SUMIFS('Regional allocations LIVE'!$T:$T, 'Regional allocations LIVE'!$H:$H, $R24, 'Regional allocations LIVE'!$D:$D, ">=" & AY$4, 'Regional allocations LIVE'!$D:$D, "<=" & Table14[[#Headers],[28/02/2027]] ) -> 0 | AZ24: =SUMIFS('Regional allocations LIVE'!$T:$T, 'Regional allocations LIVE'!$H:$H, $R24, 'Regional allocations LIVE'!$D:$D, ">=" & AZ$4, 'Regional allocations LIVE'!$D:$D, "<=" & Table14[[#Headers],[31/03/2027]] ) -> 0 | BA24: =SUMIFS('Regional allocations LIVE'!$T:$T, 'Regional allocations LIVE'!$H:$H, $R24, 'Regional allocations LIVE'!$D:$D, ">=" & BA$4, 'Regional allocations LIVE'!$D:$D, "<=" & Table14[[#Headers],[30/04/2027]] ) -> 0 | BB24: =SUMIFS('Regional allocations LIVE'!$T:$T, 'Regional allocations LIVE'!$H:$H, $R24, 'Regional allocations LIVE'!$D:$D, ">=" & BB$4, 'Regional allocations LIVE'!$D:$D, "<=" & Table14[[#Headers],[31/05/2027]] ) -> 0 | BC24: =SUMIFS('Regional allocations LIVE'!$T:$T, 'Regional allocations LIVE'!$H:$H, $R24, 'Regional allocations LIVE'!$D:$D, ">=" & BC$4, 'Regional allocations LIVE'!$D:$D, "<=" & Table14[[#Headers],[30/06/2027]] ) -> 0 | BD24: =SUMIFS('Regional allocations LIVE'!$T:$T, 'Regional allocations LIVE'!$H:$H, $R24, 'Regional allocations LIVE'!$D:$D, ">=" & BD$4, 'Regional allocations LIVE'!$D:$D, "<=" & Table14[[#Headers],[31/07/2027]] ) -> 0 | BE24: =SUMIFS('Regional allocations LIVE'!$T:$T, 'Regional allocations LIVE'!$H:$H, $R24, 'Regional allocations LIVE'!$D:$D, ">=" & BE$4, 'Regional allocations LIVE'!$D:$D, "<=" & Table14[[#Headers],[31/08/2027]] ) -> 0 | BF24: =SUMIFS('Regional allocations LIVE'!$T:$T, 'Regional allocations LIVE'!$H:$H, $R24, 'Regional allocations LIVE'!$D:$D, ">=" & BF$4, 'Regional allocations LIVE'!$D:$D, "<=" & Table14[[#Headers],[30/09/2027]] ) -> 0 | BG24: =SUMIFS('Regional allocations LIVE'!$T:$T, 'Regional allocations LIVE'!$H:$H, $R24, 'Regional allocations LIVE'!$D:$D, ">=" & BG$4, 'Regional allocations LIVE'!$D:$D, "<=" & Table14[[#Headers],[31/10/2027]] ) -> 0
J25: =SUM(I8:K16)-SUM(Table1116[Contractors]) -> 183 | K25: excludes contractors | R25: Advisory, Data &AI | AE25: 1 | AF25: =SUMIFS('Regional allocations LIVE'!$T:$T, 'Regional allocations LIVE'!$H:$H, $R25, 'Regional allocations LIVE'!$D:$D, ">=" & AF$4, 'Regional allocations LIVE'!$D:$D, "<=" & Table14[[#Headers],[31/07/2025]] ) -> 1 | AG25: =SUMIFS('Regional allocations LIVE'!$T:$T, 'Regional allocations LIVE'!$H:$H, $R25, 'Regional allocations LIVE'!$D:$D, ">=" & AG$4, 'Regional allocations LIVE'!$D:$D, "<=" & Table14[[#Headers],[31/08/2025]] ) -> 0.5 | AH25: =SUMIFS('Regional allocations LIVE'!$T:$T, 'Regional allocations LIVE'!$H:$H, $R25, 'Regional allocations LIVE'!$D:$D, ">=" & AH$4, 'Regional allocations LIVE'!$D:$D, "<=" & Table14[[#Headers],[30/09/2025]] ) -> 0.2 | AI25: =SUMIFS('Regional allocations LIVE'!$T:$T, 'Regional allocations LIVE'!$H:$H, $R25, 'Regional allocations LIVE'!$D:$D, ">=" & AI$4, 'Regional allocations LIVE'!$D:$D, "<=" & Table14[[#Headers],[31/10/2025]] ) -> 0 | AJ25: =SUMIFS('Regional allocations LIVE'!$T:$T, 'Regional allocations LIVE'!$H:$H, $R25, 'Regional allocations LIVE'!$D:$D, ">=" & AJ$4, 'Regional allocations LIVE'!$D:$D, "<=" & Table14[[#Headers],[30/11/2025]] ) -> 0 | AK25: =SUMIFS('Regional allocations LIVE'!$T:$T, 'Regional allocations LIVE'!$H:$H, $R25, 'Regional allocations LIVE'!$D:$D, ">=" & AK$4, 'Regional allocations LIVE'!$D:$D, "<=" & Table14[[#Headers],[31/12/2025]] ) -> 0 | AL25: =SUMIFS('Regional allocations LIVE'!$T:$T, 'Regional allocations LIVE'!$H:$H, $R25, 'Regional allocations LIVE'!$D:$D, ">=" & AL$4, 'Regional allocations LIVE'!$D:$D, "<=" & Table14[[#Headers],[30/01/2026]] ) -> 0 | AM25: =SUMIFS('Regional allocations LIVE'!$T:$T, 'Regional allocations LIVE'!$H:$H, $R25, 'Regional allocations LIVE'!$D:$D, ">=" & AM$4, 'Regional allocations LIVE'!$D:$D, "<=" & Table14[[#Headers],[28/02/2026]] ) -> 0 | AN25: =SUMIFS('Regional allocations LIVE'!$T:$T, 'Regional allocations LIVE'!$H:$H, $R25, 'Regional allocations LIVE'!$D:$D, ">=" & AN$4, 'Regional allocations LIVE'!$D:$D, "<=" & Table14[[#Headers],[31/03/2026]] ) -> 0 | AO25: =SUMIFS('Regional allocations LIVE'!$T:$T, 'Regional allocations LIVE'!$H:$H, $R25, 'Regional allocations LIVE'!$D:$D, ">=" & AO$4, 'Regional allocations LIVE'!$D:$D, "<=" & Table14[[#Headers],[30/04/2026]] ) -> 0 | AP25: =SUMIFS('Regional allocations LIVE'!$T:$T, 'Regional allocations LIVE'!$H:$H, $R25, 'Regional allocations LIVE'!$D:$D, ">=" & AP$4, 'Regional allocations LIVE'!$D:$D, "<=" & Table14[[#Headers],[31/05/2026]] ) -> 0 | AQ25: =SUMIFS('Regional allocations LIVE'!$T:$T, 'Regional allocations LIVE'!$H:$H, $R25, 'Regional allocations LIVE'!$D:$D, ">=" & AQ$4, 'Regional allocations LIVE'!$D:$D, "<=" & Table14[[#Headers],[30/06/2026]] ) -> 0 | AR25: =SUMIFS('Regional allocations LIVE'!$T:$T, 'Regional allocations LIVE'!$H:$H, $R25, 'Regional allocations LIVE'!$D:$D, ">=" & AR$4, 'Regional allocations LIVE'!$D:$D, "<=" & Table14[[#Headers],[31/07/2026]] ) -> 0 | AS25: =SUMIFS('Regional allocations LIVE'!$T:$T, 'Regional allocations LIVE'!$H:$H, $R25, 'Regional allocations LIVE'!$D:$D, ">=" & AS$4, 'Regional allocations LIVE'!$D:$D, "<=" & Table14[[#Headers],[31/08/2026]] ) -> 0 | AT25: =SUMIFS('Regional allocations LIVE'!$T:$T, 'Regional allocations LIVE'!$H:$H, $R25, 'Regional allocations LIVE'!$D:$D, ">=" & AT$4, 'Regional allocations LIVE'!$D:$D, "<=" & Table14[[#Headers],[30/09/2026]] ) -> 0 | AU25: =SUMIFS('Regional allocations LIVE'!$T:$T, 'Regional allocations LIVE'!$H:$H, $R25, 'Regional allocations LIVE'!$D:$D, ">=" & AU$4, 'Regional allocations LIVE'!$D:$D, "<=" & Table14[[#Headers],[31/10/2026]] ) -> 0 | AV25: =SUMIFS('Regional allocations LIVE'!$T:$T, 'Regional allocations LIVE'!$H:$H, $R25, 'Regional allocations LIVE'!$D:$D, ">=" & AV$4, 'Regional allocations LIVE'!$D:$D, "<=" & Table14[[#Headers],[30/11/2026]] ) -> 0 | AW25: =SUMIFS('Regional allocations LIVE'!$T:$T, 'Regional allocations LIVE'!$H:$H, $R25, 'Regional allocations LIVE'!$D:$D, ">=" & AW$4, 'Regional allocations LIVE'!$D:$D, "<=" & Table14[[#Headers],[31/12/2026]] ) -> 0 | AX25: =SUMIFS('Regional allocations LIVE'!$T:$T, 'Regional allocations LIVE'!$H:$H, $R25, 'Regional allocations LIVE'!$D:$D, ">=" & AX$4, 'Regional allocations LIVE'!$D:$D, "<=" & Table14[[#Headers],[30/01/2027]] ) -> 0 | AY25: =SUMIFS('Regional allocations LIVE'!$T:$T, 'Regional allocations LIVE'!$H:$H, $R25, 'Regional allocations LIVE'!$D:$D, ">=" & AY$4, 'Regional allocations LIVE'!$D:$D, "<=" & Table14[[#Headers],[28/02/2027]] ) -> 0 | AZ25: =SUMIFS('Regional allocations LIVE'!$T:$T, 'Regional allocations LIVE'!$H:$H, $R25, 'Regional allocations LIVE'!$D:$D, ">=" & AZ$4, 'Regional allocations LIVE'!$D:$D, "<=" & Table14[[#Headers],[31/03/2027]] ) -> 0 | BA25: =SUMIFS('Regional allocations LIVE'!$T:$T, 'Regional allocations LIVE'!$H:$H, $R25, 'Regional allocations LIVE'!$D:$D, ">=" & BA$4, 'Regional allocations LIVE'!$D:$D, "<=" & Table14[[#Headers],[30/04/2027]] ) -> 0 | BB25: =SUMIFS('Regional allocations LIVE'!$T:$T, 'Regional allocations LIVE'!$H:$H, $R25, 'Regional allocations LIVE'!$D:$D, ">=" & BB$4, 'Regional allocations LIVE'!$D:$D, "<=" & Table14[[#Headers],[31/05/2027]] ) -> 0 | BC25: =SUMIFS('Regional allocations LIVE'!$T:$T, 'Regional allocations LIVE'!$H:$H, $R25, 'Regional allocations LIVE'!$D:$D, ">=" & BC$4, 'Regional allocations LIVE'!$D:$D, "<=" & Table14[[#Headers],[30/06/2027]] ) -> 0 | BD25: =SUMIFS('Regional allocations LIVE'!$T:$T, 'Regional allocations LIVE'!$H:$H, $R25, 'Regional allocations LIVE'!$D:$D, ">=" & BD$4, 'Regional allocations LIVE'!$D:$D, "<=" & Table14[[#Headers],[31/07/2027]] ) -> 0 | BE25: =SUMIFS('Regional allocations LIVE'!$T:$T, 'Regional allocations LIVE'!$H:$H, $R25, 'Regional allocations LIVE'!$D:$D, ">=" & BE$4, 'Regional allocations LIVE'!$D:$D, "<=" & Table14[[#Headers],[31/08/2027]] ) -> 0 | BF25: =SUMIFS('Regional allocations LIVE'!$T:$T, 'Regional allocations LIVE'!$H:$H, $R25, 'Regional allocations LIVE'!$D:$D, ">=" & BF$4, 'Regional allocations LIVE'!$D:$D, "<=" & Table14[[#Headers],[30/09/2027]] ) -> 0 | BG25: =SUMIFS('Regional allocations LIVE'!$T:$T, 'Regional allocations LIVE'!$H:$H, $R25, 'Regional allocations LIVE'!$D:$D, ">=" & BG$4, 'Regional allocations LIVE'!$D:$D, "<=" & Table14[[#Headers],[31/10/2027]] ) -> 0
R26: Total | AC26: =SUM(Table16[30/04/2025]) -> 1 | AD26: =SUM(Table16[31/05/2025]) -> 2 | AE26: =SUM(Table16[30/06/2025]) -> 4 | AF26: =SUM(Table16[31/07/2025]) -> 3 | AG26: =SUM(Table16[31/08/2025]) -> 5.5 | AH26: =SUM(Table16[30/09/2025]) -> 4.2 | AI26: =SUM(Table16[31/10/2025]) -> 4 | AJ26: =SUM(Table16[30/11/2025]) -> 8 | AK26: =SUM(Table16[31/12/2025]) -> 2 | AL26: =SUM(Table16[30/01/2026]) -> 1 | AM26: =SUM(Table16[28/02/2026]) -> 0 | AN26: =SUM(Table16[31/03/2026]) -> 0 | AO26: =SUM(Table16[30/04/2026]) -> 0 | AP26: =SUM(Table16[31/05/2026]) -> 0 | AQ26: =SUM(Table16[30/06/2026]) -> 0 | AR26: =SUM(Table16[31/07/2026]) -> 0 | AS26: =SUM(Table16[31/08/2026]) -> 0 | AT26: =SUM(Table16[30/09/2026]) -> 0 | AU26: =SUM(Table16[31/10/2026]) -> 0 | AV26: =SUM(Table16[30/11/2026]) -> 0 | AW26: =SUM(Table16[31/12/2026]) -> 0 | AX26: =SUM(Table16[30/01/2027]) -> 0 | AY26: =SUM(Table16[28/02/2027]) -> 0 | AZ26: =SUM(Table16[31/03/2027]) -> 0 | BA26: =SUM(Table16[30/04/2027]) -> 0 | BB26: =SUM(Table16[31/05/2027]) -> 0 | BC26: =SUM(Table16[30/06/2027]) -> 0 | BD26: =SUM(Table16[31/07/2027]) -> 0
J27: Target headcount with vaccancies filled | R27: Internal Moves
B28: Summary by office by region | J28: Approx 187 | K28: 175 | L28: Historically averaged 175 | R28: May - pre any transitions | S28: 30/06/2024 | T28: 31/07/2024 | U28: 31/08/2024 | V28: 30/09/2024 | W28: 31/10/2024 | X28: 30/11/2024 | Y28: 31/12/2024 | Z28: 30/01/2025 | AA28: 28/02/2025 | AB28: 31/03/2025 | AC28: 30/04/2025 | AD28: 31/05/2025 | AE28: 30/06/2025 | AF28: 31/07/2025 | AG28: 31/08/2025 | AH28: 30/09/2025 | AI28: 31/10/2025 | AJ28: 30/11/2025 | AK28: 31/12/2025 | AL28: 30/01/2026 | AM28: 28/02/2026 | AN28: 31/03/2026 | AO28: 30/04/2026 | AP28: 31/05/2026 | AQ28: 30/06/2026 | AR28: 31/07/2026 | AS28: 31/08/2026 | AT28: 30/09/2026 | AU28: 31/10/2026 | AV28: 30/11/2026 | AW28: 31/12/2026 | AX28: 30/01/2027 | AY28: 28/02/2027 | AZ28: 31/03/2027 | BA28: 30/04/2027 | BB28: 31/05/2027 | BC28: 30/06/2027 | BD28: 31/07/2027 | BE28: 31/08/2027 | BF28: 30/09/2027 | BG28: 31/10/2027
B29: Leaving Date | C29: (blank) | K29: 5 | L29: new roles in Engineering | Q29: Engineering | R29: 37.2 | V29: -1 | Z29: 0 | AA29: 1 | AB29: -1 | AC29: 1 | AE29: -2 | AG29: 1
K30: 5 | L30: new roles in Americas | Q30: Sales | R30: 6 | T30: -1 | AA30: -1 | AG30: 1
B31: Count of Employee ID | C31: Column Labels | K31: 2 | L31: new roles in DAC | Q31: Shared Services | R31: 18 | AG31: -1
B32: Row Labels | C32: Cyprus | D32: Costa Rica | E32: New Zealand | F32: Remote | G32: NZ Remote | H32: (blank) | L32: Other | Q32: Europe | R32: 48.8 | V32: -2 | Y32: 1 | Z32: -1 | AB32: 1 | AF32: -1
B33: Americas | D33: 9 | E33: 28 | F33: 1 | G33: 1 | Q33: Asia Pacific | R33: 22.75 | S33: -3 | T33: -1 | U33: -4 | V33: 1 | X33: -1 | Z33: 1 | AC33: -1 | AG33: -2
B34: Asia Pacific | E34: 14 | F34: 1 | G34: 2 | K34: =SUM(K28:K32) -> 187 | Q34: ELT | AE34: 0
B35: Clever Cloud | F35: 4 | Q35: Americas | R35: 27 | S35: 3 | T35: 2 | U35: 4 | V35: 2 | X35: 1 | Y35: -1
B36: Engineering | E36: 36 | F36: 4 | Q36: Advisory, Data &AI | AE36: 1.5 | AF36: 1 | AG36: 1
B37: Europe | C37: 8 | E37: 34 | G37: 4 | Q37: Check - Total | R37: =SUM(R29:R35) -> 159.75 | S37: =SUM(S29:S35) -> 0 | T37: =SUM(T29:T35) -> 0 | U37: =SUM(U29:U35) -> 0 | V37: =SUM(V29:V35) -> 0 | W37: =SUM(W29:W35) -> 0 | X37: =SUM(X29:X35) -> 0 | Y37: =SUM(Y29:Y35) -> 0 | ... AD37: =SUM(AD29:AD35) -> 0 | AE37: =SUM(AE29:AE36) -> -0.5 | AF37: =SUM(AF29:AF36) -> 0 | AG37: =SUM(AG29:AG36) -> 0
B38: Sales | E38: 4 | R38: Business Unit Headcount overtime
B39: Shared Services2 | E39: 15 | Q39: Business Unit | R39: 31/05/2024 | S39: 30/06/2024 | T39: 31/07/2024 | U39: 31/08/2024 | V39: 30/09/2024 | W39: 31/10/2024 | X39: 30/11/2024 | Y39: 31/12/2024 | Z39: 30/01/2025 | AA39: 28/02/2025 | AB39: 31/03/2025 | AC39: 30/04/2025 | AD39: 31/05/2025 | AE39: 30/06/2025 | AF39: 31/07/2025 | AG39: 31/08/2025 | AH39: 30/09/2025 | AI39: 31/10/2025 | AJ39: 30/11/2025 | AK39: 31/12/2025 | AL39: 30/01/2026 | AM39: 28/02/2026 | AN39: 31/03/2026 | AO39: 30/04/2026 | AP39: 31/05/2026 | AQ39: 30/06/2026 | AR39: 31/07/2026 | AS39: 31/08/2026 | AT39: 30/09/2026 | AU39: 31/10/2026 | AV39: 30/11/2026 | AW39: 31/12/2026 | AX39: 30/01/2027 | AY39: 28/02/2027 | AZ39: 31/03/2027 | BA39: 30/04/2027 | BB39: 31/05/2027 | BC39: 30/06/2027 | BD39: 31/07/2027 | BE39: 31/08/2027 | BF39: 30/09/2027 | BG39: 31/10/2027
B40: Advisory, Data &AI | E40: 4 | F40: 1 | G40: 2 | Q40: Engineering | R40: =R29 -> 37.2 | S40: =$R29+S18-S6+S29 -> 36.2 | T40: =$R29+SUM(S18:T18)-SUM(S6:T6)+SUM(S29:T29) -> 39.2 | U40: =$R29+SUM(S18:U18)-SUM(S6:U6)+SUM(S29:U29) -> 40.2 | V40: =$R29+SUM(S18:V18)-SUM(S6:V6)+SUM(S29:V29) -> 41.2 | W40: =$R29+SUM(S18:W18)-SUM(S6:W6)+SUM(S29:W29) -> 41.2 | X40: =$R29+SUM(S18:X18)-SUM(S6:X6)+SUM(S29:X29) -> 41.2 | Y40: =$R29+SUM(S18:Y18)-SUM(S6:Y6)+SUM(S29:Y29) -> 40.2 | Z40: =$R29+SUM(S18:Z18)-SUM(S6:Z6)+SUM(S29:Z29) -> 41.2 | AA40: =$R29+SUM(S18:AA18)-SUM(S6:AA6)+SUM(S29:AA29) -> 41.2 | AB40: =$R29+SUM(S18:AB18)-SUM(S6:AB6)+SUM(S29:AB29) -> 41.2 | AC40: =$R29+SUM(S18:AC18)-SUM(S6:AC6)+SUM(S29:AC29) -> 41.2 | AD40: =$R29+SUM(S18:AD18)-SUM(S6:AD6)+SUM(S29:AD29) -> 42.2 | AE40: =$R29+SUM(S18:AE18)-SUM(S6:AE6)+SUM(S29:AE29) -> 41.2 | AF40: =$R29+SUM($S18:AF18)-SUM($S6:AF6)+SUM($S29:AF29) -> 41.2 | AG40: =$R29+SUM($S18:AG18)-SUM($S6:AG6)+SUM($S29:AG29) -> 41.2 | AH40: =$R29+SUM($S18:AH18)-SUM($S6:AH6)+SUM($S29:AH29) -> 42.4 | AI40: =$R29+SUM($S18:AI18)-SUM($S6:AI6)+SUM($S29:AI29) -> 44.4 | AJ40: =$R29+SUM($S18:AJ18)-SUM($S6:AJ6)+SUM($S29:AJ29) -> 48.4 | AK40: =$R29+SUM($S18:AK18)-SUM($S6:AK6)+SUM($S29:AK29) -> 49.4 | AL40: =$R29+SUM($S18:AL18)-SUM($S6:AL6)+SUM($S29:AL29) -> 49.4 | AM40: =$R29+SUM($S18:AM18)-SUM($S6:AM6)+SUM($S29:AM29) -> 49.4 | ... BC40: =$R29+SUM($S18:BC18)-SUM($S6:BC6)+SUM($S29:BC29) -> 49.4
B41: CEO | E41: 1 | Q41: Sales | R41: =R30 -> 6 | S41: =$R30+S19-S7+S30 -> 6 | T41: =$R30+SUM(S19:T19)-SUM(S7:T7)+SUM(S30:T30) -> 5 | U41: =$R30+SUM(S19:U19)-SUM(S7:U7)+SUM(S30:U30) -> 5 | V41: =$R30+SUM(S19:V19)-SUM(S7:V7)+SUM(S30:V30) -> 4 | W41: =$R30+SUM(S19:W19)-SUM(S7:W7)+SUM(S30:W30) -> 4 | X41: =$R30+SUM(S19:X19)-SUM(S7:X7)+SUM(S30:X30) -> 4 | Y41: =$R30+SUM(S19:Y19)-SUM(S7:Y7)+SUM(S30:Y30) -> 4 | Z41: =$R30+SUM(S19:Z19)-SUM(S7:Z7)+SUM(S30:Z30) -> 4 | AA41: =$R30+SUM(S19:AA19)-SUM(S7:AA7)+SUM(S30:AA30) -> 3 | AB41: =$R30+SUM(S19:AB19)-SUM(S7:AB7)+SUM(S30:AB30) -> 3 | AC41: =$R30+SUM(S19:AC19)-SUM(S7:AC7)+SUM(S30:AC30) -> 3 | AD41: =$R30+SUM(S19:AD19)-SUM(S7:AD7)+SUM(S30:AD30) -> 3 | AE41: =$R30+SUM(S19:AE19)-SUM(S7:AE7)+SUM(S30:AE30) -> 3 | AF41: =$R30+SUM($S19:AF19)-SUM($S7:AF7)+SUM($S30:AF30) -> 3 | AG41: =$R30+SUM($S19:AG19)-SUM($S7:AG7)+SUM($S30:AG30) -> 4 | AH41: =$R30+SUM($S19:AH19)-SUM($S7:AH7)+SUM($S30:AH30) -> 4 | AI41: =$R30+SUM($S19:AI19)-SUM($S7:AI7)+SUM($S30:AI30) -> 4 | AJ41: =$R30+SUM($S19:AJ19)-SUM($S7:AJ7)+SUM($S30:AJ30) -> 4 | AK41: =$R30+SUM($S19:AK19)-SUM($S7:AK7)+SUM($S30:AK30) -> 4 | AL41: =$R30+SUM($S19:AL19)-SUM($S7:AL7)+SUM($S30:AL30) -> 4 | AM41: =$R30+SUM($S19:AM19)-SUM($S7:AM7)+SUM($S30:AM30) -> 4 | ... BC41: =$R30+SUM($S19:BC19)-SUM($S7:BC7)+SUM($S30:BC30) -> 4
Q42: Shared Services | R42: =R31 -> 18 | S42: =$R31+S20-S8+S31 -> 18 | T42: =$R31+SUM(S20:T20)-SUM(S8:T8)+SUM(S31:T31) -> 17 | U42: =$R31+SUM(S20:U20)-SUM(S8:U8)+SUM(S31:U31) -> 17 | V42: =$R31+SUM(S20:V20)-SUM(S8:V8)+SUM(S31:V31) -> 17 | W42: =$R31+SUM(S20:W20)-SUM(S8:W8)+SUM(S31:W31) -> 17 | X42: =$R31+SUM(S20:X20)-SUM(S8:X8)+SUM(S31:X31) -> 17 | Y42: =$R31+SUM(S20:Y20)-SUM(S8:Y8)+SUM(S31:Y31) -> 17 | Z42: =$R31+SUM(S20:Z20)-SUM(S8:Z8)+SUM(S31:Z31) -> 16 | AA42: =$R31+SUM(S20:AA20)-SUM(S8:AA8)+SUM(S31:AA31) -> 16 | AB42: =$R31+SUM(S20:AB20)-SUM(S8:AB8)+SUM(S31:AB31) -> 16 | AC42: =$R31+SUM(S20:AC20)-SUM(S8:AC8)+SUM(S31:AC31) -> 16 | AD42: =$R31+SUM(S20:AD20)-SUM(S8:AD8)+SUM(S31:AD31) -> 16 | AE42: =$R31+SUM(S20:AE20)-SUM(S8:AE8)+SUM(S31:AE31) -> 16 | AF42: =$R31+SUM($S20:AF20)-SUM($S8:AF8)+SUM($S31:AF31) -> 16 | AG42: =$R31+SUM($S20:AG20)-SUM($S8:AG8)+SUM($S31:AG31) -> 15 | AH42: =$R31+SUM($S20:AH20)-SUM($S8:AH8)+SUM($S31:AH31) -> 15 | AI42: =$R31+SUM($S20:AI20)-SUM($S8:AI8)+SUM($S31:AI31) -> 16 | AJ42: =$R31+SUM($S20:AJ20)-SUM($S8:AJ8)+SUM($S31:AJ31) -> 16 | AK42: =$R31+SUM($S20:AK20)-SUM($S8:AK8)+SUM($S31:AK31) -> 16 | AL42: =$R31+SUM($S20:AL20)-SUM($S8:AL8)+SUM($S31:AL31) -> 16 | AM42: =$R31+SUM($S20:AM20)-SUM($S8:AM8)+SUM($S31:AM31) -> 16 | ... BC42: =$R31+SUM($S20:BC20)-SUM($S8:BC8)+SUM($S31:BC31) -> 16
Q43: Europe | R43: =R32 -> 48.8 | S43: =$R32+S21-S9+S32 -> 46.8 | T43: =$R32+SUM(S21:T21)-SUM(S9:T9)+SUM(S32:T32) -> 46.8 | U43: =$R32+SUM(S21:U21)-SUM(S9:U9)+SUM(S32:U32) -> 46.8 | V43: =$R32+SUM(S21:V21)-SUM(S9:V9)+SUM(S32:V32) -> 46.8 | W43: =$R32+SUM(S21:W21)-SUM(S9:W9)+SUM(S32:W32) -> 46.8 | X43: =$R32+SUM(S21:X21)-SUM(S9:X9)+SUM(S32:X32) -> 45.8 | Y43: =$R32+SUM(S21:Y21)-SUM(S9:Y9)+SUM(S32:Y32) -> 47.8 | Z43: =$R32+SUM(S21:Z21)-SUM(S9:Z9)+SUM(S32:Z32) -> 47.8 | AA43: =$R32+SUM(S21:AA21)-SUM(S9:AA9)+SUM(S32:AA32) -> 46.8 | AB43: =$R32+SUM(S21:AB21)-SUM(S9:AB9)+SUM(S32:AB32) -> 46.8 | AC43: =$R32+SUM(S21:AC21)-SUM(S9:AC9)+SUM(S32:AC32) -> 45.8 | AD43: =$R32+SUM(S21:AD21)-SUM(S9:AD9)+SUM(S32:AD32) -> 44.8 | AE43: =$R32+SUM(S21:AE21)-SUM(S9:AE9)+SUM(S32:AE32) -> 43.8 | AF43: =$R32+SUM($S21:AF21)-SUM($S9:AF9)+SUM($S32:AF32) -> 42.8 | AG43: =$R32+SUM($S21:AG21)-SUM($S9:AG9)+SUM($S32:AG32) -> 44.8 | AH43: =$R32+SUM($S21:AH21)-SUM($S9:AH9)+SUM($S32:AH32) -> 45.8 | AI43: =$R32+SUM($S21:AI21)-SUM($S9:AI9)+SUM($S32:AI32) -> 45.8 | AJ43: =$R32+SUM($S21:AJ21)-SUM($S9:AJ9)+SUM($S32:AJ32) -> 46.8 | AK43: =$R32+SUM($S21:AK21)-SUM($S9:AK9)+SUM($S32:AK32) -> 46.8 | AL43: =$R32+SUM($S21:AL21)-SUM($S9:AL9)+SUM($S32:AL32) -> 47.8 | AM43: =$R32+SUM($S21:AM21)-SUM($S9:AM9)+SUM($S32:AM32) -> 47.8 | ... BC43: =$R32+SUM($S21:BC21)-SUM($S9:BC9)+SUM($S32:BC32) -> 47.8
Q44: Asia Pacific | R44: =R33 -> 22.75 | S44: =$R33+S22-S10+S33 -> 19.75 | T44: =$R33+SUM(S22:T22)-SUM(S10:T10)+SUM(S33:T33) -> 22.75 | U44: =$R33+SUM(S22:U22)-SUM(S10:U10)+SUM(S33:U33) -> 18.75 | V44: =$R33+SUM(S22:V22)-SUM(S10:V10)+SUM(S33:V33) -> 19.75 | W44: =$R33+SUM(S22:W22)-SUM(S10:W10)+SUM(S33:W33) -> 21.75 | X44: =$R33+SUM(S22:X22)-SUM(S10:X10)+SUM(S33:X33) -> 20.75 | Y44: =$R33+SUM(S22:Y22)-SUM(S10:Y10)+SUM(S33:Y33) -> 19.75 | Z44: =$R33+SUM(S22:Z22)-SUM(S10:Z10)+SUM(S33:Z33) -> 18.75 | AA44: =$R33+SUM(S22:AA22)-SUM(S10:AA10)+SUM(S33:AA33) -> 19.75 | AB44: =$R33+SUM(S22:AB22)-SUM(S10:AB10)+SUM(S33:AB33) -> 20.75 | AC44: =$R33+SUM(S22:AC22)-SUM(S10:AC10)+SUM(S33:AC33) -> 19.75 | AD44: =$R33+SUM(S22:AD22)-SUM(S10:AD10)+SUM(S33:AD33) -> 19.75 | AE44: =$R33+SUM(S22:AE22)-SUM(S10:AE10)+SUM(S33:AE33) -> 18.75 | AF44: =$R33+SUM($S22:AF22)-SUM($S10:AF10)+SUM($S33:AF33) -> 18.75 | AG44: =$R33+SUM($S22:AG22)-SUM($S10:AG10)+SUM($S33:AG33) -> 16.75 | AH44: =$R33+SUM($S22:AH22)-SUM($S10:AH10)+SUM($S33:AH33) -> 16.75 | AI44: =$R33+SUM($S22:AI22)-SUM($S10:AI10)+SUM($S33:AI33) -> 16.75 | AJ44: =$R33+SUM($S22:AJ22)-SUM($S10:AJ10)+SUM($S33:AJ33) -> 17.75 | AK44: =$R33+SUM($S22:AK22)-SUM($S10:AK10)+SUM($S33:AK33) -> 17.75 | AL44: =$R33+SUM($S22:AL22)-SUM($S10:AL10)+SUM($S33:AL33) -> 17.75 | AM44: =$R33+SUM($S22:AM22)-SUM($S10:AM10)+SUM($S33:AM33) -> 17.75 | ... BC44: =$R33+SUM($S22:BC22)-SUM($S10:BC10)+SUM($S33:BC33) -> 17.75
Q45: ELT | AH45: 1
Q46: Americas | R46: =R35 -> 27 | S46: =$R35+S24-S12+S35 -> 31 | T46: =$R35+SUM(S24:T24)-SUM(S12:T12)+SUM(S35:T35) -> 32 | U46: =$R35+SUM(S24:U24)-SUM(S12:U12)+SUM(S35:U35) -> 39 | V46: =$R35+SUM(S24:V24)-SUM(S12:V12)+SUM(S35:V35) -> 41 | W46: =$R35+SUM(S24:W24)-SUM(S12:W12)+SUM(S35:W35) -> 41 | X46: =$R35+SUM(S24:X24)-SUM(S12:X12)+SUM(S35:X35) -> 42 | Y46: =$R35+SUM(S24:Y24)-SUM(S12:Y12)+SUM(S35:Y35) -> 41 | Z46: =$R35+SUM(S24:Z24)-SUM(S12:Z12)+SUM(S35:Z35) -> 41 | AA46: =$R35+SUM(S24:AA24)-SUM(S12:AA12)+SUM(S35:AA35) -> 41 | AB46: =$R35+SUM(S24:AB24)-SUM(S12:AB12)+SUM(S35:AB35) -> 41 | AC46: =$R35+SUM(S24:AC24)-SUM(S12:AC12)+SUM(S35:AC35) -> 41 | AD46: =$R35+SUM(S24:AD24)-SUM(S12:AD12)+SUM(S35:AD35) -> 41 | AE46: =$R35+SUM(S24:AE24)-SUM(S12:AE12)+SUM(S35:AE35) -> 39 | AF46: =$R35+SUM($S24:AF24)-SUM($S12:AF12)+SUM($S35:AF35) -> 39 | AG46: =$R35+SUM($S24:AG24)-SUM($S12:AG12)+SUM($S35:AG35) -> 41 | AH46: =$R35+SUM($S24:AH24)-SUM($S12:AH12)+SUM($S35:AH35) -> 40 | AI46: =$R35+SUM($S24:AI24)-SUM($S12:AI12)+SUM($S35:AI35) -> 38 | AJ46: =$R35+SUM($S24:AJ24)-SUM($S12:AJ12)+SUM($S35:AJ35) -> 39 | AK46: =$R35+SUM($S24:AK24)-SUM($S12:AK12)+SUM($S35:AK35) -> 39 | AL46: =$R35+SUM($S24:AL24)-SUM($S12:AL12)+SUM($S35:AL35) -> 38 | AM46: =$R35+SUM($S24:AM24)-SUM($S12:AM12)+SUM($S35:AM35) -> 38 | ... BC46: =$R35+SUM($S24:BC24)-SUM($S12:BC12)+SUM($S35:BC35) -> 38
Q47: Advisory, Data &AI | AE47: =AE36+AE25 -> 2.5 | AF47: =Table13[[#This Row],[30/06/2025]]+AF25+AF36 -> 4.5 | AG47: =Table13[[#This Row],[30/06/2025]]+SUM(AF25:AG25)+SUM(AF36:AG36) -> 6 | AH47: =Table13[[#This Row],[31/07/2025]]+SUM(AG25:AH25)+SUM(AG36:AH36) -> 6.2
Q48: Totals | R48: =SUM(R40:R47) -> 159.75 | S48: =SUM(S40:S47) -> 157.75 | T48: =SUM(T40:T46) -> 162.75 | U48: =SUM(U40:U46) -> 166.75 | V48: =SUM(V40:V46) -> 169.75 | W48: =SUM(W40:W46) -> 171.75 | X48: =SUM(X40:X47) -> 170.75 | Y48: =SUM(Y40:Y46) -> 169.75 | Z48: =SUM(Z40:Z46) -> 168.75 | AA48: =SUM(AA40:AA46) -> 167.75 | AB48: =SUM(AB40:AB46) -> 168.75 | AC48: =SUM(AC40:AC46) -> 166.75 | AD48: =SUM(AD40:AD47) -> 166.75 | AE48: =SUM(AE40:AE47) -> 164.25 | AF48: =SUM(AF40:AF47) -> 165.25 | AG48: =SUM(AG40:AG47) -> 168.75 | AH48: =SUM(AH40:AH47) -> 171.15
Q49: Regional Total
B50: Europe | C50: 7 | E50: 34 | G50: 4 | H50: 45 | Q50: FTE | R50: Business Unit FTE overtime | AG50: includes contractors
B51: Shared Services | E51: 15 | H51: 15 | Q51: Business Unit | R51: Column1 | S51: Column2 | T51: Column3 | U51: 31/08/2024 | V51: 30/09/2024 | W51: 31/10/2024 | X51: 30/11/2024 | Y51: 31/12/2024 | Z51: 30/01/2025 | AA51: 28/02/2025 | AB51: 31/03/2025 | AC51: 30/04/2025 | AD51: 31/05/2025 | AE51: 30/06/2025 | AF51: 31/07/2025 | AG51: 31/08/2025 | AH51: 30/09/2025 | AI51: 31/10/2025 | AJ51: 30/11/2025 | AK51: 31/12/2025 | AL51: 30/01/2026 | AM51: 28/02/2026 | AN51: 31/03/2026 | AO51: 30/04/2026 | AP51: 31/05/2026 | AQ51: 30/06/2026 | AR51: 31/07/2026 | AS51: 31/08/2026 | AT51: 30/09/2026 | AU51: 31/10/2026 | AV51: 30/11/2026 | AW51: 31/12/2026 | AX51: 30/01/2027 | AY51: 28/02/2027 | AZ51: 31/03/2027 | BA51: 30/04/2027 | BB51: 31/05/2027 | BC51: 30/06/2027 | BD51: 31/07/2027 | BE51: 31/08/2027 | BF51: 30/09/2027 | BG51: 31/10/2027
B52: Sales | E52: 2 | H52: 2 | O52: Engineering | Q52: Engineering | AG52: {=SUMPRODUCT( ('Regional allocations LIVE'!$H$4:$H$269=$O52) * ('Regional allocations LIVE'!$D$4:$D$269<AH$4) * (ISNUMBER('Regional allocations LIVE'!$D$4:$D$269)) * (('Regional allocations LIVE'!$R$4:$R$269="") + ('Regional allocations LIVE'!$R$4:$R$269>=AH$4)) * 'Regional allocations LIVE'!$T$4:$T$269)} -> 27.4 | AH52: {=SUMPRODUCT( ('Regional allocations LIVE'!$H$4:$H$269=$O52) * ('Regional allocations LIVE'!$D$4:$D$269<AI$4) * (ISNUMBER('Regional allocations LIVE'!$D$4:$D$269)) * (('Regional allocations LIVE'!$R$4:$R$269="") + ('Regional allocations LIVE'!$R$4:$R$269>=AI$4)) * 'Regional allocations LIVE'!$T$4:$T$269)} -> 28.6 | AI52: {=SUMPRODUCT( ('Regional allocations LIVE'!$H$4:$H$269=$O52) * ('Regional allocations LIVE'!$D$4:$D$269<AJ$4) * (ISNUMBER('Regional allocations LIVE'!$D$4:$D$269)) * (('Regional allocations LIVE'!$R$4:$R$269="") + ('Regional allocations LIVE'!$R$4:$R$269>=AJ$4)) * 'Regional allocations LIVE'!$T$4:$T$269)} -> 30.6 | AJ52: {=SUMPRODUCT( ('Regional allocations LIVE'!$H$4:$H$269=$O52) * ('Regional allocations LIVE'!$D$4:$D$269<AK$4) * (ISNUMBER('Regional allocations LIVE'!$D$4:$D$269)) * (('Regional allocations LIVE'!$R$4:$R$269="") + ('Regional allocations LIVE'!$R$4:$R$269>=AK$4)) * 'Regional allocations LIVE'!$T$4:$T$269)} -> 34.6 | AK52: {=SUMPRODUCT( ('Regional allocations LIVE'!$H$4:$H$269=$O52) * ('Regional allocations LIVE'!$D$4:$D$269<AL$4) * (ISNUMBER('Regional allocations LIVE'!$D$4:$D$269)) * (('Regional allocations LIVE'!$R$4:$R$269="") + ('Regional allocations LIVE'!$R$4:$R$269>=AL$4)) * 'Regional allocations LIVE'!$T$4:$T$269)} -> 35.6 | AL52: {=SUMPRODUCT( ('Regional allocations LIVE'!$H$4:$H$269=$O52) * ('Regional allocations LIVE'!$D$4:$D$269<AM$4) * (ISNUMBER('Regional allocations LIVE'!$D$4:$D$269)) * (('Regional allocations LIVE'!$R$4:$R$269="") + ('Regional allocations LIVE'!$R$4:$R$269>=AM$4)) * 'Regional allocations LIVE'!$T$4:$T$269)} -> 35.6 | AM52: {=SUMPRODUCT( ('Regional allocations LIVE'!$H$4:$H$269=$O52) * ('Regional allocations LIVE'!$D$4:$D$269<AN$4) * (ISNUMBER('Regional allocations LIVE'!$D$4:$D$269)) * (('Regional allocations LIVE'!$R$4:$R$269="") + ('Regional allocations LIVE'!$R$4:$R$269>=AN$4)) * 'Regional allocations LIVE'!$T$4:$T$269)} -> 35.6 | AN52: {=SUMPRODUCT( ('Regional allocations LIVE'!$H$4:$H$269=$O52) * ('Regional allocations LIVE'!$D$4:$D$269<AO$4) * (ISNUMBER('Regional allocations LIVE'!$D$4:$D$269)) * (('Regional allocations LIVE'!$R$4:$R$269="") + ('Regional allocations LIVE'!$R$4:$R$269>=AO$4)) * 'Regional allocations LIVE'!$T$4:$T$269)} -> 35.6 | ... BD52: {=SUMPRODUCT( ('Regional allocations LIVE'!$H$4:$H$269=$O52) * ('Regional allocations LIVE'!$D$4:$D$269<BE$4) * (ISNUMBER('Regional allocations LIVE'!$D$4:$D$269)) * (('Regional allocations LIVE'!$R$4:$R$269="") + ('Regional allocations LIVE'!$R$4:$R$269>=BE$4)) * 'Regional allocations LIVE'!$T$4:$T$269)} -> 35.6
B53: Grand Total | C53: 7 | D53: 9 | E53: 140 | F53: 10 | G53: 8 | H53: 174 | O53: Sales | Q53: Sales | AG53: {=SUMPRODUCT( ('Regional allocations LIVE'!$H$4:$H$269=$O53) * ('Regional allocations LIVE'!$D$4:$D$269<AH$4) * (ISNUMBER('Regional allocations LIVE'!$D$4:$D$269)) * (('Regional allocations LIVE'!$R$4:$R$269="") + ('Regional allocations LIVE'!$R$4:$R$269>=AH$4)) * 'Regional allocations LIVE'!$T$4:$T$269)} -> 4.33 | AH53: {=SUMPRODUCT( ('Regional allocations LIVE'!$H$4:$H$269=$O53) * ('Regional allocations LIVE'!$D$4:$D$269<AI$4) * (ISNUMBER('Regional allocations LIVE'!$D$4:$D$269)) * (('Regional allocations LIVE'!$R$4:$R$269="") + ('Regional allocations LIVE'!$R$4:$R$269>=AI$4)) * 'Regional allocations LIVE'!$T$4:$T$269)} -> 4.33 | AI53: {=SUMPRODUCT( ('Regional allocations LIVE'!$H$4:$H$269=$O53) * ('Regional allocations LIVE'!$D$4:$D$269<AJ$4) * (ISNUMBER('Regional allocations LIVE'!$D$4:$D$269)) * (('Regional allocations LIVE'!$R$4:$R$269="") + ('Regional allocations LIVE'!$R$4:$R$269>=AJ$4)) * 'Regional allocations LIVE'!$T$4:$T$269)} -> 4.33 | AJ53: {=SUMPRODUCT( ('Regional allocations LIVE'!$H$4:$H$269=$O53) * ('Regional allocations LIVE'!$D$4:$D$269<AK$4) * (ISNUMBER('Regional allocations LIVE'!$D$4:$D$269)) * (('Regional allocations LIVE'!$R$4:$R$269="") + ('Regional allocations LIVE'!$R$4:$R$269>=AK$4)) * 'Regional allocations LIVE'!$T$4:$T$269)} -> 4.33 | AK53: {=SUMPRODUCT( ('Regional allocations LIVE'!$H$4:$H$269=$O53) * ('Regional allocations LIVE'!$D$4:$D$269<AL$4) * (ISNUMBER('Regional allocations LIVE'!$D$4:$D$269)) * (('Regional allocations LIVE'!$R$4:$R$269="") + ('Regional allocations LIVE'!$R$4:$R$269>=AL$4)) * 'Regional allocations LIVE'!$T$4:$T$269)} -> 4.33 | AL53: {=SUMPRODUCT( ('Regional allocations LIVE'!$H$4:$H$269=$O53) * ('Regional allocations LIVE'!$D$4:$D$269<AM$4) * (ISNUMBER('Regional allocations LIVE'!$D$4:$D$269)) * (('Regional allocations LIVE'!$R$4:$R$269="") + ('Regional allocations LIVE'!$R$4:$R$269>=AM$4)) * 'Regional allocations LIVE'!$T$4:$T$269)} -> 4.33 | AM53: {=SUMPRODUCT( ('Regional allocations LIVE'!$H$4:$H$269=$O53) * ('Regional allocations LIVE'!$D$4:$D$269<AN$4) * (ISNUMBER('Regional allocations LIVE'!$D$4:$D$269)) * (('Regional allocations LIVE'!$R$4:$R$269="") + ('Regional allocations LIVE'!$R$4:$R$269>=AN$4)) * 'Regional allocations LIVE'!$T$4:$T$269)} -> 4.33 | AN53: {=SUMPRODUCT( ('Regional allocations LIVE'!$H$4:$H$269=$O53) * ('Regional allocations LIVE'!$D$4:$D$269<AO$4) * (ISNUMBER('Regional allocations LIVE'!$D$4:$D$269)) * (('Regional allocations LIVE'!$R$4:$R$269="") + ('Regional allocations LIVE'!$R$4:$R$269>=AO$4)) * 'Regional allocations LIVE'!$T$4:$T$269)} -> 4.33 | ... BD53: {=SUMPRODUCT( ('Regional allocations LIVE'!$H$4:$H$269=$O53) * ('Regional allocations LIVE'!$D$4:$D$269<BE$4) * (ISNUMBER('Regional allocations LIVE'!$D$4:$D$269)) * (('Regional allocations LIVE'!$R$4:$R$269="") + ('Regional allocations LIVE'!$R$4:$R$269>=BE$4)) * 'Regional allocations LIVE'!$T$4:$T$269)} -> 4.33
O54: Shared Services | Q54: Shared Services | AG54: {=SUMPRODUCT( ('Regional allocations LIVE'!$H$4:$H$269=$O54) * ('Regional allocations LIVE'!$D$4:$D$269<AH$4) * (ISNUMBER('Regional allocations LIVE'!$D$4:$D$269)) * (('Regional allocations LIVE'!$R$4:$R$269="") + ('Regional allocations LIVE'!$R$4:$R$269>=AH$4)) * 'Regional allocations LIVE'!$T$4:$T$269)} -> 14.5 | AH54: {=SUMPRODUCT( ('Regional allocations LIVE'!$H$4:$H$269=$O54) * ('Regional allocations LIVE'!$D$4:$D$269<AI$4) * (ISNUMBER('Regional allocations LIVE'!$D$4:$D$269)) * (('Regional allocations LIVE'!$R$4:$R$269="") + ('Regional allocations LIVE'!$R$4:$R$269>=AI$4)) * 'Regional allocations LIVE'!$T$4:$T$269)} -> 14.5 | AI54: {=SUMPRODUCT( ('Regional allocations LIVE'!$H$4:$H$269=$O54) * ('Regional allocations LIVE'!$D$4:$D$269<AJ$4) * (ISNUMBER('Regional allocations LIVE'!$D$4:$D$269)) * (('Regional allocations LIVE'!$R$4:$R$269="") + ('Regional allocations LIVE'!$R$4:$R$269>=AJ$4)) * 'Regional allocations LIVE'!$T$4:$T$269)} -> 15.5 | AJ54: {=SUMPRODUCT( ('Regional allocations LIVE'!$H$4:$H$269=$O54) * ('Regional allocations LIVE'!$D$4:$D$269<AK$4) * (ISNUMBER('Regional allocations LIVE'!$D$4:$D$269)) * (('Regional allocations LIVE'!$R$4:$R$269="") + ('Regional allocations LIVE'!$R$4:$R$269>=AK$4)) * 'Regional allocations LIVE'!$T$4:$T$269)} -> 15.5 | AK54: {=SUMPRODUCT( ('Regional allocations LIVE'!$H$4:$H$269=$O54) * ('Regional allocations LIVE'!$D$4:$D$269<AL$4) * (ISNUMBER('Regional allocations LIVE'!$D$4:$D$269)) * (('Regional allocations LIVE'!$R$4:$R$269="") + ('Regional allocations LIVE'!$R$4:$R$269>=AL$4)) * 'Regional allocations LIVE'!$T$4:$T$269)} -> 15.5 | AL54: {=SUMPRODUCT( ('Regional allocations LIVE'!$H$4:$H$269=$O54) * ('Regional allocations LIVE'!$D$4:$D$269<AM$4) * (ISNUMBER('Regional allocations LIVE'!$D$4:$D$269)) * (('Regional allocations LIVE'!$R$4:$R$269="") + ('Regional allocations LIVE'!$R$4:$R$269>=AM$4)) * 'Regional allocations LIVE'!$T$4:$T$269)} -> 15.5 | AM54: {=SUMPRODUCT( ('Regional allocations LIVE'!$H$4:$H$269=$O54) * ('Regional allocations LIVE'!$D$4:$D$269<AN$4) * (ISNUMBER('Regional allocations LIVE'!$D$4:$D$269)) * (('Regional allocations LIVE'!$R$4:$R$269="") + ('Regional allocations LIVE'!$R$4:$R$269>=AN$4)) * 'Regional allocations LIVE'!$T$4:$T$269)} -> 15.5 | AN54: {=SUMPRODUCT( ('Regional allocations LIVE'!$H$4:$H$269=$O54) * ('Regional allocations LIVE'!$D$4:$D$269<AO$4) * (ISNUMBER('Regional allocations LIVE'!$D$4:$D$269)) * (('Regional allocations LIVE'!$R$4:$R$269="") + ('Regional allocations LIVE'!$R$4:$R$269>=AO$4)) * 'Regional allocations LIVE'!$T$4:$T$269)} -> 15.5 | ... BD54: {=SUMPRODUCT( ('Regional allocations LIVE'!$H$4:$H$269=$O54) * ('Regional allocations LIVE'!$D$4:$D$269<BE$4) * (ISNUMBER('Regional allocations LIVE'!$D$4:$D$269)) * (('Regional allocations LIVE'!$R$4:$R$269="") + ('Regional allocations LIVE'!$R$4:$R$269>=BE$4)) * 'Regional allocations LIVE'!$T$4:$T$269)} -> 15.5
O55: Europe | Q55: Europe | AG55: {=SUMPRODUCT( ('Regional allocations LIVE'!$H$4:$H$269=$O55) * ('Regional allocations LIVE'!$D$4:$D$269<AH$4) * (ISNUMBER('Regional allocations LIVE'!$D$4:$D$269)) * (('Regional allocations LIVE'!$R$4:$R$269="") + ('Regional allocations LIVE'!$R$4:$R$269>=AH$4)) * 'Regional allocations LIVE'!$T$4:$T$269)} -> 44.8 | AH55: {=SUMPRODUCT( ('Regional allocations LIVE'!$H$4:$H$269=$O55) * ('Regional allocations LIVE'!$D$4:$D$269<AI$4) * (ISNUMBER('Regional allocations LIVE'!$D$4:$D$269)) * (('Regional allocations LIVE'!$R$4:$R$269="") + ('Regional allocations LIVE'!$R$4:$R$269>=AI$4)) * 'Regional allocations LIVE'!$T$4:$T$269)} -> 45.8 | AI55: {=SUMPRODUCT( ('Regional allocations LIVE'!$H$4:$H$269=$O55) * ('Regional allocations LIVE'!$D$4:$D$269<AJ$4) * (ISNUMBER('Regional allocations LIVE'!$D$4:$D$269)) * (('Regional allocations LIVE'!$R$4:$R$269="") + ('Regional allocations LIVE'!$R$4:$R$269>=AJ$4)) * 'Regional allocations LIVE'!$T$4:$T$269)} -> 45.8 | AJ55: {=SUMPRODUCT( ('Regional allocations LIVE'!$H$4:$H$269=$O55) * ('Regional allocations LIVE'!$D$4:$D$269<AK$4) * (ISNUMBER('Regional allocations LIVE'!$D$4:$D$269)) * (('Regional allocations LIVE'!$R$4:$R$269="") + ('Regional allocations LIVE'!$R$4:$R$269>=AK$4)) * 'Regional allocations LIVE'!$T$4:$T$269)} -> 46.8 | AK55: {=SUMPRODUCT( ('Regional allocations LIVE'!$H$4:$H$269=$O55) * ('Regional allocations LIVE'!$D$4:$D$269<AL$4) * (ISNUMBER('Regional allocations LIVE'!$D$4:$D$269)) * (('Regional allocations LIVE'!$R$4:$R$269="") + ('Regional allocations LIVE'!$R$4:$R$269>=AL$4)) * 'Regional allocations LIVE'!$T$4:$T$269)} -> 46.8 | AL55: {=SUMPRODUCT( ('Regional allocations LIVE'!$H$4:$H$269=$O55) * ('Regional allocations LIVE'!$D$4:$D$269<AM$4) * (ISNUMBER('Regional allocations LIVE'!$D$4:$D$269)) * (('Regional allocations LIVE'!$R$4:$R$269="") + ('Regional allocations LIVE'!$R$4:$R$269>=AM$4)) * 'Regional allocations LIVE'!$T$4:$T$269)} -> 47.8 | AM55: {=SUMPRODUCT( ('Regional allocations LIVE'!$H$4:$H$269=$O55) * ('Regional allocations LIVE'!$D$4:$D$269<AN$4) * (ISNUMBER('Regional allocations LIVE'!$D$4:$D$269)) * (('Regional allocations LIVE'!$R$4:$R$269="") + ('Regional allocations LIVE'!$R$4:$R$269>=AN$4)) * 'Regional allocations LIVE'!$T$4:$T$269)} -> 47.8 | AN55: {=SUMPRODUCT( ('Regional allocations LIVE'!$H$4:$H$269=$O55) * ('Regional allocations LIVE'!$D$4:$D$269<AO$4) * (ISNUMBER('Regional allocations LIVE'!$D$4:$D$269)) * (('Regional allocations LIVE'!$R$4:$R$269="") + ('Regional allocations LIVE'!$R$4:$R$269>=AO$4)) * 'Regional allocations LIVE'!$T$4:$T$269)} -> 47.8 | ... BD55: {=SUMPRODUCT( ('Regional allocations LIVE'!$H$4:$H$269=$O55) * ('Regional allocations LIVE'!$D$4:$D$269<BE$4) * (ISNUMBER('Regional allocations LIVE'!$D$4:$D$269)) * (('Regional allocations LIVE'!$R$4:$R$269="") + ('Regional allocations LIVE'!$R$4:$R$269>=BE$4)) * 'Regional allocations LIVE'!$T$4:$T$269)} -> 47.8
O56: Asia Pacific | Q56: Asia Pacific | AG56: {=SUMPRODUCT( ('Regional allocations LIVE'!$H$4:$H$269=$O56) * ('Regional allocations LIVE'!$D$4:$D$269<AH$4) * (ISNUMBER('Regional allocations LIVE'!$D$4:$D$269)) * (('Regional allocations LIVE'!$R$4:$R$269="") + ('Regional allocations LIVE'!$R$4:$R$269>=AH$4)) * 'Regional allocations LIVE'!$T$4:$T$269)} -> 16.45 | AH56: {=SUMPRODUCT( ('Regional allocations LIVE'!$H$4:$H$269=$O56) * ('Regional allocations LIVE'!$D$4:$D$269<AI$4) * (ISNUMBER('Regional allocations LIVE'!$D$4:$D$269)) * (('Regional allocations LIVE'!$R$4:$R$269="") + ('Regional allocations LIVE'!$R$4:$R$269>=AI$4)) * 'Regional allocations LIVE'!$T$4:$T$269)} -> 16.45 | AI56: {=SUMPRODUCT( ('Regional allocations LIVE'!$H$4:$H$269=$O56) * ('Regional allocations LIVE'!$D$4:$D$269<AJ$4) * (ISNUMBER('Regional allocations LIVE'!$D$4:$D$269)) * (('Regional allocations LIVE'!$R$4:$R$269="") + ('Regional allocations LIVE'!$R$4:$R$269>=AJ$4)) * 'Regional allocations LIVE'!$T$4:$T$269)} -> 16.45 | AJ56: {=SUMPRODUCT( ('Regional allocations LIVE'!$H$4:$H$269=$O56) * ('Regional allocations LIVE'!$D$4:$D$269<AK$4) * (ISNUMBER('Regional allocations LIVE'!$D$4:$D$269)) * (('Regional allocations LIVE'!$R$4:$R$269="") + ('Regional allocations LIVE'!$R$4:$R$269>=AK$4)) * 'Regional allocations LIVE'!$T$4:$T$269)} -> 17.45 | AK56: {=SUMPRODUCT( ('Regional allocations LIVE'!$H$4:$H$269=$O56) * ('Regional allocations LIVE'!$D$4:$D$269<AL$4) * (ISNUMBER('Regional allocations LIVE'!$D$4:$D$269)) * (('Regional allocations LIVE'!$R$4:$R$269="") + ('Regional allocations LIVE'!$R$4:$R$269>=AL$4)) * 'Regional allocations LIVE'!$T$4:$T$269)} -> 17.45 | AL56: {=SUMPRODUCT( ('Regional allocations LIVE'!$H$4:$H$269=$O56) * ('Regional allocations LIVE'!$D$4:$D$269<AM$4) * (ISNUMBER('Regional allocations LIVE'!$D$4:$D$269)) * (('Regional allocations LIVE'!$R$4:$R$269="") + ('Regional allocations LIVE'!$R$4:$R$269>=AM$4)) * 'Regional allocations LIVE'!$T$4:$T$269)} -> 17.45 | AM56: {=SUMPRODUCT( ('Regional allocations LIVE'!$H$4:$H$269=$O56) * ('Regional allocations LIVE'!$D$4:$D$269<AN$4) * (ISNUMBER('Regional allocations LIVE'!$D$4:$D$269)) * (('Regional allocations LIVE'!$R$4:$R$269="") + ('Regional allocations LIVE'!$R$4:$R$269>=AN$4)) * 'Regional allocations LIVE'!$T$4:$T$269)} -> 17.45 | AN56: {=SUMPRODUCT( ('Regional allocations LIVE'!$H$4:$H$269=$O56) * ('Regional allocations LIVE'!$D$4:$D$269<AO$4) * (ISNUMBER('Regional allocations LIVE'!$D$4:$D$269)) * (('Regional allocations LIVE'!$R$4:$R$269="") + ('Regional allocations LIVE'!$R$4:$R$269>=AO$4)) * 'Regional allocations LIVE'!$T$4:$T$269)} -> 17.45 | ... BD56: {=SUMPRODUCT( ('Regional allocations LIVE'!$H$4:$H$269=$O56) * ('Regional allocations LIVE'!$D$4:$D$269<BE$4) * (ISNUMBER('Regional allocations LIVE'!$D$4:$D$269)) * (('Regional allocations LIVE'!$R$4:$R$269="") + ('Regional allocations LIVE'!$R$4:$R$269>=BE$4)) * 'Regional allocations LIVE'!$T$4:$T$269)} -> 17.45
O57: CEO | Q57: CEO | AG57: {=SUMPRODUCT( ('Regional allocations LIVE'!$H$4:$H$269=$O57) * ('Regional allocations LIVE'!$D$4:$D$269<AH$4) * (ISNUMBER('Regional allocations LIVE'!$D$4:$D$269)) * (('Regional allocations LIVE'!$R$4:$R$269="") + ('Regional allocations LIVE'!$R$4:$R$269>=AH$4)) * 'Regional allocations LIVE'!$T$4:$T$269)} -> 1 | AH57: {=SUMPRODUCT( ('Regional allocations LIVE'!$H$4:$H$269=$O57) * ('Regional allocations LIVE'!$D$4:$D$269<AI$4) * (ISNUMBER('Regional allocations LIVE'!$D$4:$D$269)) * (('Regional allocations LIVE'!$R$4:$R$269="") + ('Regional allocations LIVE'!$R$4:$R$269>=AI$4)) * 'Regional allocations LIVE'!$T$4:$T$269)} -> 1 | AI57: {=SUMPRODUCT( ('Regional allocations LIVE'!$H$4:$H$269=$O57) * ('Regional allocations LIVE'!$D$4:$D$269<AJ$4) * (ISNUMBER('Regional allocations LIVE'!$D$4:$D$269)) * (('Regional allocations LIVE'!$R$4:$R$269="") + ('Regional allocations LIVE'!$R$4:$R$269>=AJ$4)) * 'Regional allocations LIVE'!$T$4:$T$269)} -> 1 | AJ57: {=SUMPRODUCT( ('Regional allocations LIVE'!$H$4:$H$269=$O57) * ('Regional allocations LIVE'!$D$4:$D$269<AK$4) * (ISNUMBER('Regional allocations LIVE'!$D$4:$D$269)) * (('Regional allocations LIVE'!$R$4:$R$269="") + ('Regional allocations LIVE'!$R$4:$R$269>=AK$4)) * 'Regional allocations LIVE'!$T$4:$T$269)} -> 1 | AK57: {=SUMPRODUCT( ('Regional allocations LIVE'!$H$4:$H$269=$O57) * ('Regional allocations LIVE'!$D$4:$D$269<AL$4) * (ISNUMBER('Regional allocations LIVE'!$D$4:$D$269)) * (('Regional allocations LIVE'!$R$4:$R$269="") + ('Regional allocations LIVE'!$R$4:$R$269>=AL$4)) * 'Regional allocations LIVE'!$T$4:$T$269)} -> 1 | AL57: {=SUMPRODUCT( ('Regional allocations LIVE'!$H$4:$H$269=$O57) * ('Regional allocations LIVE'!$D$4:$D$269<AM$4) * (ISNUMBER('Regional allocations LIVE'!$D$4:$D$269)) * (('Regional allocations LIVE'!$R$4:$R$269="") + ('Regional allocations LIVE'!$R$4:$R$269>=AM$4)) * 'Regional allocations LIVE'!$T$4:$T$269)} -> 1 | AM57: {=SUMPRODUCT( ('Regional allocations LIVE'!$H$4:$H$269=$O57) * ('Regional allocations LIVE'!$D$4:$D$269<AN$4) * (ISNUMBER('Regional allocations LIVE'!$D$4:$D$269)) * (('Regional allocations LIVE'!$R$4:$R$269="") + ('Regional allocations LIVE'!$R$4:$R$269>=AN$4)) * 'Regional allocations LIVE'!$T$4:$T$269)} -> 1 | AN57: {=SUMPRODUCT( ('Regional allocations LIVE'!$H$4:$H$269=$O57) * ('Regional allocations LIVE'!$D$4:$D$269<AO$4) * (ISNUMBER('Regional allocations LIVE'!$D$4:$D$269)) * (('Regional allocations LIVE'!$R$4:$R$269="") + ('Regional allocations LIVE'!$R$4:$R$269>=AO$4)) * 'Regional allocations LIVE'!$T$4:$T$269)} -> 1 | ... BD57: {=SUMPRODUCT( ('Regional allocations LIVE'!$H$4:$H$269=$O57) * ('Regional allocations LIVE'!$D$4:$D$269<BE$4) * (ISNUMBER('Regional allocations LIVE'!$D$4:$D$269)) * (('Regional allocations LIVE'!$R$4:$R$269="") + ('Regional allocations LIVE'!$R$4:$R$269>=BE$4)) * 'Regional allocations LIVE'!$T$4:$T$269)} -> 1
O58: Americas | Q58: Americas | AG58: {=SUMPRODUCT( ('Regional allocations LIVE'!$H$4:$H$269=$O58) * ('Regional allocations LIVE'!$D$4:$D$269<AH$4) * (ISNUMBER('Regional allocations LIVE'!$D$4:$D$269)) * (('Regional allocations LIVE'!$R$4:$R$269="") + ('Regional allocations LIVE'!$R$4:$R$269>=AH$4)) * 'Regional allocations LIVE'!$T$4:$T$269)} -> 41 | AH58: {=SUMPRODUCT( ('Regional allocations LIVE'!$H$4:$H$269=$O58) * ('Regional allocations LIVE'!$D$4:$D$269<AI$4) * (ISNUMBER('Regional allocations LIVE'!$D$4:$D$269)) * (('Regional allocations LIVE'!$R$4:$R$269="") + ('Regional allocations LIVE'!$R$4:$R$269>=AI$4)) * 'Regional allocations LIVE'!$T$4:$T$269)} -> 40 | AI58: {=SUMPRODUCT( ('Regional allocations LIVE'!$H$4:$H$269=$O58) * ('Regional allocations LIVE'!$D$4:$D$269<AJ$4) * (ISNUMBER('Regional allocations LIVE'!$D$4:$D$269)) * (('Regional allocations LIVE'!$R$4:$R$269="") + ('Regional allocations LIVE'!$R$4:$R$269>=AJ$4)) * 'Regional allocations LIVE'!$T$4:$T$269)} -> 38 | AJ58: {=SUMPRODUCT( ('Regional allocations LIVE'!$H$4:$H$269=$O58) * ('Regional allocations LIVE'!$D$4:$D$269<AK$4) * (ISNUMBER('Regional allocations LIVE'!$D$4:$D$269)) * (('Regional allocations LIVE'!$R$4:$R$269="") + ('Regional allocations LIVE'!$R$4:$R$269>=AK$4)) * 'Regional allocations LIVE'!$T$4:$T$269)} -> 39 | AK58: {=SUMPRODUCT( ('Regional allocations LIVE'!$H$4:$H$269=$O58) * ('Regional allocations LIVE'!$D$4:$D$269<AL$4) * (ISNUMBER('Regional allocations LIVE'!$D$4:$D$269)) * (('Regional allocations LIVE'!$R$4:$R$269="") + ('Regional allocations LIVE'!$R$4:$R$269>=AL$4)) * 'Regional allocations LIVE'!$T$4:$T$269)} -> 39 | AL58: {=SUMPRODUCT( ('Regional allocations LIVE'!$H$4:$H$269=$O58) * ('Regional allocations LIVE'!$D$4:$D$269<AM$4) * (ISNUMBER('Regional allocations LIVE'!$D$4:$D$269)) * (('Regional allocations LIVE'!$R$4:$R$269="") + ('Regional allocations LIVE'!$R$4:$R$269>=AM$4)) * 'Regional allocations LIVE'!$T$4:$T$269)} -> 38 | AM58: {=SUMPRODUCT( ('Regional allocations LIVE'!$H$4:$H$269=$O58) * ('Regional allocations LIVE'!$D$4:$D$269<AN$4) * (ISNUMBER('Regional allocations LIVE'!$D$4:$D$269)) * (('Regional allocations LIVE'!$R$4:$R$269="") + ('Regional allocations LIVE'!$R$4:$R$269>=AN$4)) * 'Regional allocations LIVE'!$T$4:$T$269)} -> 38 | AN58: {=SUMPRODUCT( ('Regional allocations LIVE'!$H$4:$H$269=$O58) * ('Regional allocations LIVE'!$D$4:$D$269<AO$4) * (ISNUMBER('Regional allocations LIVE'!$D$4:$D$269)) * (('Regional allocations LIVE'!$R$4:$R$269="") + ('Regional allocations LIVE'!$R$4:$R$269>=AO$4)) * 'Regional allocations LIVE'!$T$4:$T$269)} -> 38 | ... BD58: {=SUMPRODUCT( ('Regional allocations LIVE'!$H$4:$H$269=$O58) * ('Regional allocations LIVE'!$D$4:$D$269<BE$4) * (ISNUMBER('Regional allocations LIVE'!$D$4:$D$269)) * (('Regional allocations LIVE'!$R$4:$R$269="") + ('Regional allocations LIVE'!$R$4:$R$269>=BE$4)) * 'Regional allocations LIVE'!$T$4:$T$269)} -> 38
O59: Advisory, Data &AI | Q59: Advisory, Data &AI | AG59: {=SUMPRODUCT( ('Regional allocations LIVE'!$H$4:$H$269=$O59) * ('Regional allocations LIVE'!$D$4:$D$269<AH$4) * (ISNUMBER('Regional allocations LIVE'!$D$4:$D$269)) * (('Regional allocations LIVE'!$R$4:$R$269="") + ('Regional allocations LIVE'!$R$4:$R$269>=AH$4)) * 'Regional allocations LIVE'!$T$4:$T$269)} -> 6.82 | AH59: {=SUMPRODUCT( ('Regional allocations LIVE'!$H$4:$H$269=$O59) * ('Regional allocations LIVE'!$D$4:$D$269<AI$4) * (ISNUMBER('Regional allocations LIVE'!$D$4:$D$269)) * (('Regional allocations LIVE'!$R$4:$R$269="") + ('Regional allocations LIVE'!$R$4:$R$269>=AI$4)) * 'Regional allocations LIVE'!$T$4:$T$269)} -> 7.02 | AI59: {=SUMPRODUCT( ('Regional allocations LIVE'!$H$4:$H$269=$O59) * ('Regional allocations LIVE'!$D$4:$D$269<AJ$4) * (ISNUMBER('Regional allocations LIVE'!$D$4:$D$269)) * (('Regional allocations LIVE'!$R$4:$R$269="") + ('Regional allocations LIVE'!$R$4:$R$269>=AJ$4)) * 'Regional allocations LIVE'!$T$4:$T$269)} -> 6.02 | AJ59: {=SUMPRODUCT( ('Regional allocations LIVE'!$H$4:$H$269=$O59) * ('Regional allocations LIVE'!$D$4:$D$269<AK$4) * (ISNUMBER('Regional allocations LIVE'!$D$4:$D$269)) * (('Regional allocations LIVE'!$R$4:$R$269="") + ('Regional allocations LIVE'!$R$4:$R$269>=AK$4)) * 'Regional allocations LIVE'!$T$4:$T$269)} -> 6.02 | AK59: {=SUMPRODUCT( ('Regional allocations LIVE'!$H$4:$H$269=$O59) * ('Regional allocations LIVE'!$D$4:$D$269<AL$4) * (ISNUMBER('Regional allocations LIVE'!$D$4:$D$269)) * (('Regional allocations LIVE'!$R$4:$R$269="") + ('Regional allocations LIVE'!$R$4:$R$269>=AL$4)) * 'Regional allocations LIVE'!$T$4:$T$269)} -> 6.02 | AL59: {=SUMPRODUCT( ('Regional allocations LIVE'!$H$4:$H$269=$O59) * ('Regional allocations LIVE'!$D$4:$D$269<AM$4) * (ISNUMBER('Regional allocations LIVE'!$D$4:$D$269)) * (('Regional allocations LIVE'!$R$4:$R$269="") + ('Regional allocations LIVE'!$R$4:$R$269>=AM$4)) * 'Regional allocations LIVE'!$T$4:$T$269)} -> 6.02 | AM59: {=SUMPRODUCT( ('Regional allocations LIVE'!$H$4:$H$269=$O59) * ('Regional allocations LIVE'!$D$4:$D$269<AN$4) * (ISNUMBER('Regional allocations LIVE'!$D$4:$D$269)) * (('Regional allocations LIVE'!$R$4:$R$269="") + ('Regional allocations LIVE'!$R$4:$R$269>=AN$4)) * 'Regional allocations LIVE'!$T$4:$T$269)} -> 6.02 | AN59: {=SUMPRODUCT( ('Regional allocations LIVE'!$H$4:$H$269=$O59) * ('Regional allocations LIVE'!$D$4:$D$269<AO$4) * (ISNUMBER('Regional allocations LIVE'!$D$4:$D$269)) * (('Regional allocations LIVE'!$R$4:$R$269="") + ('Regional allocations LIVE'!$R$4:$R$269>=AO$4)) * 'Regional allocations LIVE'!$T$4:$T$269)} -> 6.02 | ... BD59: {=SUMPRODUCT( ('Regional allocations LIVE'!$H$4:$H$269=$O59) * ('Regional allocations LIVE'!$D$4:$D$269<BE$4) * (ISNUMBER('Regional allocations LIVE'!$D$4:$D$269)) * (('Regional allocations LIVE'!$R$4:$R$269="") + ('Regional allocations LIVE'!$R$4:$R$269>=BE$4)) * 'Regional allocations LIVE'!$T$4:$T$269)} -> 6.02
O60: Technology | Q60: Technology | AG60: {=SUMPRODUCT( ('Regional allocations LIVE'!$H$4:$H$269=$O60) * ('Regional allocations LIVE'!$D$4:$D$269<AH$4) * (ISNUMBER('Regional allocations LIVE'!$D$4:$D$269)) * (('Regional allocations LIVE'!$R$4:$R$269="") + ('Regional allocations LIVE'!$R$4:$R$269>=AH$4)) * 'Regional allocations LIVE'!$T$4:$T$269)} -> 12.8 | AH60: {=SUMPRODUCT( ('Regional allocations LIVE'!$H$4:$H$269=$O60) * ('Regional allocations LIVE'!$D$4:$D$269<AI$4) * (ISNUMBER('Regional allocations LIVE'!$D$4:$D$269)) * (('Regional allocations LIVE'!$R$4:$R$269="") + ('Regional allocations LIVE'!$R$4:$R$269>=AI$4)) * 'Regional allocations LIVE'!$T$4:$T$269)} -> 13.1 | AI60: {=SUMPRODUCT( ('Regional allocations LIVE'!$H$4:$H$269=$O60) * ('Regional allocations LIVE'!$D$4:$D$269<AJ$4) * (ISNUMBER('Regional allocations LIVE'!$D$4:$D$269)) * (('Regional allocations LIVE'!$R$4:$R$269="") + ('Regional allocations LIVE'!$R$4:$R$269>=AJ$4)) * 'Regional allocations LIVE'!$T$4:$T$269)} -> 14.1 | AJ60: {=SUMPRODUCT( ('Regional allocations LIVE'!$H$4:$H$269=$O60) * ('Regional allocations LIVE'!$D$4:$D$269<AK$4) * (ISNUMBER('Regional allocations LIVE'!$D$4:$D$269)) * (('Regional allocations LIVE'!$R$4:$R$269="") + ('Regional allocations LIVE'!$R$4:$R$269>=AK$4)) * 'Regional allocations LIVE'!$T$4:$T$269)} -> 14.1 | AK60: {=SUMPRODUCT( ('Regional allocations LIVE'!$H$4:$H$269=$O60) * ('Regional allocations LIVE'!$D$4:$D$269<AL$4) * (ISNUMBER('Regional allocations LIVE'!$D$4:$D$269)) * (('Regional allocations LIVE'!$R$4:$R$269="") + ('Regional allocations LIVE'!$R$4:$R$269>=AL$4)) * 'Regional allocations LIVE'!$T$4:$T$269)} -> 14.1 | AL60: {=SUMPRODUCT( ('Regional allocations LIVE'!$H$4:$H$269=$O60) * ('Regional allocations LIVE'!$D$4:$D$269<AM$4) * (ISNUMBER('Regional allocations LIVE'!$D$4:$D$269)) * (('Regional allocations LIVE'!$R$4:$R$269="") + ('Regional allocations LIVE'!$R$4:$R$269>=AM$4)) * 'Regional allocations LIVE'!$T$4:$T$269)} -> 14.1 | AM60: {=SUMPRODUCT( ('Regional allocations LIVE'!$H$4:$H$269=$O60) * ('Regional allocations LIVE'!$D$4:$D$269<AN$4) * (ISNUMBER('Regional allocations LIVE'!$D$4:$D$269)) * (('Regional allocations LIVE'!$R$4:$R$269="") + ('Regional allocations LIVE'!$R$4:$R$269>=AN$4)) * 'Regional allocations LIVE'!$T$4:$T$269)} -> 14.1 | AN60: {=SUMPRODUCT( ('Regional allocations LIVE'!$H$4:$H$269=$O60) * ('Regional allocations LIVE'!$D$4:$D$269<AO$4) * (ISNUMBER('Regional allocations LIVE'!$D$4:$D$269)) * (('Regional allocations LIVE'!$R$4:$R$269="") + ('Regional allocations LIVE'!$R$4:$R$269>=AO$4)) * 'Regional allocations LIVE'!$T$4:$T$269)} -> 14.1 | ... BD60: {=SUMPRODUCT( ('Regional allocations LIVE'!$H$4:$H$269=$O60) * ('Regional allocations LIVE'!$D$4:$D$269<BE$4) * (ISNUMBER('Regional allocations LIVE'!$D$4:$D$269)) * (('Regional allocations LIVE'!$R$4:$R$269="") + ('Regional allocations LIVE'!$R$4:$R$269>=BE$4)) * 'Regional allocations LIVE'!$T$4:$T$269)} -> 14.1
O61: Clever Cloud | Q61: Clever Cloud | AG61: {=SUMPRODUCT( ('Regional allocations LIVE'!$H$4:$H$269=$O61) * ('Regional allocations LIVE'!$D$4:$D$269<AH$4) * (ISNUMBER('Regional allocations LIVE'!$D$4:$D$269)) * (('Regional allocations LIVE'!$R$4:$R$269="") + ('Regional allocations LIVE'!$R$4:$R$269>=AH$4)) * 'Regional allocations LIVE'!$T$4:$T$269)} -> 0 | AH61: {=SUMPRODUCT( ('Regional allocations LIVE'!$H$4:$H$269=$O61) * ('Regional allocations LIVE'!$D$4:$D$269<AI$4) * (ISNUMBER('Regional allocations LIVE'!$D$4:$D$269)) * (('Regional allocations LIVE'!$R$4:$R$269="") + ('Regional allocations LIVE'!$R$4:$R$269>=AI$4)) * 'Regional allocations LIVE'!$T$4:$T$269)} -> 0 | AI61: {=SUMPRODUCT( ('Regional allocations LIVE'!$H$4:$H$269=$O61) * ('Regional allocations LIVE'!$D$4:$D$269<AJ$4) * (ISNUMBER('Regional allocations LIVE'!$D$4:$D$269)) * (('Regional allocations LIVE'!$R$4:$R$269="") + ('Regional allocations LIVE'!$R$4:$R$269>=AJ$4)) * 'Regional allocations LIVE'!$T$4:$T$269)} -> 0 | AJ61: {=SUMPRODUCT( ('Regional allocations LIVE'!$H$4:$H$269=$O61) * ('Regional allocations LIVE'!$D$4:$D$269<AK$4) * (ISNUMBER('Regional allocations LIVE'!$D$4:$D$269)) * (('Regional allocations LIVE'!$R$4:$R$269="") + ('Regional allocations LIVE'!$R$4:$R$269>=AK$4)) * 'Regional allocations LIVE'!$T$4:$T$269)} -> 0 | AK61: {=SUMPRODUCT( ('Regional allocations LIVE'!$H$4:$H$269=$O61) * ('Regional allocations LIVE'!$D$4:$D$269<AL$4) * (ISNUMBER('Regional allocations LIVE'!$D$4:$D$269)) * (('Regional allocations LIVE'!$R$4:$R$269="") + ('Regional allocations LIVE'!$R$4:$R$269>=AL$4)) * 'Regional allocations LIVE'!$T$4:$T$269)} -> 0 | AL61: {=SUMPRODUCT( ('Regional allocations LIVE'!$H$4:$H$269=$O61) * ('Regional allocations LIVE'!$D$4:$D$269<AM$4) * (ISNUMBER('Regional allocations LIVE'!$D$4:$D$269)) * (('Regional allocations LIVE'!$R$4:$R$269="") + ('Regional allocations LIVE'!$R$4:$R$269>=AM$4)) * 'Regional allocations LIVE'!$T$4:$T$269)} -> 0 | AM61: {=SUMPRODUCT( ('Regional allocations LIVE'!$H$4:$H$269=$O61) * ('Regional allocations LIVE'!$D$4:$D$269<AN$4) * (ISNUMBER('Regional allocations LIVE'!$D$4:$D$269)) * (('Regional allocations LIVE'!$R$4:$R$269="") + ('Regional allocations LIVE'!$R$4:$R$269>=AN$4)) * 'Regional allocations LIVE'!$T$4:$T$269)} -> 0 | AN61: {=SUMPRODUCT( ('Regional allocations LIVE'!$H$4:$H$269=$O61) * ('Regional allocations LIVE'!$D$4:$D$269<AO$4) * (ISNUMBER('Regional allocations LIVE'!$D$4:$D$269)) * (('Regional allocations LIVE'!$R$4:$R$269="") + ('Regional allocations LIVE'!$R$4:$R$269>=AO$4)) * 'Regional allocations LIVE'!$T$4:$T$269)} -> 0 | ... BD61: {=SUMPRODUCT( ('Regional allocations LIVE'!$H$4:$H$269=$O61) * ('Regional allocations LIVE'!$D$4:$D$269<BE$4) * (ISNUMBER('Regional allocations LIVE'!$D$4:$D$269)) * (('Regional allocations LIVE'!$R$4:$R$269="") + ('Regional allocations LIVE'!$R$4:$R$269>=BE$4)) * 'Regional allocations LIVE'!$T$4:$T$269)} -> 0
Q62: Totals minus CC | R62: =SUM(R52:R61) -> 0 | S62: =SUM(S52:S61) -> 0 | T62: =SUM(T52:T58) -> 0 | U62: =SUM(U52:U59) -> 0 | V62: =SUM(V52:V58) -> 0 | W62: =SUM(W52:W58) -> 0 | X62: =SUM(X52:X61) -> 0 | Y62: =SUM(Y52:Y58) -> 0 | Z62: =SUM(Z52:Z58) -> 0 | AA62: =SUM(AA52:AA58) -> 0 | AB62: =SUM(AB52:AB58) -> 0 | AC62: =SUM(AC52:AC58) -> 0 | AD62: =SUM(AD52:AD61) -> 0 | AE62: =SUM(AE52:AE61) -> 0 | AF62: =SUM(AF52:AF61) -> 0 | AG62: =SUM(AG52:AG59) -> 156.3 | AH62: =SUM(AH52:AH61) -> 170.8 | AI62: =SUM(AI52:AI61) -> 171.8 | AJ62: =SUM(AJ52:AJ61) -> 178.8 | AK62: =SUM(AK52:AK61) -> 179.8 | AL62: =SUM(AL52:AL61) -> 179.8 | AM62: =SUM(AM52:AM61) -> 179.8 | AN62: =SUM(AN52:AN61) -> 179.8 | AO62: =SUM(AO52:AO61) -> 179.8 | ... BD62: =SUM(BD52:BD61) -> 179.8
B64: Europe | C64: 7 | E64: 34 | G64: 4 | H64: 45 | Q64: Headcount | R64: Business Unit Headcount overtime
B65: Shared Services | E65: 15 | H65: 15 | Q65: Business Unit | R65: 31/05/2024 | S65: 30/06/2024 | T65: 31/07/2024 | U65: 31/08/2024 | V65: 30/09/2024 | W65: 31/10/2024 | X65: 30/11/2024 | Y65: 31/12/2024 | Z65: 30/01/2025 | AA65: 28/02/2025 | AB65: 31/03/2025 | AC65: 30/04/2025 | AD65: 31/05/2025 | AE65: 30/06/2025 | AF65: 31/07/2025 | AG65: 31/08/2025 | AH65: 30/09/2025 | AI65: 31/10/2025 | AJ65: 30/11/2025 | AK65: 31/12/2025 | AL65: 30/01/2026 | AM65: 28/02/2026 | AN65: 31/03/2026 | AO65: 30/04/2026 | AP65: 31/05/2026 | AQ65: 30/06/2026 | AR65: 31/07/2026 | AS65: 31/08/2026 | AT65: 30/09/2026 | AU65: 31/10/2026 | AV65: 30/11/2026 | AW65: 31/12/2026 | AX65: 30/01/2027 | AY65: 28/02/2027 | AZ65: 31/03/2027 | BA65: 30/04/2027 | BB65: 31/05/2027 | BC65: 30/06/2027 | BD65: 31/07/2027 | BE65: 31/08/2027 | BF65: 30/09/2027 | BG65: 31/10/2027
B66: Sales | E66: 2 | H66: 2 | Q66: Engineering | AG66: {=SUMPRODUCT( ('Regional allocations LIVE'!$H$2:$H$1047 = $O52) * (ISBLANK('Regional allocations LIVE'!$R$2:$R$1047) + ('Regional allocations LIVE'!$R$2:$R$1047 >= AH$4)) * (ISNUMBER('Regional allocations LIVE'!$D$2:$D$1047)) * ('Regional allocations LIVE'!$D$2:$D$1047 <= AH$4) )} -> 28 | AH66: {=SUMPRODUCT( ('Regional allocations LIVE'!$H$2:$H$1047 = $O52) * (ISBLANK('Regional allocations LIVE'!$R$2:$R$1047) + ('Regional allocations LIVE'!$R$2:$R$1047 >= AI$4)) * (ISNUMBER('Regional allocations LIVE'!$D$2:$D$1047)) * ('Regional allocations LIVE'!$D$2:$D$1047 <= AI$4) )} -> 29 | AI66: {=SUMPRODUCT( ('Regional allocations LIVE'!$H$2:$H$1047 = $O52) * (ISBLANK('Regional allocations LIVE'!$R$2:$R$1047) + ('Regional allocations LIVE'!$R$2:$R$1047 >= AJ$4)) * (ISNUMBER('Regional allocations LIVE'!$D$2:$D$1047)) * ('Regional allocations LIVE'!$D$2:$D$1047 <= AJ$4) )} -> 34 | AJ66: {=SUMPRODUCT( ('Regional allocations LIVE'!$H$2:$H$1047 = $O52) * (ISBLANK('Regional allocations LIVE'!$R$2:$R$1047) + ('Regional allocations LIVE'!$R$2:$R$1047 >= AK$4)) * (ISNUMBER('Regional allocations LIVE'!$D$2:$D$1047)) * ('Regional allocations LIVE'!$D$2:$D$1047 <= AK$4) )} -> 36 | AK66: {=SUMPRODUCT( ('Regional allocations LIVE'!$H$2:$H$1047 = $O52) * (ISBLANK('Regional allocations LIVE'!$R$2:$R$1047) + ('Regional allocations LIVE'!$R$2:$R$1047 >= AL$4)) * (ISNUMBER('Regional allocations LIVE'!$D$2:$D$1047)) * ('Regional allocations LIVE'!$D$2:$D$1047 <= AL$4) )} -> 36 | AL66: {=SUMPRODUCT( ('Regional allocations LIVE'!$H$2:$H$1047 = $O52) * (ISBLANK('Regional allocations LIVE'!$R$2:$R$1047) + ('Regional allocations LIVE'!$R$2:$R$1047 >= AM$4)) * (ISNUMBER('Regional allocations LIVE'!$D$2:$D$1047)) * ('Regional allocations LIVE'!$D$2:$D$1047 <= AM$4) )} -> 36 | AM66: {=SUMPRODUCT( ('Regional allocations LIVE'!$H$2:$H$1047 = $O52) * (ISBLANK('Regional allocations LIVE'!$R$2:$R$1047) + ('Regional allocations LIVE'!$R$2:$R$1047 >= AN$4)) * (ISNUMBER('Regional allocations LIVE'!$D$2:$D$1047)) * ('Regional allocations LIVE'!$D$2:$D$1047 <= AN$4) )} -> 36 | AN66: {=SUMPRODUCT( ('Regional allocations LIVE'!$H$2:$H$1047 = $O52) * (ISBLANK('Regional allocations LIVE'!$R$2:$R$1047) + ('Regional allocations LIVE'!$R$2:$R$1047 >= AO$4)) * (ISNUMBER('Regional allocations LIVE'!$D$2:$D$1047)) * ('Regional allocations LIVE'!$D$2:$D$1047 <= AO$4) )} -> 36 | ... BD66: {=SUMPRODUCT( ('Regional allocations LIVE'!$H$2:$H$1047 = $O52) * (ISBLANK('Regional allocations LIVE'!$R$2:$R$1047) + ('Regional allocations LIVE'!$R$2:$R$1047 >= BE$4)) * (ISNUMBER('Regional allocations LIVE'!$D$2:$D$1047)) * ('Regional allocations LIVE'!$D$2:$D$1047 <= BE$4) )} -> 36
B67: Grand Total | C67: 7 | D67: 9 | E67: 140 | F67: 10 | G67: 8 | H67: 174 | Q67: Sales | AG67: {=SUMPRODUCT( ('Regional allocations LIVE'!$H$2:$H$1047 = $O53) * (ISBLANK('Regional allocations LIVE'!$R$2:$R$1047) + ('Regional allocations LIVE'!$R$2:$R$1047 >= AH$4)) * (ISNUMBER('Regional allocations LIVE'!$D$2:$D$1047)) * ('Regional allocations LIVE'!$D$2:$D$1047 <= AH$4) )} -> 5 | AH67: {=SUMPRODUCT( ('Regional allocations LIVE'!$H$2:$H$1047 = $O53) * (ISBLANK('Regional allocations LIVE'!$R$2:$R$1047) + ('Regional allocations LIVE'!$R$2:$R$1047 >= AI$4)) * (ISNUMBER('Regional allocations LIVE'!$D$2:$D$1047)) * ('Regional allocations LIVE'!$D$2:$D$1047 <= AI$4) )} -> 5 | AI67: {=SUMPRODUCT( ('Regional allocations LIVE'!$H$2:$H$1047 = $O53) * (ISBLANK('Regional allocations LIVE'!$R$2:$R$1047) + ('Regional allocations LIVE'!$R$2:$R$1047 >= AJ$4)) * (ISNUMBER('Regional allocations LIVE'!$D$2:$D$1047)) * ('Regional allocations LIVE'!$D$2:$D$1047 <= AJ$4) )} -> 5 | AJ67: {=SUMPRODUCT( ('Regional allocations LIVE'!$H$2:$H$1047 = $O53) * (ISBLANK('Regional allocations LIVE'!$R$2:$R$1047) + ('Regional allocations LIVE'!$R$2:$R$1047 >= AK$4)) * (ISNUMBER('Regional allocations LIVE'!$D$2:$D$1047)) * ('Regional allocations LIVE'!$D$2:$D$1047 <= AK$4) )} -> 5 | AK67: {=SUMPRODUCT( ('Regional allocations LIVE'!$H$2:$H$1047 = $O53) * (ISBLANK('Regional allocations LIVE'!$R$2:$R$1047) + ('Regional allocations LIVE'!$R$2:$R$1047 >= AL$4)) * (ISNUMBER('Regional allocations LIVE'!$D$2:$D$1047)) * ('Regional allocations LIVE'!$D$2:$D$1047 <= AL$4) )} -> 5 | AL67: {=SUMPRODUCT( ('Regional allocations LIVE'!$H$2:$H$1047 = $O53) * (ISBLANK('Regional allocations LIVE'!$R$2:$R$1047) + ('Regional allocations LIVE'!$R$2:$R$1047 >= AM$4)) * (ISNUMBER('Regional allocations LIVE'!$D$2:$D$1047)) * ('Regional allocations LIVE'!$D$2:$D$1047 <= AM$4) )} -> 5 | AM67: {=SUMPRODUCT( ('Regional allocations LIVE'!$H$2:$H$1047 = $O53) * (ISBLANK('Regional allocations LIVE'!$R$2:$R$1047) + ('Regional allocations LIVE'!$R$2:$R$1047 >= AN$4)) * (ISNUMBER('Regional allocations LIVE'!$D$2:$D$1047)) * ('Regional allocations LIVE'!$D$2:$D$1047 <= AN$4) )} -> 5 | AN67: {=SUMPRODUCT( ('Regional allocations LIVE'!$H$2:$H$1047 = $O53) * (ISBLANK('Regional allocations LIVE'!$R$2:$R$1047) + ('Regional allocations LIVE'!$R$2:$R$1047 >= AO$4)) * (ISNUMBER('Regional allocations LIVE'!$D$2:$D$1047)) * ('Regional allocations LIVE'!$D$2:$D$1047 <= AO$4) )} -> 5 | ... BD67: {=SUMPRODUCT( ('Regional allocations LIVE'!$H$2:$H$1047 = $O53) * (ISBLANK('Regional allocations LIVE'!$R$2:$R$1047) + ('Regional allocations LIVE'!$R$2:$R$1047 >= BE$4)) * (ISNUMBER('Regional allocations LIVE'!$D$2:$D$1047)) * ('Regional allocations LIVE'!$D$2:$D$1047 <= BE$4) )} -> 5
Q68: Shared Services | AG68: {=SUMPRODUCT( ('Regional allocations LIVE'!$H$2:$H$1047 = $O54) * (ISBLANK('Regional allocations LIVE'!$R$2:$R$1047) + ('Regional allocations LIVE'!$R$2:$R$1047 >= AH$4)) * (ISNUMBER('Regional allocations LIVE'!$D$2:$D$1047)) * ('Regional allocations LIVE'!$D$2:$D$1047 <= AH$4) )} -> 15 | AH68: {=SUMPRODUCT( ('Regional allocations LIVE'!$H$2:$H$1047 = $O54) * (ISBLANK('Regional allocations LIVE'!$R$2:$R$1047) + ('Regional allocations LIVE'!$R$2:$R$1047 >= AI$4)) * (ISNUMBER('Regional allocations LIVE'!$D$2:$D$1047)) * ('Regional allocations LIVE'!$D$2:$D$1047 <= AI$4) )} -> 15 | AI68: {=SUMPRODUCT( ('Regional allocations LIVE'!$H$2:$H$1047 = $O54) * (ISBLANK('Regional allocations LIVE'!$R$2:$R$1047) + ('Regional allocations LIVE'!$R$2:$R$1047 >= AJ$4)) * (ISNUMBER('Regional allocations LIVE'!$D$2:$D$1047)) * ('Regional allocations LIVE'!$D$2:$D$1047 <= AJ$4) )} -> 16 | AJ68: {=SUMPRODUCT( ('Regional allocations LIVE'!$H$2:$H$1047 = $O54) * (ISBLANK('Regional allocations LIVE'!$R$2:$R$1047) + ('Regional allocations LIVE'!$R$2:$R$1047 >= AK$4)) * (ISNUMBER('Regional allocations LIVE'!$D$2:$D$1047)) * ('Regional allocations LIVE'!$D$2:$D$1047 <= AK$4) )} -> 16 | AK68: {=SUMPRODUCT( ('Regional allocations LIVE'!$H$2:$H$1047 = $O54) * (ISBLANK('Regional allocations LIVE'!$R$2:$R$1047) + ('Regional allocations LIVE'!$R$2:$R$1047 >= AL$4)) * (ISNUMBER('Regional allocations LIVE'!$D$2:$D$1047)) * ('Regional allocations LIVE'!$D$2:$D$1047 <= AL$4) )} -> 16 | AL68: {=SUMPRODUCT( ('Regional allocations LIVE'!$H$2:$H$1047 = $O54) * (ISBLANK('Regional allocations LIVE'!$R$2:$R$1047) + ('Regional allocations LIVE'!$R$2:$R$1047 >= AM$4)) * (ISNUMBER('Regional allocations LIVE'!$D$2:$D$1047)) * ('Regional allocations LIVE'!$D$2:$D$1047 <= AM$4) )} -> 16 | AM68: {=SUMPRODUCT( ('Regional allocations LIVE'!$H$2:$H$1047 = $O54) * (ISBLANK('Regional allocations LIVE'!$R$2:$R$1047) + ('Regional allocations LIVE'!$R$2:$R$1047 >= AN$4)) * (ISNUMBER('Regional allocations LIVE'!$D$2:$D$1047)) * ('Regional allocations LIVE'!$D$2:$D$1047 <= AN$4) )} -> 16 | AN68: {=SUMPRODUCT( ('Regional allocations LIVE'!$H$2:$H$1047 = $O54) * (ISBLANK('Regional allocations LIVE'!$R$2:$R$1047) + ('Regional allocations LIVE'!$R$2:$R$1047 >= AO$4)) * (ISNUMBER('Regional allocations LIVE'!$D$2:$D$1047)) * ('Regional allocations LIVE'!$D$2:$D$1047 <= AO$4) )} -> 16 | ... BD68: {=SUMPRODUCT( ('Regional allocations LIVE'!$H$2:$H$1047 = $O54) * (ISBLANK('Regional allocations LIVE'!$R$2:$R$1047) + ('Regional allocations LIVE'!$R$2:$R$1047 >= BE$4)) * (ISNUMBER('Regional allocations LIVE'!$D$2:$D$1047)) * ('Regional allocations LIVE'!$D$2:$D$1047 <= BE$4) )} -> 16
Q69: Europe | AG69: {=SUMPRODUCT( ('Regional allocations LIVE'!$H$2:$H$1047 = $O55) * (ISBLANK('Regional allocations LIVE'!$R$2:$R$1047) + ('Regional allocations LIVE'!$R$2:$R$1047 >= AH$4)) * (ISNUMBER('Regional allocations LIVE'!$D$2:$D$1047)) * ('Regional allocations LIVE'!$D$2:$D$1047 <= AH$4) )} -> 46 | AH69: {=SUMPRODUCT( ('Regional allocations LIVE'!$H$2:$H$1047 = $O55) * (ISBLANK('Regional allocations LIVE'!$R$2:$R$1047) + ('Regional allocations LIVE'!$R$2:$R$1047 >= AI$4)) * (ISNUMBER('Regional allocations LIVE'!$D$2:$D$1047)) * ('Regional allocations LIVE'!$D$2:$D$1047 <= AI$4) )} -> 47 | AI69: {=SUMPRODUCT( ('Regional allocations LIVE'!$H$2:$H$1047 = $O55) * (ISBLANK('Regional allocations LIVE'!$R$2:$R$1047) + ('Regional allocations LIVE'!$R$2:$R$1047 >= AJ$4)) * (ISNUMBER('Regional allocations LIVE'!$D$2:$D$1047)) * ('Regional allocations LIVE'!$D$2:$D$1047 <= AJ$4) )} -> 46 | AJ69: {=SUMPRODUCT( ('Regional allocations LIVE'!$H$2:$H$1047 = $O55) * (ISBLANK('Regional allocations LIVE'!$R$2:$R$1047) + ('Regional allocations LIVE'!$R$2:$R$1047 >= AK$4)) * (ISNUMBER('Regional allocations LIVE'!$D$2:$D$1047)) * ('Regional allocations LIVE'!$D$2:$D$1047 <= AK$4) )} -> 47 | AK69: {=SUMPRODUCT( ('Regional allocations LIVE'!$H$2:$H$1047 = $O55) * (ISBLANK('Regional allocations LIVE'!$R$2:$R$1047) + ('Regional allocations LIVE'!$R$2:$R$1047 >= AL$4)) * (ISNUMBER('Regional allocations LIVE'!$D$2:$D$1047)) * ('Regional allocations LIVE'!$D$2:$D$1047 <= AL$4) )} -> 47 | AL69: {=SUMPRODUCT( ('Regional allocations LIVE'!$H$2:$H$1047 = $O55) * (ISBLANK('Regional allocations LIVE'!$R$2:$R$1047) + ('Regional allocations LIVE'!$R$2:$R$1047 >= AM$4)) * (ISNUMBER('Regional allocations LIVE'!$D$2:$D$1047)) * ('Regional allocations LIVE'!$D$2:$D$1047 <= AM$4) )} -> 48 | AM69: {=SUMPRODUCT( ('Regional allocations LIVE'!$H$2:$H$1047 = $O55) * (ISBLANK('Regional allocations LIVE'!$R$2:$R$1047) + ('Regional allocations LIVE'!$R$2:$R$1047 >= AN$4)) * (ISNUMBER('Regional allocations LIVE'!$D$2:$D$1047)) * ('Regional allocations LIVE'!$D$2:$D$1047 <= AN$4) )} -> 48 | AN69: {=SUMPRODUCT( ('Regional allocations LIVE'!$H$2:$H$1047 = $O55) * (ISBLANK('Regional allocations LIVE'!$R$2:$R$1047) + ('Regional allocations LIVE'!$R$2:$R$1047 >= AO$4)) * (ISNUMBER('Regional allocations LIVE'!$D$2:$D$1047)) * ('Regional allocations LIVE'!$D$2:$D$1047 <= AO$4) )} -> 48 | ... BD69: {=SUMPRODUCT( ('Regional allocations LIVE'!$H$2:$H$1047 = $O55) * (ISBLANK('Regional allocations LIVE'!$R$2:$R$1047) + ('Regional allocations LIVE'!$R$2:$R$1047 >= BE$4)) * (ISNUMBER('Regional allocations LIVE'!$D$2:$D$1047)) * ('Regional allocations LIVE'!$D$2:$D$1047 <= BE$4) )} -> 48
Q70: Asia Pacific | AG70: {=SUMPRODUCT( ('Regional allocations LIVE'!$H$2:$H$1047 = $O56) * (ISBLANK('Regional allocations LIVE'!$R$2:$R$1047) + ('Regional allocations LIVE'!$R$2:$R$1047 >= AH$4)) * (ISNUMBER('Regional allocations LIVE'!$D$2:$D$1047)) * ('Regional allocations LIVE'!$D$2:$D$1047 <= AH$4) )} -> 17 | AH70: {=SUMPRODUCT( ('Regional allocations LIVE'!$H$2:$H$1047 = $O56) * (ISBLANK('Regional allocations LIVE'!$R$2:$R$1047) + ('Regional allocations LIVE'!$R$2:$R$1047 >= AI$4)) * (ISNUMBER('Regional allocations LIVE'!$D$2:$D$1047)) * ('Regional allocations LIVE'!$D$2:$D$1047 <= AI$4) )} -> 17 | AI70: {=SUMPRODUCT( ('Regional allocations LIVE'!$H$2:$H$1047 = $O56) * (ISBLANK('Regional allocations LIVE'!$R$2:$R$1047) + ('Regional allocations LIVE'!$R$2:$R$1047 >= AJ$4)) * (ISNUMBER('Regional allocations LIVE'!$D$2:$D$1047)) * ('Regional allocations LIVE'!$D$2:$D$1047 <= AJ$4) )} -> 17 | AJ70: {=SUMPRODUCT( ('Regional allocations LIVE'!$H$2:$H$1047 = $O56) * (ISBLANK('Regional allocations LIVE'!$R$2:$R$1047) + ('Regional allocations LIVE'!$R$2:$R$1047 >= AK$4)) * (ISNUMBER('Regional allocations LIVE'!$D$2:$D$1047)) * ('Regional allocations LIVE'!$D$2:$D$1047 <= AK$4) )} -> 18 | AK70: {=SUMPRODUCT( ('Regional allocations LIVE'!$H$2:$H$1047 = $O56) * (ISBLANK('Regional allocations LIVE'!$R$2:$R$1047) + ('Regional allocations LIVE'!$R$2:$R$1047 >= AL$4)) * (ISNUMBER('Regional allocations LIVE'!$D$2:$D$1047)) * ('Regional allocations LIVE'!$D$2:$D$1047 <= AL$4) )} -> 18 | AL70: {=SUMPRODUCT( ('Regional allocations LIVE'!$H$2:$H$1047 = $O56) * (ISBLANK('Regional allocations LIVE'!$R$2:$R$1047) + ('Regional allocations LIVE'!$R$2:$R$1047 >= AM$4)) * (ISNUMBER('Regional allocations LIVE'!$D$2:$D$1047)) * ('Regional allocations LIVE'!$D$2:$D$1047 <= AM$4) )} -> 18 | AM70: {=SUMPRODUCT( ('Regional allocations LIVE'!$H$2:$H$1047 = $O56) * (ISBLANK('Regional allocations LIVE'!$R$2:$R$1047) + ('Regional allocations LIVE'!$R$2:$R$1047 >= AN$4)) * (ISNUMBER('Regional allocations LIVE'!$D$2:$D$1047)) * ('Regional allocations LIVE'!$D$2:$D$1047 <= AN$4) )} -> 18 | AN70: {=SUMPRODUCT( ('Regional allocations LIVE'!$H$2:$H$1047 = $O56) * (ISBLANK('Regional allocations LIVE'!$R$2:$R$1047) + ('Regional allocations LIVE'!$R$2:$R$1047 >= AO$4)) * (ISNUMBER('Regional allocations LIVE'!$D$2:$D$1047)) * ('Regional allocations LIVE'!$D$2:$D$1047 <= AO$4) )} -> 18 | ... BD70: {=SUMPRODUCT( ('Regional allocations LIVE'!$H$2:$H$1047 = $O56) * (ISBLANK('Regional allocations LIVE'!$R$2:$R$1047) + ('Regional allocations LIVE'!$R$2:$R$1047 >= BE$4)) * (ISNUMBER('Regional allocations LIVE'!$D$2:$D$1047)) * ('Regional allocations LIVE'!$D$2:$D$1047 <= BE$4) )} -> 18
Q71: ELT | AG71: {=SUMPRODUCT( ('Regional allocations LIVE'!$H$2:$H$1047 = $O57) * (ISBLANK('Regional allocations LIVE'!$R$2:$R$1047) + ('Regional allocations LIVE'!$R$2:$R$1047 >= AH$4)) * (ISNUMBER('Regional allocations LIVE'!$D$2:$D$1047)) * ('Regional allocations LIVE'!$D$2:$D$1047 <= AH$4) )} -> 1 | AH71: {=SUMPRODUCT( ('Regional allocations LIVE'!$H$2:$H$1047 = $O57) * (ISBLANK('Regional allocations LIVE'!$R$2:$R$1047) + ('Regional allocations LIVE'!$R$2:$R$1047 >= AI$4)) * (ISNUMBER('Regional allocations LIVE'!$D$2:$D$1047)) * ('Regional allocations LIVE'!$D$2:$D$1047 <= AI$4) )} -> 1 | AI71: {=SUMPRODUCT( ('Regional allocations LIVE'!$H$2:$H$1047 = $O57) * (ISBLANK('Regional allocations LIVE'!$R$2:$R$1047) + ('Regional allocations LIVE'!$R$2:$R$1047 >= AJ$4)) * (ISNUMBER('Regional allocations LIVE'!$D$2:$D$1047)) * ('Regional allocations LIVE'!$D$2:$D$1047 <= AJ$4) )} -> 1 | AJ71: {=SUMPRODUCT( ('Regional allocations LIVE'!$H$2:$H$1047 = $O57) * (ISBLANK('Regional allocations LIVE'!$R$2:$R$1047) + ('Regional allocations LIVE'!$R$2:$R$1047 >= AK$4)) * (ISNUMBER('Regional allocations LIVE'!$D$2:$D$1047)) * ('Regional allocations LIVE'!$D$2:$D$1047 <= AK$4) )} -> 1 | AK71: {=SUMPRODUCT( ('Regional allocations LIVE'!$H$2:$H$1047 = $O57) * (ISBLANK('Regional allocations LIVE'!$R$2:$R$1047) + ('Regional allocations LIVE'!$R$2:$R$1047 >= AL$4)) * (ISNUMBER('Regional allocations LIVE'!$D$2:$D$1047)) * ('Regional allocations LIVE'!$D$2:$D$1047 <= AL$4) )} -> 1 | AL71: {=SUMPRODUCT( ('Regional allocations LIVE'!$H$2:$H$1047 = $O57) * (ISBLANK('Regional allocations LIVE'!$R$2:$R$1047) + ('Regional allocations LIVE'!$R$2:$R$1047 >= AM$4)) * (ISNUMBER('Regional allocations LIVE'!$D$2:$D$1047)) * ('Regional allocations LIVE'!$D$2:$D$1047 <= AM$4) )} -> 1 | AM71: {=SUMPRODUCT( ('Regional allocations LIVE'!$H$2:$H$1047 = $O57) * (ISBLANK('Regional allocations LIVE'!$R$2:$R$1047) + ('Regional allocations LIVE'!$R$2:$R$1047 >= AN$4)) * (ISNUMBER('Regional allocations LIVE'!$D$2:$D$1047)) * ('Regional allocations LIVE'!$D$2:$D$1047 <= AN$4) )} -> 1 | AN71: {=SUMPRODUCT( ('Regional allocations LIVE'!$H$2:$H$1047 = $O57) * (ISBLANK('Regional allocations LIVE'!$R$2:$R$1047) + ('Regional allocations LIVE'!$R$2:$R$1047 >= AO$4)) * (ISNUMBER('Regional allocations LIVE'!$D$2:$D$1047)) * ('Regional allocations LIVE'!$D$2:$D$1047 <= AO$4) )} -> 1 | ... BD71: {=SUMPRODUCT( ('Regional allocations LIVE'!$H$2:$H$1047 = $O57) * (ISBLANK('Regional allocations LIVE'!$R$2:$R$1047) + ('Regional allocations LIVE'!$R$2:$R$1047 >= BE$4)) * (ISNUMBER('Regional allocations LIVE'!$D$2:$D$1047)) * ('Regional allocations LIVE'!$D$2:$D$1047 <= BE$4) )} -> 1
Q72: Americas | AG72: {=SUMPRODUCT( ('Regional allocations LIVE'!$H$2:$H$1047 = $O58) * (ISBLANK('Regional allocations LIVE'!$R$2:$R$1047) + ('Regional allocations LIVE'!$R$2:$R$1047 >= AH$4)) * (ISNUMBER('Regional allocations LIVE'!$D$2:$D$1047)) * ('Regional allocations LIVE'!$D$2:$D$1047 <= AH$4) )} -> 41 | AH72: {=SUMPRODUCT( ('Regional allocations LIVE'!$H$2:$H$1047 = $O58) * (ISBLANK('Regional allocations LIVE'!$R$2:$R$1047) + ('Regional allocations LIVE'!$R$2:$R$1047 >= AI$4)) * (ISNUMBER('Regional allocations LIVE'!$D$2:$D$1047)) * ('Regional allocations LIVE'!$D$2:$D$1047 <= AI$4) )} -> 40 | AI72: {=SUMPRODUCT( ('Regional allocations LIVE'!$H$2:$H$1047 = $O58) * (ISBLANK('Regional allocations LIVE'!$R$2:$R$1047) + ('Regional allocations LIVE'!$R$2:$R$1047 >= AJ$4)) * (ISNUMBER('Regional allocations LIVE'!$D$2:$D$1047)) * ('Regional allocations LIVE'!$D$2:$D$1047 <= AJ$4) )} -> 38 | AJ72: {=SUMPRODUCT( ('Regional allocations LIVE'!$H$2:$H$1047 = $O58) * (ISBLANK('Regional allocations LIVE'!$R$2:$R$1047) + ('Regional allocations LIVE'!$R$2:$R$1047 >= AK$4)) * (ISNUMBER('Regional allocations LIVE'!$D$2:$D$1047)) * ('Regional allocations LIVE'!$D$2:$D$1047 <= AK$4) )} -> 39 | AK72: {=SUMPRODUCT( ('Regional allocations LIVE'!$H$2:$H$1047 = $O58) * (ISBLANK('Regional allocations LIVE'!$R$2:$R$1047) + ('Regional allocations LIVE'!$R$2:$R$1047 >= AL$4)) * (ISNUMBER('Regional allocations LIVE'!$D$2:$D$1047)) * ('Regional allocations LIVE'!$D$2:$D$1047 <= AL$4) )} -> 39 | AL72: {=SUMPRODUCT( ('Regional allocations LIVE'!$H$2:$H$1047 = $O58) * (ISBLANK('Regional allocations LIVE'!$R$2:$R$1047) + ('Regional allocations LIVE'!$R$2:$R$1047 >= AM$4)) * (ISNUMBER('Regional allocations LIVE'!$D$2:$D$1047)) * ('Regional allocations LIVE'!$D$2:$D$1047 <= AM$4) )} -> 38 | AM72: {=SUMPRODUCT( ('Regional allocations LIVE'!$H$2:$H$1047 = $O58) * (ISBLANK('Regional allocations LIVE'!$R$2:$R$1047) + ('Regional allocations LIVE'!$R$2:$R$1047 >= AN$4)) * (ISNUMBER('Regional allocations LIVE'!$D$2:$D$1047)) * ('Regional allocations LIVE'!$D$2:$D$1047 <= AN$4) )} -> 38 | AN72: {=SUMPRODUCT( ('Regional allocations LIVE'!$H$2:$H$1047 = $O58) * (ISBLANK('Regional allocations LIVE'!$R$2:$R$1047) + ('Regional allocations LIVE'!$R$2:$R$1047 >= AO$4)) * (ISNUMBER('Regional allocations LIVE'!$D$2:$D$1047)) * ('Regional allocations LIVE'!$D$2:$D$1047 <= AO$4) )} -> 38 | ... BD72: {=SUMPRODUCT( ('Regional allocations LIVE'!$H$2:$H$1047 = $O58) * (ISBLANK('Regional allocations LIVE'!$R$2:$R$1047) + ('Regional allocations LIVE'!$R$2:$R$1047 >= BE$4)) * (ISNUMBER('Regional allocations LIVE'!$D$2:$D$1047)) * ('Regional allocations LIVE'!$D$2:$D$1047 <= BE$4) )} -> 38
Q73: Advisory, Data &AI | AG73: {=SUMPRODUCT( ('Regional allocations LIVE'!$H$2:$H$1047 = $O59) * (ISBLANK('Regional allocations LIVE'!$R$2:$R$1047) + ('Regional allocations LIVE'!$R$2:$R$1047 >= AH$4)) * (ISNUMBER('Regional allocations LIVE'!$D$2:$D$1047)) * ('Regional allocations LIVE'!$D$2:$D$1047 <= AH$4) )} -> 8 | AH73: {=SUMPRODUCT( ('Regional allocations LIVE'!$H$2:$H$1047 = $O59) * (ISBLANK('Regional allocations LIVE'!$R$2:$R$1047) + ('Regional allocations LIVE'!$R$2:$R$1047 >= AI$4)) * (ISNUMBER('Regional allocations LIVE'!$D$2:$D$1047)) * ('Regional allocations LIVE'!$D$2:$D$1047 <= AI$4) )} -> 9 | AI73: {=SUMPRODUCT( ('Regional allocations LIVE'!$H$2:$H$1047 = $O59) * (ISBLANK('Regional allocations LIVE'!$R$2:$R$1047) + ('Regional allocations LIVE'!$R$2:$R$1047 >= AJ$4)) * (ISNUMBER('Regional allocations LIVE'!$D$2:$D$1047)) * ('Regional allocations LIVE'!$D$2:$D$1047 <= AJ$4) )} -> 8 | AJ73: {=SUMPRODUCT( ('Regional allocations LIVE'!$H$2:$H$1047 = $O59) * (ISBLANK('Regional allocations LIVE'!$R$2:$R$1047) + ('Regional allocations LIVE'!$R$2:$R$1047 >= AK$4)) * (ISNUMBER('Regional allocations LIVE'!$D$2:$D$1047)) * ('Regional allocations LIVE'!$D$2:$D$1047 <= AK$4) )} -> 8 | AK73: {=SUMPRODUCT( ('Regional allocations LIVE'!$H$2:$H$1047 = $O59) * (ISBLANK('Regional allocations LIVE'!$R$2:$R$1047) + ('Regional allocations LIVE'!$R$2:$R$1047 >= AL$4)) * (ISNUMBER('Regional allocations LIVE'!$D$2:$D$1047)) * ('Regional allocations LIVE'!$D$2:$D$1047 <= AL$4) )} -> 8 | AL73: {=SUMPRODUCT( ('Regional allocations LIVE'!$H$2:$H$1047 = $O59) * (ISBLANK('Regional allocations LIVE'!$R$2:$R$1047) + ('Regional allocations LIVE'!$R$2:$R$1047 >= AM$4)) * (ISNUMBER('Regional allocations LIVE'!$D$2:$D$1047)) * ('Regional allocations LIVE'!$D$2:$D$1047 <= AM$4) )} -> 8 | AM73: {=SUMPRODUCT( ('Regional allocations LIVE'!$H$2:$H$1047 = $O59) * (ISBLANK('Regional allocations LIVE'!$R$2:$R$1047) + ('Regional allocations LIVE'!$R$2:$R$1047 >= AN$4)) * (ISNUMBER('Regional allocations LIVE'!$D$2:$D$1047)) * ('Regional allocations LIVE'!$D$2:$D$1047 <= AN$4) )} -> 8 | AN73: {=SUMPRODUCT( ('Regional allocations LIVE'!$H$2:$H$1047 = $O59) * (ISBLANK('Regional allocations LIVE'!$R$2:$R$1047) + ('Regional allocations LIVE'!$R$2:$R$1047 >= AO$4)) * (ISNUMBER('Regional allocations LIVE'!$D$2:$D$1047)) * ('Regional allocations LIVE'!$D$2:$D$1047 <= AO$4) )} -> 8 | ... BD73: {=SUMPRODUCT( ('Regional allocations LIVE'!$H$2:$H$1047 = $O59) * (ISBLANK('Regional allocations LIVE'!$R$2:$R$1047) + ('Regional allocations LIVE'!$R$2:$R$1047 >= BE$4)) * (ISNUMBER('Regional allocations LIVE'!$D$2:$D$1047)) * ('Regional allocations LIVE'!$D$2:$D$1047 <= BE$4) )} -> 8
Q74: Totals | R74: =SUM(R66:R73) -> 0 | S74: =SUM(S66:S73) -> 0 | T74: =SUM(T66:T72) -> 0 | U74: =SUM(U66:U72) -> 0 | V74: =SUM(V66:V72) -> 0 | W74: =SUM(W66:W72) -> 0 | X74: =SUM(X66:X73) -> 0 | Y74: =SUM(Y66:Y72) -> 0 | Z74: =SUM(Z66:Z72) -> 0 | AA74: =SUM(AA66:AA72) -> 0 | AB74: =SUM(AB66:AB72) -> 0 | AC74: =SUM(AC66:AC72) -> 0 | AD74: =SUM(AD66:AD73) -> 0 | AE74: =SUM(AE66:AE73) -> 0 | AF74: =SUM(AF66:AF73) -> 0 | AG74: =SUM(AG66:AG73) -> 161 | AH74: =SUM(AH66:AH73) -> 163 | AI74: =SUM(AI66:AI73) -> 165 | AJ74: =SUM(AJ66:AJ73) -> 170 | AK74: =SUM(AK66:AK73) -> 170 | ... BC74: =SUM(BC66:BC73) -> 170
Q88: Attrition
Q89: Business Unit | R89: 31/05/2024 | S89: 30/06/2024 | T89: 31/07/2024 | U89: 31/08/2024 | V89: 30/09/2024 | W89: 31/10/2024 | X89: 30/11/2024 | Y89: 31/12/2024 | Z89: 30/01/2025 | AA89: 28/02/2025 | AB89: 31/03/2025 | AC89: 30/04/2025 | AD89: 31/05/2025 | AE89: Jun-25 | AF89: 31/07/2025 | AG89: Aug-25 | AH89: Sept-25
Q90: Engineering | AB90: =SUM(W6:AB6) / AVERAGE(W40:AB40) -> 0.12185215 | AC90: =SUM(X6:AC6) / AVERAGE(X40:AC40) -> 0.073111292 | AD90: =SUM(Y6:AD6) / AVERAGE(Y40:AD40) -> 0.072815534 | AE90: =SUM(Z6:AE6) / AVERAGE(Z40:AE40) -> 0.07252216 | AF90: =SUM(Table14[[30/01/2025]:[30/06/2025]]) / AVERAGE(AA39:AF39) -> #DIV/0!
Q91: Sales | AB91: =SUM(W7:AB7) / AVERAGE(W41:AB41) -> 0 | AC91: =SUM(X7:AC7) / AVERAGE(X41:AC41) -> 0 | AD91: =SUM(Y7:AD7) / AVERAGE(Y41:AD41) -> 0 | AE91: =SUM(Z7:AE7) / AVERAGE(Z41:AE41) -> 0 | AF91: =SUM(Table14[[30/01/2025]:[30/06/2025]]) / AVERAGE(AA40:AF40) -> 0.45930701
Q92: Shared Services | AB92: =SUM(W8:AB8) / AVERAGE(W42:AB42) -> 0.060606061 | AC92: =SUM(X8:AC8) / AVERAGE(X42:AC42) -> 0.12244898 | AD92: =SUM(Y8:AD8) / AVERAGE(Y42:AD42) -> 0.12371134 | AE92: =SUM(Z8:AE8) / AVERAGE(Z42:AE42) -> 0.125 | AF92: =SUM(Table14[[30/01/2025]:[30/06/2025]]) / AVERAGE(AA41:AF41) -> 6.3333333
Q93: Europe | AB93: =SUM(W9:AB9) / AVERAGE(W43:AB43) -> 0.10645848 | AC93: =SUM(X9:AC9) / AVERAGE(X43:AC43) -> 0.10683761 | AD93: =SUM(Y9:AD9) / AVERAGE(Y43:AD43) -> 0.10721944 | AE93: =SUM(Z9:AE9) / AVERAGE(Z43:AE43) -> 0.15228426 | AF93: =SUM(Table14[[30/01/2025]:[30/06/2025]]) / AVERAGE(AA42:AF42) -> 1.1875
Q94: Asia Pacific | AB94: =SUM(W10:AB10) / AVERAGE(W44:AB44) -> 0.14814815 | AC94: =SUM(X10:AC10) / AVERAGE(X44:AC44) -> 0.15062762 | AD94: =SUM(Y10:AD10) / AVERAGE(Y44:AD44) -> 0.15189873 | AE94: =SUM(Z10:AE10) / AVERAGE(Z44:AE44) -> 0.15319149 | AF94: =SUM(Table14[[30/01/2025]:[30/06/2025]]) / AVERAGE(AA43:AF43) -> 0.42097489
Q95: ELT | AB95: =SUM(W11:AB11) / AVERAGE(W45:AB45) -> #DIV/0! | AC95: =SUM(X11:AC11) / AVERAGE(X45:AC45) -> #DIV/0! | AD95: =SUM(Y11:AD11) / AVERAGE(Y45:AD45) -> #DIV/0! | AE95: =SUM(Z11:AE11) / AVERAGE(Z45:AE45) -> #DIV/0! | AF95: =SUM(Table14[[30/01/2025]:[30/06/2025]]) / AVERAGE(AA44:AF44) -> 0.97021277
Q96: Americas | AB96: =SUM(W12:AB12) / AVERAGE(W46:AB46) -> 0 | AC96: =SUM(X12:AC12) / AVERAGE(X46:AC46) -> 0 | AD96: =SUM(Y12:AD12) / AVERAGE(Y46:AD46) -> 0.024390244 | AE96: =SUM(Z12:AE12) / AVERAGE(Z46:AE46) -> 0.073770492 | AF96: =SUM(Table14[[30/01/2025]:[30/06/2025]]) / AVERAGE(AA45:AF45) -> #DIV/0!
Q97: Clever Cloud | AB97: =SUM(W13:AB13) / AVERAGE(#REF!) -> #REF! | AC97: =SUM(X13:AC13) / AVERAGE(#REF!) -> #REF! | AD97: =SUM(Y13:AD13) / AVERAGE(#REF!) -> #REF! | AE97: =SUM(Z13:AE13) / AVERAGE(#REF!) -> #REF! | AF97: =SUM(Table14[[30/01/2025]:[30/06/2025]]) / AVERAGE(AA46:AF46) -> 0.47107438
Q98: Data, AI & Consulting | AF98: =SUM(Table14[[30/01/2025]:[30/06/2025]]) / AVERAGE(AA47:AF47) -> 5.4285714
Q99: Total | AB99: =SUM(Table14[[31/10/2024]:[31/03/2025]]) / AVERAGE(W48:AB48) -> 0.088452088 | AC99: =SUM(Table14[[30/11/2024]:[30/04/2025]]) / AVERAGE(X48:AC48) -> 0.082962963 | AD99: =SUM(Table14[[31/12/2024]:[31/05/2025]]) / AVERAGE(Y48:AD48) -> 0.089241448 | AE99: =SUM(Table14[[30/01/2025]:[30/06/2025]]) / AVERAGE(Z48:AE48) -> 0.11365902 | AF99: =SUM(Table14[[30/01/2025]:[30/06/2025]]) / AVERAGE(AA48:AF48) -> 0.11405703 | AG99: =SUM(Table14[[30/01/2025]:[30/06/2025]]) / AVERAGE(AB48:AG48) -> 0.11394303 | AH99: =SUM(Table14[[30/01/2025]:[30/06/2025]]) / AVERAGE(AC48:AH48) -> 0.11367036

Sheet Role split
A1: Leaving Date | B1: (blank)
A2: Contractor | B2: (blank)
A3: Current Region | B3: (Multiple Items)
A4: Current project/team - primary | B4: (Multiple Items)
A6: Row Labels | B6: Count of Employee ID
A7: Business Analyst | B7: 4 | C7: =GETPIVOTDATA("Employee ID",$A$6,"Vertical","Business Analyst")/$B$17 -> 0.034482759
A8: Consultant | B8: 4 | C8: =GETPIVOTDATA("Employee ID",$A$6,"Vertical","Consultant")/$B$17 -> 0.034482759
A9: Development | B9: 62 | C9: =GETPIVOTDATA("Employee ID",$A$6,"Vertical","Development")/$B$17 -> 0.53448276
A10: Leadership | B10: 3 | C10: =GETPIVOTDATA("Employee ID",$A$6,"Vertical","Business Analyst")/$B$17 -> 0.034482759
A11: Sales | B11: 1 | C11: =GETPIVOTDATA("Employee ID",$A$6,"Vertical","Business Analyst")/$B$17 -> 0.034482759
A12: Testing | B12: 27 | C12: =GETPIVOTDATA("Employee ID",$A$6,"Vertical","Testing")/$B$17 -> 0.23275862
A13: Translator | B13: 1 | C13: =GETPIVOTDATA("Employee ID",$A$6,"Vertical","Business Analyst")/$B$17 -> 0.034482759
A14: (blank) | C14: =GETPIVOTDATA("Employee ID",$A$6,"Vertical","Business Analyst")/$B$17 -> 0.034482759
A15: Delivery Management | B15: 19 | C15: =GETPIVOTDATA("Employee ID",$A$6,"Vertical","Delivery Management")/$B$17 -> 0.1637931
A16: Grand Total | B16: 121 | C16: =GETPIVOTDATA("Employee ID",$A$6,"Vertical","Business Analyst")/$B$17 -> 0.034482759
A17: Total | B17: =GETPIVOTDATA("Employee ID",$A$6,"Vertical","Business Analyst")+GETPIVOTDATA("Employee ID",$A$6,"Vertical","Consultant")+GETPIVOTDATA("Employee ID",$A$6,"Vertical","Development")+GETPIVOTDATA("Employee ID",$A$6,"Vertical","Testing")+GETPIVOTDATA("Employee ID",$A$6,"Vertical","Delivery Management") -> 116 | C17: =C7+C8+C9+C12+C15 -> 1

Sheet Regional allocations LIVE
A1: People allocations
J2: Updated 3/4/25
A3: Employee ID | B3: Surname | C3: First Names | D3: Start | E3: Job Title | F3: Office | G3: Vertical | H3: Current Region | I3: Line manager | J3: Current project/team - primary | K3: Day 1 Region | L3: New alignment - day 90 | M3: Transition date | N3: Transition milestone | O3: Next project | P3: Next project date | Q3: Notes | R3: Leaving Date | S3: Part Time/ Full Time | T3: FTE | U3: Contractor | V3: Gender | W3: Start Time TBC | X3: Timesheet? | Y3: Partial? | Z3: When stoppped/ changed timesheet
A4: 21 | B4: EMPSON | C4: Wayne | D4: 35338 | E4: Principal Technical Consultant, Europe | F4: New Zealand | G4: Development | H4: Europe | I4: Vernon Kay | J4: Europe Region | K4: Europe | S4: FT | T4: 1 | V4: Male | W4: =IF(AND(T4<>"",NOT(ISNUMBER(T4))),"Non-numeric","") | X4: N | Y4: N | Z4: 13089
A5: 60 | B5: MARSHALL | C5: Raymond | D5: 36787 | E5: Vice President Americas | F5: Costa Rica | G5: Leadership | H5: Americas | I5: Vernon Kay | J5: ELT | K5: ELT | R5: 45891 | S5: FT | T5: 1 | V5: Male | W5: =IF(AND(T5<>"",NOT(ISNUMBER(T5))),"Non-numeric","") | X5: Y | Y5: N
A6: 63 | B6: NOBLE | C6: Brent | D6: 36823 | E6: Head of Platform | F6: New Zealand | G6: Leadership | H6: Engineering | I6: Mark Morgan | J6: Platform | K6: Engineering | S6: FT | T6: 1 | V6: Male | W6: =IF(AND(T6<>"",NOT(ISNUMBER(T6))),"Non-numeric","") | X6: N | Y6: N | Z6: 45901
A7: 65 | B7: SHEN | C7: Dongbo | D7: 36842 | E7: Senior Developer | F7: New Zealand | G7: Development | H7: Europe | I7: Tim Claridge | J7: Jersey | K7: Europe | S7: FT | T7: 1 | V7: Male | W7: =IF(AND(T7<>"",NOT(ISNUMBER(T7))),"Non-numeric","") | X7: Y | Y7: N
A8: 87 | B8: MORGAN | C8: Mark | D8: 38202 | E8: Vice President of Engineering | F8: New Zealand | G8: Leadership | H8: Engineering | I8: Vernon Kay | J8: ELT | K8: ELT | S8: FT | T8: 1 | V8: Male | W8: =IF(AND(T8<>"",NOT(ISNUMBER(T8))),"Non-numeric","") | X8: N | Y8: N | Z8: 45901
A9: 98 | B9: O'TOOLE | C9: Tom | D9: 38495 | E9: Senior Developer | F9: New Zealand | G9: Development | H9: Engineering | I9: Brendon Tribe | J9: Platform | K9: Engineering | S9: FT | T9: 1 | V9: Male | W9: =IF(AND(T9<>"",NOT(ISNUMBER(T9))),"Non-numeric","") | X9: Y | Y9: Y | Z9: 45992
A10: 101 | B10: SMITH | C10: Len | D10: 38551 | E10: Senior Project Manager | F10: New Zealand | G10: Delivery Management | H10: Americas | I10: Richard Morrison | J10: Belize | K10: Americas | S10: FT | T10: 1 | V10: Male | W10: =IF(AND(T10<>"",NOT(ISNUMBER(T10))),"Non-numeric","") | X10: Y | Y10: N
A11: 117 | B11: CHATWIN | C11: Bill | D11: 39475 | E11: Managing Director & Head of Sales | F11: New Zealand | G11: Leadership | H11: Sales | I11: Vernon Kay | J11: ELT | K11: ELT | S11: FT | T11: 1 | V11: Male | W11: =IF(AND(T11<>"",NOT(ISNUMBER(T11))),"Non-numeric","") | X11: N | Y11: N | Z11: 45931
A12: 115 | B12: MCCARTHY | C12: Daniel | D12: 39630 | E12: Senior Developer | F12: New Zealand | G12: Development | H12: Engineering | I12: Brendon Tribe | J12: Platform | K12: Asia Pacific | Q12: Seconded to Engineering till 17 October | S12: FT | T12: 1 | V12: Male | W12: =IF(AND(T12<>"",NOT(ISNUMBER(T12))),"Non-numeric","") | X12: Y | Y12: Y | Z12: 45992
A13: 133 | B13: RAVLA | C13: Jayesh | D13: 39958 | E13: Development Manager | F13: New Zealand | G13: Platform - Zephyr | H13: Engineering | I13: Brent Noble | K13: Engineering | R13: 45576 | T13: 1 | V13: Male | W13: =IF(AND(T13<>"",NOT(ISNUMBER(T13))),"Non-numeric","") | X13: Y | Y13: Y | Z13: 45992
A14: 138 | B14: ALDER | C14: Blaire | D14: 40067 | E14: Head of Technical Delivery and Leadership - Europe | F14: New Zealand | G14: Development | H14: Europe | I14: Vernon Kay | J14: Cyprus | K14: Europe | S14: FT | T14: 1 | V14: Male | W14: =IF(AND(T14<>"",NOT(ISNUMBER(T14))),"Non-numeric","") | X14: Y | Y14: N
A15: 154 | B15: WOODMAN | C15: Nicola | D15: 40959 | E15: Head of Architecture, Americas | F15: New Zealand | G15: Development | H15: Americas | I15: Pollob Sharma | J15: Belize | K15: Americas | R15: 46031 | S15: FT | T15: 1 | V15: Female | W15: =IF(AND(T15<>"",NOT(ISNUMBER(T15))),"Non-numeric","") | X15: Y | Y15: N
A16: 153 | B16: GRANT | C16: Jane | D16: 41120 | E16: VP Asia Pacific | F16: New Zealand | G16: Leadership | H16: Asia Pacific | I16: Vernon Kay | J16: ELT | K16: ELT | S16: FT | T16: 1 | V16: Female | W16: =IF(AND(T16<>"",NOT(ISNUMBER(T16))),"Non-numeric","") | X16: N | Y16: N | Z16: 45901
A17: 142 | B17: HARVISON | C17: James | D17: 41171 | E17: Practice Lead, Solutions Design | F17: New Zealand | G17: Development | H17: Engineering | I17: Lauchlan Robertson | J17: Product | K17: Engineering | S17: FT | T17: 1 | V17: Male | W17: =IF(AND(T17<>"",NOT(ISNUMBER(T17))),"Non-numeric","") | X17: Y | Y17: Y | Z17: 45992
A18: 165 | B18: YANG | C18: Wenping | D18: 41390 | E18: Senior Test Analyst | F18: Remote | G18: Testing | H18: Engineering | I18: Calli Bradford | J18: Platform | K18: Engineering | Q18: Remote from Australia | S18: FT | T18: 1 | V18: Male | W18: =IF(AND(T18<>"",NOT(ISNUMBER(T18))),"Non-numeric","") | X18: Y | Y18: Y | Z18: 45992
A19: 200 | B19: FALCONER | C19: Lincoln | D19: 41641 | E19: Director | F19: New Zealand | G19: Leadership | H19: ELT | I19: Vernon Kay | J19: ELT | K19: ELT | Q19: No longer an employee but director only | R19: 45716 | S19: PT | T19: 1 | V19: Male | W19: =IF(AND(T19<>"",NOT(ISNUMBER(T19))),"Non-numeric","") | X19: Y | Y19: N
A20: 211 | B20: RENNELL | C20: Stephen | D20: 41651 | E20: Principal Developer | F20: New Zealand | G20: Development | H20: Americas | I20: Richard Morrison | J20: Belize | K20: Americas | S20: FT | T20: 1 | V20: Male | W20: =IF(AND(T20<>"",NOT(ISNUMBER(T20))),"Non-numeric","") | X20: Y | Y20: N
A21: 197 | B21: PROFFITT | C21: Rebecca | D21: 41652 | E21: Senior Advisor Planning | F21: New Zealand | G21: Planning | H21: Shared Services | I21: Nick Steevens | J21: Portfolio planning & reporting | K21: Finance + People | S21: PT | T21: 0.8 | V21: Female | W21: =IF(AND(T21<>"",NOT(ISNUMBER(T21))),"Non-numeric","") | X21: N | Y21: N | Z21: 45870
A22: 202 | B22: DAWSON | C22: Emma | D22: 41701 | E22: Payroll & Accounts Manager | F22: New Zealand | G22: Finance | H22: Shared Services | I22: Sharleen Thornley | J22: Finance | K22: Finance + People | S22: FT | T22: 1 | V22: Female | W22: =IF(AND(T22<>"",NOT(ISNUMBER(T22))),"Non-numeric","") | X22: N | Y22: N | Z22: 45870
A23: 203 | B23: DUNNING | C23: Chris | D23: 41715 | E23: Senior Developer | F23: New Zealand | G23: Development | H23: Europe | I23: Blaire Alder | J23: Cyprus | K23: Europe | S23: FT | T23: 1 | V23: Male | W23: =IF(AND(T23<>"",NOT(ISNUMBER(T23))),"Non-numeric","") | X23: Y | Y23: N
A24: 274 | B24: WOJTAS | C24: Aidan | D24: 41957 | E24: Head of Technology | F24: New Zealand | G24: Technology | H24: Engineering | I24: Mark Morgan | J24: Technology | K24: Engineering | R24: 45875 | S24: FT | T24: 1 | V24: Male | W24: =IF(AND(T24<>"",NOT(ISNUMBER(T24))),"Non-numeric","") | X24: Y | Y24: Y | Z24: 45992
A25: 190 | B25: CLARIDGE | C25: Tim | D25: 41984 | E25: Practice Lead | F25: New Zealand | G25: Development | H25: Europe | I25: Joe Ede | J25: IOM | K25: Europe | Q25: Move to Jersey from 12 Aug | S25: FT | T25: 1 | V25: Male | W25: =IF(AND(T25<>"",NOT(ISNUMBER(T25))),"Non-numeric","") | X25: Y | Y25: N
A26: 249 | B26: WILLIAMS | C26: Shona | D26: 42377 | E26: Strategic Advisor | F26: NZ Remote | G26: Consultant | H26: Advisory, Data &AI | I26: Evan Wilson | J26: ADAPT | K26: ELT | S26: FT | T26: 1 | V26: Female | W26: =IF(AND(T26<>"",NOT(ISNUMBER(T26))),"Non-numeric","") | X26: N | Y26: Y | Z26: 45962
A27: 245 | B27: TOWNSEND | C27: Cara | D27: 42435 | E27: Engagement Manager | F27: New Zealand | G27: Delivery Management | H27: Americas | I27: Richard Morrison | J27: Guyana | K27: Engineering | M27: Sept | R27: 45982 | S27: FT | T27: 1 | V27: Female | W27: =IF(AND(T27<>"",NOT(ISNUMBER(T27))),"Non-numeric","") | X27: Y | Y27: N
A28: 264 | B28: RENNIE | C28: Craig | D28: 42741 | E28: Senior Developer | F28: New Zealand | G28: Development | H28: Europe | I28: Tim Claridge | J28: IOM | K28: Europe | Q28: Staying Iom 14 Dec on Support | S28: FT | T28: 1 | V28: Male | W28: =IF(AND(T28<>"",NOT(ISNUMBER(T28))),"Non-numeric","") | X28: Y | Y28: N
A29: 265 | B29: MURTAGH | C29: Neil | D29: 42801 | E29: Principal Architect | F29: Remote | G29: Development | H29: Engineering | I29: Brent Noble | J29: Platform | K29: Engineering | Q29: Moved to AUS 21 Aug '24, now fully remote | S29: FT | T29: 1 | V29: Male | W29: =IF(AND(T29<>"",NOT(ISNUMBER(T29))),"Non-numeric","") | X29: Y | Y29: Y | Z29: 45992
A30: 267 | B30: SWANN | C30: Lisa | D30: 43024 | E30: Pricing & Reporting Manager | F30: New Zealand | G30: Planning | H30: Shared Services | I30: Nick Steevens | J30: Portfolio planning & reporting | K30: Finance + People | S30: FT | T30: 1 | V30: Female | W30: =IF(AND(T30<>"",NOT(ISNUMBER(T30))),"Non-numeric","") | X30: N | Y30: N | Z30: 45870
A31: 275 | B31: CAPEWELL | C31: Jonathan (Jono) | D31: 43059 | E31: Business Analyst | F31: NZ Remote | G31: Business Analyst | H31: Europe | I31: Chris Morton | J31: Cyprus | K31: Europe | S31: FT | T31: 1 | V31: Male | W31: =IF(AND(T31<>"",NOT(ISNUMBER(T31))),"Non-numeric","") | X31: Y | Y31: N
A32: 147 | B32: THURSTON | C32: Sharron | D32: 43066 | E32: Principal Advisor/Consulting Practice Manager | F32: NZ Remote | G32: Consultant | H32: Asia Pacific | I32: Jane Grant | J32: Bhutan | K32: Europe | M32: 45537 | S32: FT | T32: 1 | V32: Female | W32: =IF(AND(T32<>"",NOT(ISNUMBER(T32))),"Non-numeric","") | X32: N | Y32: N | Z32: 45901
A33: 290 | B33: MACASKILL | C33: Janet | D33: 43196 | E33: Head of People and Culture | F33: New Zealand | G33: People | H33: Shared Services | I33: Nick Steevens | J33: People | K33: Finance + People | S33: FT | T33: 1 | V33: Female | W33: =IF(AND(T33<>"",NOT(ISNUMBER(T33))),"Non-numeric","") | X33: N | Y33: N | Z33: 45870
A34: 57 | B34: Sanderson | C34: Tom | D34: 43220 | E34: Technical Consultant | F34: Remote | G34: Partners | H34: Clever Cloud | I34: Tom Sanderson | J34: Data Migration | S34: PT | T34: 0.5 | U34: y | V34: Male | W34: =IF(AND(T34<>"",NOT(ISNUMBER(T34))),"Non-numeric","") | X34: Y | Y34: N
